Workbook

Sheet Financial Analysis Memo
A1: Vertical Analysis/Common Sized Income Statement | B1: Divide all the like items by revenue, in come statement. Allows comparison with other companies in the same industry
A2: Horizontal Analysis/Trend Analysis | B2: Move across the income statement, comparing year over year performance
A3: Growth Rates | B3: Looks at historical performance an allows for projection of future performance | D3: Year-over-year; regression analysis; Bottom-up analysis (starting with individual drivers of revenue in the business); Top-down analysis (starting with market size and market share); Other forecasting methods
A4: Profitability Ratios | B4: Income compare to revenue | D4: Gross profit margin; EBITDA margin; EBIT magin; Net Profit margin
A5: Liquidity Ratios | B5: Short term ability to meet obligations | D5: Current ratio; Acid test ratio; Cash ratio; Net working capital
A6: Efficiency Ratios | B6: Balance sheet and ability to generate revenue | D6: Inventory turnover (days in inventor); Accounts receivable turnover (days receivable); Accounts payable turnover (days payable); Asset turnover, Fixed asset turnover, Cash conversion
A7: Leverage Ratios | B7: Shows how much debt is present compared to | D7: Debt to Equity; Debt to EBITDA; EBIT to Interest (Interest Coverage); Dupont analysis (a combination of ratios, often referred to as the pyramid of ratios, including leverage and liquidity analysis)
A8: Cash flow Analysis | B8: Clear picture on how much cash a company is generating | D8: Operating cash flow (OCF); Free cash flow (FCF); Free cash flow to the firm (FCFF); Free cash flow to equity (FCFE)
A9: Rates of Return (ROI) Ratios | B9: Return for an investor | D9: ROE; ROA; ROIC; Dividend yield; Capital gain; Accounting rate of return (ARR); Internal rate of return (IRR)
A10: Valuation Analysis | B10: Cost approach -> Cost to build & Replacement cost; Market approach (relative value) -> Public company comparables & Precedent transactions; DCF -> Forecast future cash flows
A11: Scenario and Sensitivity | B11: Can be layered on top of valuation work. Looks to understand how sensitive the value of a company is relative to changes in operating assumptions. Different scenarios can be used to better understand outcome.
A12: Variance Analysis | B12: Is the process of comparing actual results to budget or forecast

Sheet Vertical Analysis
A1: Cross Sectional Techniques
A2: Vertical Analysis/Common Sized Income Statement
A4: Monster-US
A5: Income Statement ($'000)
B6: FY2025A
A7: Revenue | B7: 8294343
A8: Cost of sales | B8: -3662148
A9: Gross margin | B9: =B8+B7 -> 4632195
A11: Freight-Out Costs | B11: -237000
A12: Advertising and Promotional Expenses | B12: -599900
A13: Other expenses | B13: -1261500
A14: Total Operating Costs | B14: =B13+B12+B11 -> -2098400
A15: EBITDA | B15: =B14+B9 -> 2533795
A17: Depreciation | B17: -114441
A18: EBIT | B18: =B15+B17 -> 2419354
A20: INTEREST AND OTHER INCOME (EXPENSE), NET | B20: 63175
A21: INCOME BEFORE PROVISION FOR INCOME TAXES | B21: =B18+B20 -> 2482529
A23: PROVISION FOR INCOME TAXES | B23: -577097
A24: Tax Rate | B24: 0.23246335
A25: NET INCOME | B25: =B21+B23 -> 1905432
A27: Monster-US
A28: Balance Sheet ($'000) | B28: FY2025A
A29: Current assets
A30: Cash and cash equivalents | B30: 2088117
A31: Short-term investments | B31: 677084
A32: Accounts receivable, net | B32: 1618072
A33: Inventories | B33: 799623
A34: Prepaid expenses and other current assets | B34: 103551
A35: Intangibles held-for-sale | B35: 0
A36: Prepaid Income Taxes | B36: 74637
A37: Deferred income tax | B37: 0
A38: Total current assets | B38: =B37+B34+B33+B32+B31+B30+B36+B35 -> 5361084
A40: Long-term assets
A41: Investments | B41: 48329
A42: Property and equipment, net | B42: 1081544
A43: Deferred Income Taxes | B43: 188646
A44: Intangible assets, net | B44: 1379268
A45: Goodwill | B45: 1331643
A46: Other assets | B46: 159431
A47: Total long-term assets | B47: =B46+B45+B44+B42+B43+B41 -> 4188861
A48: Total assets | B48: =B47+B38 -> 9549945
A50: Current liabilitiies
A51: Short term debt
A52: Accounts payable | B52: 565974
A53: Accrued liabilities | B53: 306085
A54: Accrued distributor terminations | B54: 0
A55: Deferred revenue | B55: 45323
A56: Customer deposit liabilities | B56: 0
A57: Accrued promotional allowances | B57: 384070
A58: Accrued compensation | B58: 114023
A59: Income taxes payable | B59: 32305
A60: Current portion of long-term debt | B60: 0
A61: Total current liabilities | B61: =B51+B60+B59+B57+B53+B52+B56+B54+B55+B58 -> 1447780
A63: Long-term liabilities
A64: Long-term debt | B64: 0
A65: Deferred revenue | B65: 159991
A66: Deferred income taxes | B66: 0
A67: Other Liabilities | B67: 127066
A68: Total long term liabilities | B68: =B65+B64+B66+B67 -> 287057
A69: Total liabilities | B69: =B68+B61 -> 1734837
A71: Equity
A72: Common stock | B72: 5665
A73: Additional paid-in capital | B73: 5430847
A74: Retained earnings / accumulated deficit | B74: 9354216
A75: Accumulated other comprehensive income (loss) | B75: -60841
A76: Treasury stock | B76: -6475779
A77: Total stockholders' equity | B77: =B76+B75+B74+B73+B72 -> 8254108
A78: Total liabilities and stockholders' equity | B78: =B77+B69 -> 9988945
A81: Monster-US
A82: Income Statement ($'000)
B83: FY2025A
A84: Revenue | B84: =B7/B7 -> 1
A85: Gross Profit Ratio | B85: =B9/B7 -> 0.55847642
A86: EBITDA | B86: =B15/B7 -> 0.30548471
A87: EBIT (Operating Profit) Ratio | B87: =B18/B7 -> 0.29168724
A88: Net Profit Ratio | B88: =B25/B7 -> 0.22972669
A90: Tax Ratio | B90: =-B23/B21 -> 0.23246335 | C90: Interest/Pretax Income
A91: Interest Coverage Ratio | B91: =B18/B20 -> 38.296066 | C91: EBIT/Interest expense
A94: Monster-US
A95: Balance Sheet ($'000) | B95: FY2025A
A96: Current assets
A97: Cash and cash equivalents | B97: =B30/$B$48 -> 0.21865225
A98: Short-term investments | B98: =B31/$B$48 -> 0.070899256
A99: Accounts receivable, net | B99: =B32/$B$48 -> 0.1694326
A100: Inventories | B100: =B33/$B$48 -> 0.083730639
A101: Prepaid expenses and other current assets | B101: =B34/$B$48 -> 0.010843099
A102: Intangibles held-for-sale | B102: =B35/$B$48 -> 0
A103: Prepaid Income Taxes | B103: =B36/$B$48 -> 0.0078154377
A104: Deferred income tax | B104: =B37/$B$48 -> 0
A105: Total current assets | B105: =B38/$B$48 -> 0.56137329
A107: Long-term assets
A108: Investments | B108: =B41/$B$48 -> 0.0050606574
A109: Property and equipment, net | B109: =B42/$B$48 -> 0.11325133
A110: Deferred Income Taxes | B110: =B43/$B$48 -> 0.019753622
A111: Intangible assets, net | B111: =B44/$B$48 -> 0.1444268
A112: Goodwill | B112: =B45/$B$48 -> 0.13943986
A113: Other assets | B113: =B46/$B$48 -> 0.016694442
A114: Total long-term assets | B114: =B47/$B$48 -> 0.43862671
A115: Total assets | B115: =B48/$B$48 -> 1
A117: Current liabilitiies
...

Sheet Horizontal Analysis
A1: Cross Sectional Techniques
A2: Horizontal Analysis/Trend Analysis | B2: Move across the income statement, comparing year over year performance (dividing each line item by revenue)
A4: Monster-US
A5: Income Statement ($'000)
B6: 2010 | C6: =B6+1 -> 2011 | D6: =C6+1 -> 2012 | E6: =D6+1 -> 2013 | F6: =E6+1 -> 2014 | G6: =F6+1 -> 2015 | H6: =G6+1 -> 2016 | I6: =H6+1 -> 2017 | J6: =I6+1 -> 2018 | ... N6: =M6+1 -> 2022 | O6: FY2023A | P6: FY2024A | Q6: FY2025A
A7: Net sales | B7: 1303942 | C7: 1703230 | D7: 2060702 | E7: 2246428 | F7: 2464867 | G7: 2722564 | H7: 3049393 | I7: 3369045 | J7: 3807183 | K7: 4200819 | L7: 4598638 | M7: 5541352 | N7: 6311050 | O7: 7140027 | P7: 7492709 | Q7: 8294343
A8: Cost of sales | B8: 623702 | C8: 808921 | D8: 995046 | E8: 1073497 | F8: 1125057 | G8: 1090263 | H8: 1107393 | I8: 1231355 | J8: 1511808 | K8: 1682234 | L8: 1874758 | M8: 2432839 | N8: 3136483 | O8: 3345821 | P8: 3443831 | Q8: 3662148
A9: Gross profit | B9: =B7-B8 -> 680240 | C9: =C7-C8 -> 894309 | D9: =D7-D8 -> 1065656 | E9: =E7-E8 -> 1172931 | F9: =F7-F8 -> 1339810 | G9: =G7-G8 -> 1632301 | H9: =H7-H8 -> 1942000 | I9: =I7-I8 -> 2137690 | ... Q9: =Q7-Q8 -> 4632195
A11: Selling, general and administrative | B11: 0 | C11: 0 | D11: 0 | E11: 0 | F11: 0 | G11: 0 | H11: 0 | I11: 0 | J11: 0 | K11: 0 | L11: 0 | M11: 0 | N11: 0 | O11: 0 | P11: 0 | Q11: 0
A12: Freight-Out-Cots | B12: 47400 | C12: 60500 | D12: 76100 | E12: 84000 | F12: 92700 | G12: 87000 | H12: 83600 | I12: 91900 | J12: 128500 | K12: 122500 | L12: 134100 | M12: 213900 | N12: 249200 | O12: 223600 | P12: 224200 | Q12: 237000
A13: Advertising and Promotional | B13: 104900 | C13: 148800 | D13: 165400 | E13: 181800 | F13: 171500 | G13: 209700 | H13: 270600 | I13: 324000 | J13: 353900 | K13: 391600 | L13: 345700 | M13: 417600 | N13: 460700 | O13: 528900 | P13: 584100 | Q13: 599900
A14: Other Expenses | B14: 180126 | C14: 228586 | D14: 273533 | E14: 334215 | F14: 328105 | G14: 603418 | H14: 502462 | I14: 523003 | J14: 529356 | K14: 601546 | L14: 610927 | M14: 679546 | N14: 879946 | O14: 1088351 | P14: 1310284 | Q14: 1375941
A15: Total Operating expenses | B15: =B14+B13+B12+B11 -> 332426 | C15: =C14+C13+C12+C11 -> 437886 | D15: =D14+D13+D12+D11 -> 515033 | E15: =E14+E13+E12+E11 -> 600015 | F15: =F14+F13+F12+F11 -> 592305 | G15: =G14+G13+G12+G11 -> 900118 | H15: =H14+H13+H12+H11 -> 856662 | I15: =I14+I13+I12+I11 -> 938903 | ... Q15: =Q14+Q13+Q12+Q11 -> 2212841
A16: Operating income (loss) | B16: =B9-B15 -> 347814 | C16: =C9-C15 -> 456423 | D16: =D9-D15 -> 550623 | E16: =E9-E15 -> 572916 | F16: =F9-F15 -> 747505 | G16: =G9-G15 -> 732183 | H16: =H9-H15 -> 1085338 | I16: =I9-I15 -> 1198787 | ... Q16: =Q9-Q15 -> 2419354
A18: Interest income | B18: 0 | C18: 0 | D18: 0 | E18: 0 | F18: 0 | G18: 0 | H18: 0 | I18: 0 | J18: 0 | K18: 0 | L18: 0 | M18: 0 | N18: 0 | O18: 0 | P18: 0 | Q18: 0
A19: Interest expense | B19: 0 | C19: 0 | D19: 0 | E19: 0 | F19: 0 | G19: 0 | H19: 0 | I19: 0 | J19: 0 | K19: 0 | L19: 0 | M19: 0 | N19: 0 | O19: 0 | P19: 0 | Q19: 0
A20: Other income (expense), net | B20: 0 | C20: 0 | D20: 0 | E20: 0 | F20: 0 | G20: -2105 | H20: -5653 | I20: 2836 | J20: 9653 | K20: 13023 | L20: -6996 | M20: 3952 | N20: -12757 | O20: 115127 | P20: 59165 | Q20: 63175
A21: Income before income taxes | B21: =B16-B19+B18-B20 -> 347814 | C21: =C16-C19+C18-C20 -> 456423 | D21: =D16-D19+D18-D20 -> 550623 | E21: =E16-E19+E18-E20 -> 572916 | F21: =F16-F19+F18-F20 -> 747505 | G21: =G16-G19+G18-G20 -> 734288 | H21: =H16-H19+H18-H20 -> 1090991 | I21: =I16-I19+I18-I20 -> 1195951 | ... Q21: =Q16-Q19+Q18-Q20 -> 2356179
A23: Provision for income taxes | B23: 137273 | C23: 171051 | D23: 209134 | E23: 225233 | F23: 262603 | G23: 344815 | H23: 367000 | I23: 380945 | J23: 300268 | K23: 308127 | L23: 216563 | M23: 423944 | N23: 380340 | O23: 437494 | P23: 480411 | Q23: 577097
A24: Net income (loss) | B24: =B21-B23 -> 210541 | C24: =C21-C23 -> 285372 | D24: =D21-D23 -> 341489 | E24: =E21-E23 -> 347683 | F24: =F21-F23 -> 484902 | G24: =G21-G23 -> 389473 | H24: =H21-H23 -> 723991 | I24: =I21-I23 -> 815006 | ... Q24: =Q21-Q23 -> 1779082
A26: Monster-US
A27: Balance Sheet ($'000)
B28: 2010 | C28: =B28+1 -> 2011 | D28: =C28+1 -> 2012 | E28: =D28+1 -> 2013 | F28: =E28+1 -> 2014 | G28: =F28+1 -> 2015 | H28: =G28+1 -> 2016 | I28: =H28+1 -> 2017 | J28: =I28+1 -> 2018 | ... N28: =M28+1 -> 2022 | O28: 2023 | P28: =O28+1 -> 2024 | Q28: =P28+1 -> 2025
A29: Current assets
A30: Cash and cash equivalents | B30: 354842 | C30: 359331 | D30: 222514 | E30: 211349 | F30: 370323 | G30: 2175417 | H30: 377582 | I30: 528622 | J30: 637513 | K30: 797957 | L30: 1180413 | M30: 1326462 | N30: 1307141 | O30: 2297675 | P30: 1533287 | Q30: 2088117
A31: Short-term investments | B31: 244649 | C31: 411282 | D31: 97042 | E31: 402247 | F31: 781134 | G31: 744610 | H31: 220554 | I31: 672933 | J31: 320650 | K31: 533063 | L31: 881354 | M31: 1749727 | N31: 1362314 | O31: 955605 | P31: 0 | Q31: 677084
A32: Accounts receivable, net | B32: 101635 | C32: 218741 | D32: 236710 | E32: =291638+4542 -> 296180 | F32: =280203+552 -> 280755 | G32: =352955+125000 -> 477955 | H32: =448051+125000 -> 573051 | I32: 449476 | J32: 484562 | K32: 540330 | L32: 666012 | M32: 896658 | N32: 1016203 | O32: 1193964 | P32: 1221646 | Q32: 1618072
A33: Inventories | B33: 153241 | C33: 155613 | D33: 203106 | E33: 221449 | F33: 174573 | G33: 156121 | H33: 161971 | I33: 255745 | J33: 277705 | K33: 360731 | L33: 333085 | M33: 593357 | N33: 935631 | O33: 971406 | P33: 737107 | Q33: 799623
A34: Prepaid expenses and other current assets | B34: 17022 | C34: 20912 | D34: 24983 | E34: 21376 | F34: 19673 | G34: 26967 | H34: 32562 | I34: 40877 | J34: 44909 | K34: 54868 | L34: 55358 | M34: 82668 | N34: 109823 | O34: 116195 | P34: 107262 | Q34: 103551
A35: Intangibles held-for-sale | E35: 0 | F35: 18079 | G35: 0 | H35: 0
A36: Prepaid Income Taxes | B36: 9992 | C36: 370 | D36: 33709 | E36: 9518 | F36: 8617 | G36: 18462 | H36: 66550 | I36: 138724 | J36: 38831 | L36: 24733 | M36: 33238 | N36: 33785 | O36: 54151 | P36: 42202 | Q36: 74637
A37: Deferred income tax | B37: 16772 | C37: 16428 | D37: 17004 | E37: 20924 | F37: 40275 | G37: 0 | H37: 0
A38: Total current assets | B38: =B37+B34+B33+B32+B31+B30+B36+B35 -> 898153 | C38: =C37+C34+C33+C32+C31+C30+C36+C35 -> 1182677 | D38: =D37+D34+D33+D32+D31+D30+D36+D35 -> 835068 | E38: =E37+E34+E33+E32+E31+E30+E36+E35 -> 1183043 | F38: =F37+F34+F33+F32+F31+F30+F36+F35 -> 1693429 | G38: =G37+G34+G33+G32+G31+G30+G36+G35 -> 3599532 | H38: =H37+H34+H33+H32+H31+H30+H36+H35 -> 1432270 | I38: =I37+I34+I33+I32+I31+I30+I36+I35 -> 2086377 | ... Q38: =Q37+Q34+Q33+Q32+Q31+Q30+Q36+Q35 -> 5361084
A40: Long-term assets
A41: Investments | B41: 44189 | C41: 23194 | D41: 21393 | E41: 9792 | F41: 42940 | G41: 15348 | H41: 2394 | I41: 2366 | L41: 44291 | M41: 99419 | N41: 61443 | O41: 76431 | P41: 0 | Q41: 48329
A42: Property and equipment, net | B42: 34551 | C42: 45151 | D42: 69137 | E42: 88143 | F42: 90156 | G42: 97354 | H42: 173343 | I42: 230276 | J42: 243051 | K42: 298640 | L42: 314656 | M42: 313753 | N42: 516897 | O42: 890796 | P42: 1047024 | Q42: 1081544
A43: Deferred Income Taxes | B43: 58475 | C43: 58576 | D43: 59503 | E43: 63611 | F43: 54106 | G43: 140468 | H43: 159556 | I43: 92333 | J43: 85687 | L43: 241650 | M43: 225221 | N43: 177039 | O43: 175003 | P43: 184260 | Q43: 188646
A44: Intangible assets, net | B44: 43316 | C44: 48396 | D44: 54648 | E44: 65774 | F44: 50748 | G44: 427986 | H44: 1032635 | I44: 1034085 | J44: 1045878 | K44: 1052105 | L44: 1059046 | M44: 1072386 | N44: 1220410 | O44: 1427139 | P44: 1414252 | Q44: 1379268
A45: Goodwill | B45: 0 | C45: 0 | D45: 0 | E45: 0 | F45: 0 | G45: 1279715 | H45: 1331643 | I45: 1331643 | J45: 1331643 | K45: 1331643 | L45: 1331643 | M45: 1331643 | N45: 1417941 | O45: 1417941 | P45: 1331643 | Q45: 1331643
A46: Other assets | B46: 3447 | C46: 4405 | D46: 3576 | E46: 10146 | F46: 7496 | G46: 10874 | H46: 21630 | I46: 13932 | J46: 16462 | K46: 53973 | L46: 70475 | M46: 80252 | N46: 134478 | O46: 110216 | P46: 100406 | Q46: 159431
A47: Total long-term assets | B47: =B46+B45+B44+B42+B43+B41 -> 183978 | C47: =C46+C45+C44+C42+C43+C41 -> 179722 | D47: =D46+D45+D44+D42+D43+D41 -> 208257 | E47: =E46+E45+E44+E42+E43+E41 -> 237466 | F47: =F46+F45+F44+F42+F43+F41 -> 245446 | G47: =G46+G45+G44+G42+G43+G41 -> 1971745 | H47: =H46+H45+H44+H42+H43+H41 -> 2721201 | I47: =I46+I45+I44+I42+I43+I41 -> 2704635 | ... Q47: =Q46+Q45+Q44+Q42+Q43+Q41 -> 4188861
A48: Total assets | B48: =B47+B38 -> 1082131 | C48: =C47+C38 -> 1362399 | D48: =D47+D38 -> 1043325 | E48: =E47+E38 -> 1420509 | F48: =F47+F38 -> 1938875 | G48: =G47+G38 -> 5571277 | H48: =H47+H38 -> 4153471 | I48: =I47+I38 -> 4791012 | ... Q48: =Q47+Q38 -> 9549945
A50: Current liabilitiies
A51: Short term debt
A52: Accounts payable | B52: 85674 | C52: 113446 | D52: 127330 | E52: 119376 | F52: 127641 | G52: 144763 | H52: 193270 | I52: 245910 | J52: 248760 | K52: 274045 | L52: 296800 | M52: 404263 | N52: 444265 | O52: 564379 | P52: 466775 | Q52: 565974
A53: Accrued liabilities | B53: 23811 | C53: 31966 | D53: 38916 | E53: 59113 | F53: 40271 | G53: 81786 | H53: 79526 | I53: 87475 | J53: 112507 | K53: 114075 | L53: 142653 | M53: 210964 | N53: 172991 | O53: 183988 | P53: 220764 | Q53: 306085
A54: Accrued distributor terminations | B54: 407 | G54: 11018 | H54: 8184 | I54: 91 | J54: 0
A55: Deferred revenue | B55: 10140 | C55: 11583 | D55: 12695 | E55: 13832 | F55: 49926 | G55: 32271 | H55: 41672 | I55: 43236 | J55: 44045 | L55: 45429 | M55: 42530 | N55: 43311 | O55: 41914 | P55: 45809 | Q55: 45323
A56: Customer deposit liabilities
A57: Accrued promotional allowances | B57: 0 | C57: 87746 | D57: 91208 | E57: 99470 | F57: 114047 | G57: 115530 | H57: 110237 | I57: 137998 | J57: 145741 | K57: 166761 | L57: 186658 | M57: 211461 | N57: 255631 | O57: 269061 | P57: 267711 | Q57: 384070
A58: Accrued compensation | B58: 7603 | C58: 10353 | D58: 12926 | E58: 14864 | F58: 17983 | G58: 22159 | H58: 30043 | I58: 34996 | J58: 39903 | L58: 55015 | M58: 65459 | N58: 72463 | O58: 87392 | P58: 92454 | Q58: 114023
A59: Income taxes payable | B59: 925 | C59: 10996 | D59: 5470 | E59: 9359 | F59: 5848 | G59: 2750 | H59: 7657 | I59: 10645 | J59: 10189 | K59: 14717 | L59: 23433 | M59: 30399 | N59: 13317 | O59: 14955 | P59: 4006 | Q59: 32305
A60: Current portion of long-term debt | B60: 274 | C60: 0 | D60: 0
A61: Total current liabilities | B61: =B51+B60+B59+B57+B53+B52+B56+B54+B55+B58 -> 128834 | C61: =C51+C60+C59+C57+C53+C52+C56+C54+C55+C58 -> 266090 | D61: =D51+D60+D59+D57+D53+D52+D56+D54+D55+D58 -> 288545 | E61: =E51+E60+E59+E57+E53+E52+E56+E54+E55+E58 -> 316014 | F61: =F51+F60+F59+F57+F53+F52+F56+F54+F55+F58 -> 355716 | G61: =G51+G60+G59+G57+G53+G52+G56+G54+G55+G58 -> 410277 | H61: =H51+H60+H59+H57+H53+H52+H56+H54+H55+H58 -> 470589 | I61: =I51+I60+I59+I57+I53+I52+I56+I54+I55+I58 -> 560351 | ... Q61: =Q51+Q60+Q59+Q57+Q53+Q52+Q56+Q54+Q55+Q58 -> 1447780
A63: Long-term liabilities
A64: Long-term debt | P64: 373951 | Q64: 0
A65: Deferred revenue | B65: 124899 | C65: 117151 | D65: 110383 | E65: 112216 | F65: 68009 | G65: 351590 | H65: 353173 | I65: 334354 | J65: 312224 | K65: 287469 | L65: 264436 | M65: 243249 | N65: 223800 | O65: 204251 | P65: 179008 | Q65: 159991
A66: Deferred income taxes | B66: 0 | C66: 0 | D66: 0 | E66: 0 | F66: 0 | G66: 0 | H66: 0
A67: Other Liabilities | I67: 1095 | J67: 2621 | L67: 27432 | M67: 29508 | N67: 42286 | O67: 91838 | P67: 110893 | Q67: 127066
A68: Total long term liabilities | B68: =B65+B64+B66+B67 -> 124899 | C68: =C65+C64+C66+C67 -> 117151 | D68: =D65+D64+D66+D67 -> 110383 | E68: =E65+E64+E66+E67 -> 112216 | F68: =F65+F64+F66+F67 -> 68009 | G68: =G65+G64+G66+G67 -> 351590 | H68: =H65+H64+H66+H67 -> 353173 | I68: =I65+I64+I66+I67 -> 335449 | ... Q68: =Q65+Q64+Q66+Q67 -> 287057
A69: Total liabilities | B69: =B68+B61 -> 253733 | C69: =C68+C61 -> 383241 | D69: =D68+D61 -> 398928 | E69: =E68+E61 -> 428230 | F69: =F68+F61 -> 423725 | G69: =G68+G61 -> 761867 | H69: =H68+H61 -> 823762 | I69: =I68+I61 -> 895800 | ... Q69: =Q68+Q61 -> 1734837
A71: Equity
A72: Common stock | B72: 494 | C72: 994 | D72: 1019 | E72: 1030 | F72: 1035 | G72: 3105 | H72: 3116 | I72: 3146 | J72: 3155 | K72: 3182 | L72: 3193 | M72: 3200 | N72: 6418 | O72: 5613 | P72: 5632 | Q72: 5665
A73: Additional paid-in capital | B73: 187040 | C73: 229301 | D73: 287953 | E73: 368069 | F73: 426145 | G73: 3989787 | H73: 4051245 | I73: 4150628 | J73: 4238170 | K73: 4397511 | L73: 4537982 | M73: 4652620 | N73: 4776804 | O73: 4975115 | P73: 5144922 | Q73: 5430847
A74: Retained earnings / accumulated deficit | B74: 882425 | C74: 1168644 | D74: 1508664 | E74: 1847325 | F74: 2330510 | G74: 1394863 | H74: 2107548 | I74: 2928226 | J74: 3914645 | K74: 5022480 | L74: 6432074 | M74: 7809549 | N74: 9001173 | O74: 5939736 | P74: 7448784 | Q74: 9354216
A75: Accumulated other comprehensive income (loss) | B75: 281 | C75: -1547 | D75: 2074 | E75: -1233 | F75: -11453 | G75: -21878 | H75: -23249 | I75: -16659 | J75: -32864 | K75: -32387 | L75: 3034 | M75: -69165 | N75: -159073 | O75: -125337 | P75: -269487 | Q75: -60841
A76: Treasury stock | B76: -241842 | C76: -418234 | D76: -1155313 | E76: -1222912 | F76: -1231087 | G76: -556467 | H76: -2808951 | I76: -3170129 | J76: -4512205 | K76: -5219505 | L76: -5815423 | M76: -5829253 | N76: -6600281 | O76: -2566383 | P76: -6372133 | Q76: -6475779
A77: Total stockholders' equity | B77: =B76+B75+B74+B73+B72 -> 828398 | C77: =C76+C75+C74+C73+C72 -> 979158 | D77: =D76+D75+D74+D73+D72 -> 644397 | E77: =E76+E75+E74+E73+E72 -> 992279 | F77: =F76+F75+F74+F73+F72 -> 1515150 | G77: =G76+G75+G74+G73+G72 -> 4809410 | H77: =H76+H75+H74+H73+H72 -> 3329709 | I77: =I76+I75+I74+I73+I72 -> 3895212 | ... Q77: =Q76+Q75+Q74+Q73+Q72 -> 8254108
A78: Total liabilities and stockholders' equity | B78: =B77+B69 -> 1082131 | C78: =C77+C69 -> 1362399 | D78: =D77+D69 -> 1043325 | E78: =E77+E69 -> 1420509 | F78: =F77+F69 -> 1938875 | G78: =G77+G69 -> 5571277 | H78: =H77+H69 -> 4153471 | I78: =I77+I69 -> 4791012 | ... Q78: =Q77+Q69 -> 9988945
A81: Vertical anlysis | B81: 2010 | C81: =B81+1 -> 2011 | D81: =C81+1 -> 2012 | E81: =D81+1 -> 2013 | F81: =E81+1 -> 2014 | G81: =F81+1 -> 2015 | H81: =G81+1 -> 2016 | I81: =H81+1 -> 2017 | J81: =I81+1 -> 2018 | ... N81: =M81+1 -> 2022 | O81: FY2023A | P81: FY2024A | Q81: FY2025A
A82: Net sales | C82: =C7/B7-1 -> 0.30621607 | D82: =D7/C7-1 -> 0.20987888 | E82: =E7/D7-1 -> 0.090127539 | F82: =F7/E7-1 -> 0.097238371 | G82: =G7/F7-1 -> 0.10454803 | H82: =H7/G7-1 -> 0.12004456 | I82: =I7/H7-1 -> 0.1048248 | J82: =J7/I7-1 -> 0.13004813 | ... Q82: =Q7/P7-1 -> 0.10698854
A83: Cost of sales | C83: =C8/B8-1 -> 0.29696714 | D83: =D8/C8-1 -> 0.23009045 | E83: =E8/D8-1 -> 0.078841581 | F83: =F8/E8-1 -> 0.048029943 | G83: =G8/F8-1 -> -0.030926433 | H83: =H8/G8-1 -> 0.015711805 | I83: =I8/H8-1 -> 0.11194039 | J83: =J8/I8-1 -> 0.22775966 | ... Q83: =Q8/P8-1 -> 0.063393645
A84: Gross profit | C84: =C9/B9-1 -> 0.31469628 | D84: =D9/C9-1 -> 0.19159709 | E84: =E9/D9-1 -> 0.10066569 | F84: =F9/E9-1 -> 0.14227521 | G84: =G9/F9-1 -> 0.21830782 | H84: =H9/G9-1 -> 0.18973155 | I84: =I9/H9-1 -> 0.10076725 | J84: =J9/I9-1 -> 0.073764203 | ... Q84: =Q9/P9-1 -> 0.1440688
A86: Selling, general and administrative
A87: Freight-Out-Cots | C87: =C12/B12-1 -> 0.27637131 | D87: =D12/C12-1 -> 0.25785124 | E87: =E12/D12-1 -> 0.10381078 | F87: =F12/E12-1 -> 0.10357143 | G87: =G12/F12-1 -> -0.061488673 | H87: =H12/G12-1 -> -0.03908046 | I87: =I12/H12-1 -> 0.099282297 | J87: =J12/I12-1 -> 0.39825898 | ... Q87: =Q12/P12-1 -> 0.057091882
A88: Advertising and Promotional | C88: =C13/B13-1 -> 0.4184938 | D88: =D13/C13-1 -> 0.11155914 | E88: =E13/D13-1 -> 0.099153567 | F88: =F13/E13-1 -> -0.056655666 | G88: =G13/F13-1 -> 0.22274052 | H88: =H13/G13-1 -> 0.29041488 | I88: =I13/H13-1 -> 0.19733925 | J88: =J13/I13-1 -> 0.092283951 | ... Q88: =Q13/P13-1 -> 0.027050163
A89: Other Expenses | C89: =C14/B14-1 -> 0.2690339 | D89: =D14/C14-1 -> 0.19663059 | E89: =E14/D14-1 -> 0.22184526 | F89: =F14/E14-1 -> -0.018281645 | G89: =G14/F14-1 -> 0.83910029 | H89: =H14/G14-1 -> -0.16730691 | I89: =I14/H14-1 -> 0.040880703 | J89: =J14/I14-1 -> 0.012147158 | ... Q89: =Q14/P14-1 -> 0.050108984
A90: Total Operating expenses | C90: =C15/B15-1 -> 0.31724354 | D90: =D15/C15-1 -> 0.17618056 | E90: =E15/D15-1 -> 0.16500302 | F90: =F15/E15-1 -> -0.012849679 | G90: =G15/F15-1 -> 0.51968665 | H90: =H15/G15-1 -> -0.048278115 | I90: =I15/H15-1 -> 0.09600169 | J90: =J15/I15-1 -> 0.077593745 | ... Q90: =Q15/P15-1 -> 0.044490565
A91: Operating income (loss) | C91: =C16/B16-1 -> 0.31226173 | D91: =D16/C16-1 -> 0.2063875 | E91: =E16/D16-1 -> 0.040486867 | F91: =F16/E16-1 -> 0.30473752 | G91: =G16/F16-1 -> -0.020497522 | H91: =H16/G16-1 -> 0.4823316 | I91: =I16/H16-1 -> 0.10452873 | J91: =J16/I16-1 -> 0.070764865 | ... Q91: =Q16/P16-1 -> 0.25336037
A93: Interest income | C93: 0 | D93: 0 | E93: 0 | F93: 0 | G93: 0 | H93: 0 | I93: 0 | J93: 0 | K93: 0 | L93: 0 | M93: 0 | N93: 0 | O93: 0 | P93: 0 | Q93: 0
A94: Interest expense | C94: 0 | D94: 0 | E94: 0 | F94: 0 | G94: 0 | H94: 0 | I94: 0 | J94: 0 | K94: 0 | L94: 0 | M94: 0 | N94: 0 | O94: 0 | P94: 0 | Q94: 0
A95: Other income (expense), net | C95: 0 | D95: 0 | E95: 0 | F95: 0 | G95: 0 | H95: =H20/G20-1 -> 1.6855107 | I95: =I20/H20-1 -> -1.5016805 | J95: =J20/I20-1 -> 2.4037377 | K95: =K20/J20-1 -> 0.34911426 | L95: =L20/K20-1 -> -1.5372034 | M95: =M20/L20-1 -> -1.5648942 | N95: =N20/M20-1 -> -4.2279858 | O95: =O20/N20-1 -> -10.024614 | ... Q95: =Q20/P20-1 -> 0.067776557
A96: Income before income taxes | C96: =C21/B21-1 -> 0.31226173 | D96: =D21/C21-1 -> 0.2063875 | E96: =E21/D21-1 -> 0.040486867 | F96: =F21/E21-1 -> 0.30473752 | G96: =G21/F21-1 -> -0.017681487 | H96: =H21/G21-1 -> 0.48578078 | I96: =I21/H21-1 -> 0.09620611 | J96: =J21/I21-1 -> 0.065232606 | ... Q96: =Q21/P21-1 -> 0.25922852
A98: Provision for income taxes | C98: =C23/B23-1 -> 0.24606441 | D98: =D23/C23-1 -> 0.2226412 | E98: =E23/D23-1 -> 0.076979353 | F98: =F23/E23-1 -> 0.16591707 | G98: =G23/F23-1 -> 0.31306573 | H98: =H23/G23-1 -> 0.064338848 | I98: =I23/H23-1 -> 0.037997275 | J98: =J23/I23-1 -> -0.21178123 | ... Q98: =Q23/P23-1 -> 0.20125684
A99: Net income (loss) | C99: =C24/B24-1 -> 0.35542246 | D99: =D24/C24-1 -> 0.19664508 | E99: =E24/D24-1 -> 0.018138212 | F99: =F24/E24-1 -> 0.39466698 | G99: =G24/F24-1 -> -0.19680059 | H99: =H24/G24-1 -> 0.85889908 | I99: =I24/H24-1 -> 0.12571289 | J99: =J24/I24-1 -> 0.19471268 | ... Q99: =Q24/P24-1 -> 0.27925431
A102: Monster-US
A103: Balance Sheet ($'000)
B104: 2010 | C104: =B104+1 -> 2011 | D104: =C104+1 -> 2012 | E104: =D104+1 -> 2013 | F104: =E104+1 -> 2014 | G104: =F104+1 -> 2015 | H104: =G104+1 -> 2016 | I104: =H104+1 -> 2017 | J104: =I104+1 -> 2018 | ... N104: =M104+1 -> 2022 | O104: 2023 | P104: =O104+1 -> 2024 | Q104: =P104+1 -> 2025
A105: Current assets
A106: Cash and cash equivalents | C106: =C30/B30-1 -> 0.012650701 | D106: =D30/C30-1 -> -0.38075479 | E106: =E30/D30-1 -> -0.050176618 | F106: =F30/E30-1 -> 0.75218714 | G106: =G30/F30-1 -> 4.8743772 | H106: =H30/G30-1 -> -0.82643236 | I106: =I30/H30-1 -> 0.40001907 | J106: =J30/I30-1 -> 0.20599029 | ... Q106: =Q30/P30-1 -> 0.36185659
A107: Short-term investments | C107: =C31/B31-1 -> 0.68111049 | D107: =D31/C31-1 -> -0.76404997 | E107: =E31/D31-1 -> 3.1450815 | F107: =F31/E31-1 -> 0.94192623 | G107: =G31/F31-1 -> -0.046757663 | H107: =H31/G31-1 -> -0.7037993 | I107: =I31/H31-1 -> 2.0511031 | J107: =J31/I31-1 -> -0.52350383 | ... P107: =P31/O31-1 -> -1
A108: Accounts receivable, net | C108: =C32/B32-1 -> 1.1522212 | D108: =D32/C32-1 -> 0.08214738 | E108: =E32/D32-1 -> 0.25123569 | F108: =F32/E32-1 -> -0.052079816 | G108: =G32/F32-1 -> 0.70239177 | H108: =H32/G32-1 -> 0.19896434 | I108: =I32/H32-1 -> -0.21564398 | J108: =J32/I32-1 -> 0.078059785 | ... Q108: =Q32/P32-1 -> 0.32450153
A109: Inventories | C109: =C33/B33-1 -> 0.015478886 | D109: =D33/C33-1 -> 0.30519944 | E109: =E33/D33-1 -> 0.090312448 | F109: =F33/E33-1 -> -0.21167854 | G109: =G33/F33-1 -> -0.1056979 | H109: =H33/G33-1 -> 0.037470936 | I109: =I33/H33-1 -> 0.57895549 | J109: =J33/I33-1 -> 0.085866781 | ... Q109: =Q33/P33-1 -> 0.084812653
A110: Prepaid expenses and other current assets | C110: =C34/B34-1 -> 0.22852779 | D110: =D34/C34-1 -> 0.19467292 | E110: =E34/D34-1 -> -0.14437818 | F110: =F34/E34-1 -> -0.079668787 | G110: =G34/F34-1 -> 0.37076196 | H110: =H34/G34-1 -> 0.2074758 | I110: =I34/H34-1 -> 0.25535901 | J110: =J34/I34-1 -> 0.098637376 | ... Q110: =Q34/P34-1 -> -0.034597528
A111: Intangibles held-for-sale
A112: Prepaid Income Taxes | C112: =C36/B36-1 -> -0.96297038 | D112: =D36/C36-1 -> 90.105405 | E112: =E36/D36-1 -> -0.71764217 | F112: =F36/E36-1 -> -0.094662744 | G112: =G36/F36-1 -> 1.142509 | H112: =H36/G36-1 -> 2.6047015 | I112: =I36/H36-1 -> 1.0845079 | J112: =J36/I36-1 -> -0.72008448 | K112: =K36/J36-1 -> -1 | M112: =M36/L36-1 -> 0.34387256 | N112: =N36/M36-1 -> 0.016457067 | O112: =O36/N36-1 -> 0.6028119 | P112: =P36/O36-1 -> -0.22066074 | Q112: =Q36/P36-1 -> 0.76856547
A113: Deferred income tax | C113: =C37/B37-1 -> -0.020510374 | D113: =D37/C37-1 -> 0.035062089 | E113: =E37/D37-1 -> 0.23053399 | F113: =F37/E37-1 -> 0.92482317 | G113: =G37/F37-1 -> -1
A114: Total current assets | C114: =C38/B38-1 -> 0.3167879 | D114: =D38/C38-1 -> -0.29391711 | E114: =E38/D38-1 -> 0.41670259 | F114: =F38/E38-1 -> 0.43141796 | G114: =G38/F38-1 -> 1.1255878 | H114: =H38/G38-1 -> -0.60209549 | I114: =I38/H38-1 -> 0.45669252 | J114: =J38/I38-1 -> -0.13526175 | ... Q114: =Q38/P38-1 -> 0.47221697
A116: Long-term assets
A117: Investments | C117: =C41/B41-1 -> -0.47511824 | D117: =D41/C41-1 -> -0.077649392 | E117: =E41/D41-1 -> -0.54228019 | F117: =F41/E41-1 -> 3.3852124 | G117: =G41/F41-1 -> -0.64257103 | H117: =H41/G41-1 -> -0.84401876 | I117: =I41/H41-1 -> -0.011695906 | J117: =J41/I41-1 -> -1 | M117: =M41/L41-1 -> 1.2446772 | N117: =N41/M41-1 -> -0.3819793 | O117: =O41/N41-1 -> 0.2439334 | P117: =P41/O41-1 -> -1
...

Sheet Common Size
A1: Common sized
A3: Monster-US
A4: Income Statement ($'000)
B5: 2010 | C5: =B5+1 -> 2011 | D5: =C5+1 -> 2012 | E5: =D5+1 -> 2013 | F5: =E5+1 -> 2014 | G5: =F5+1 -> 2015 | H5: =G5+1 -> 2016 | I5: =H5+1 -> 2017 | J5: =I5+1 -> 2018 | ... N5: =M5+1 -> 2022 | O5: FY2023A | P5: FY2024A | Q5: FY2025A
A6: Net sales | B6: 1303942 | C6: 1703230 | D6: 2060702 | E6: 2246428 | F6: 2464867 | G6: 2722564 | H6: 3049393 | I6: 3369045 | J6: 3807183 | K6: 4200819 | L6: 4598638 | M6: 5541352 | N6: 6311050 | O6: 7140027 | P6: 7492709 | Q6: 8294343
A7: Cost of sales | B7: 623702 | C7: 808921 | D7: 995046 | E7: 1073497 | F7: 1125057 | G7: 1090263 | H7: 1107393 | I7: 1231355 | J7: 1511808 | K7: 1682234 | L7: 1874758 | M7: 2432839 | N7: 3136483 | O7: 3345821 | P7: 3443831 | Q7: 3662148
A8: Gross profit | B8: =B6-B7 -> 680240 | C8: =C6-C7 -> 894309 | D8: =D6-D7 -> 1065656 | E8: =E6-E7 -> 1172931 | F8: =F6-F7 -> 1339810 | G8: =G6-G7 -> 1632301 | H8: =H6-H7 -> 1942000 | I8: =I6-I7 -> 2137690 | ... Q8: =Q6-Q7 -> 4632195
A10: Selling, general and administrative | B10: 0 | C10: 0 | D10: 0 | E10: 0 | F10: 0 | G10: 0 | H10: 0 | I10: 0 | J10: 0 | K10: 0 | L10: 0 | M10: 0 | N10: 0 | O10: 0 | P10: 0 | Q10: 0
A11: Freight-Out-Cots | B11: 47400 | C11: 60500 | D11: 76100 | E11: 84000 | F11: 92700 | G11: 87000 | H11: 83600 | I11: 91900 | J11: 128500 | K11: 122500 | L11: 134100 | M11: 213900 | N11: 249200 | O11: 223600 | P11: 224200 | Q11: 237000
A12: Advertising and Promotional | B12: 104900 | C12: 148800 | D12: 165400 | E12: 181800 | F12: 171500 | G12: 209700 | H12: 270600 | I12: 324000 | J12: 353900 | K12: 391600 | L12: 345700 | M12: 417600 | N12: 460700 | O12: 528900 | P12: 584100 | Q12: 599900
A13: Other Expenses | B13: 180126 | C13: 228586 | D13: 273533 | E13: 334215 | F13: 328105 | G13: 603418 | H13: 502462 | I13: 523003 | J13: 529356 | K13: 601546 | L13: 610927 | M13: 679546 | N13: 879946 | O13: 1088351 | P13: 1310284 | Q13: 1375941
A14: Total Operating expenses | B14: =B13+B12+B11+B10 -> 332426 | C14: =C13+C12+C11+C10 -> 437886 | D14: =D13+D12+D11+D10 -> 515033 | E14: =E13+E12+E11+E10 -> 600015 | F14: =F13+F12+F11+F10 -> 592305 | G14: =G13+G12+G11+G10 -> 900118 | H14: =H13+H12+H11+H10 -> 856662 | I14: =I13+I12+I11+I10 -> 938903 | ... Q14: =Q13+Q12+Q11+Q10 -> 2212841
A15: Operating income (loss) | B15: =B8-B14 -> 347814 | C15: =C8-C14 -> 456423 | D15: =D8-D14 -> 550623 | E15: =E8-E14 -> 572916 | F15: =F8-F14 -> 747505 | G15: =G8-G14 -> 732183 | H15: =H8-H14 -> 1085338 | I15: =I8-I14 -> 1198787 | ... Q15: =Q8-Q14 -> 2419354
A17: Interest income | B17: 0 | C17: 0 | D17: 0 | E17: 0 | F17: 0 | G17: 0 | H17: 0 | I17: 0 | J17: 0 | K17: 0 | L17: 0 | M17: 0 | N17: 0 | O17: 0 | P17: 0 | Q17: 0
A18: Interest expense | B18: 0 | C18: 0 | D18: 0 | E18: 0 | F18: 0 | G18: 0 | H18: 0 | I18: 0 | J18: 0 | K18: 0 | L18: 0 | M18: 0 | N18: 0 | O18: 0 | P18: 0 | Q18: 0
A19: Other income (expense), net | B19: 0 | C19: 0 | D19: 0 | E19: 0 | F19: 0 | G19: -2105 | H19: -5653 | I19: 2836 | J19: 9653 | K19: 13023 | L19: -6996 | M19: 3952 | N19: -12757 | O19: 115127 | P19: 59165 | Q19: 63175
A20: Income before income taxes | B20: =B15-B18+B17-B19 -> 347814 | C20: =C15-C18+C17-C19 -> 456423 | D20: =D15-D18+D17-D19 -> 550623 | E20: =E15-E18+E17-E19 -> 572916 | F20: =F15-F18+F17-F19 -> 747505 | G20: =G15-G18+G17-G19 -> 734288 | H20: =H15-H18+H17-H19 -> 1090991 | I20: =I15-I18+I17-I19 -> 1195951 | ... Q20: =Q15-Q18+Q17-Q19 -> 2356179
A22: Provision for income taxes | B22: 137273 | C22: 171051 | D22: 209134 | E22: 225233 | F22: 262603 | G22: 344815 | H22: 367000 | I22: 380945 | J22: 300268 | K22: 308127 | L22: 216563 | M22: 423944 | N22: 380340 | O22: 437494 | P22: 480411 | Q22: 577097
A23: Net income (loss) | B23: =B20-B22 -> 210541 | C23: =C20-C22 -> 285372 | D23: =D20-D22 -> 341489 | E23: =E20-E22 -> 347683 | F23: =F20-F22 -> 484902 | G23: =G20-G22 -> 389473 | H23: =H20-H22 -> 723991 | I23: =I20-I22 -> 815006 | ... Q23: =Q20-Q22 -> 1779082
A27: Monster-US
A28: Balance Sheet ($'000)
B29: 2010 | C29: =B29+1 -> 2011 | D29: =C29+1 -> 2012 | E29: =D29+1 -> 2013 | F29: =E29+1 -> 2014 | G29: =F29+1 -> 2015 | H29: =G29+1 -> 2016 | I29: =H29+1 -> 2017 | J29: =I29+1 -> 2018 | ... N29: =M29+1 -> 2022 | O29: 2023 | P29: =O29+1 -> 2024 | Q29: =P29+1 -> 2025
A30: Current assets
A31: Cash and cash equivalents | B31: 354842 | C31: 359331 | D31: 222514 | E31: 211349 | F31: 370323 | G31: 2175417 | H31: 377582 | I31: 528622 | J31: 637513 | K31: 797957 | L31: 1180413 | M31: 1326462 | N31: 1307141 | O31: 2297675 | P31: 1533287 | Q31: 2088117
A32: Short-term investments | B32: 244649 | C32: 411282 | D32: 97042 | E32: 402247 | F32: 781134 | G32: 744610 | H32: 220554 | I32: 672933 | J32: 320650 | K32: 533063 | L32: 881354 | M32: 1749727 | N32: 1362314 | O32: 955605 | P32: 0 | Q32: 677084
A33: Accounts receivable, net | B33: 101635 | C33: 218741 | D33: 236710 | E33: =291638+4542 -> 296180 | F33: =280203+552 -> 280755 | G33: =352955+125000 -> 477955 | H33: =448051+125000 -> 573051 | I33: 449476 | J33: 484562 | K33: 540330 | L33: 666012 | M33: 896658 | N33: 1016203 | O33: 1193964 | P33: 1221646 | Q33: 1618072
A34: Inventories | B34: 153241 | C34: 155613 | D34: 203106 | E34: 221449 | F34: 174573 | G34: 156121 | H34: 161971 | I34: 255745 | J34: 277705 | K34: 360731 | L34: 333085 | M34: 593357 | N34: 935631 | O34: 971406 | P34: 737107 | Q34: 799623
A35: Prepaid expenses and other current assets | B35: 17022 | C35: 20912 | D35: 24983 | E35: 21376 | F35: 19673 | G35: 26967 | H35: 32562 | I35: 40877 | J35: 44909 | K35: 54868 | L35: 55358 | M35: 82668 | N35: 109823 | O35: 116195 | P35: 107262 | Q35: 103551
A36: Intangibles held-for-sale | E36: 0 | F36: 18079 | G36: 0 | H36: 0
A37: Prepaid Income Taxes | B37: 9992 | C37: 370 | D37: 33709 | E37: 9518 | F37: 8617 | G37: 18462 | H37: 66550 | I37: 138724 | J37: 38831 | L37: 24733 | M37: 33238 | N37: 33785 | O37: 54151 | P37: 42202 | Q37: 74637
A38: Deferred income tax | B38: 16772 | C38: 16428 | D38: 17004 | E38: 20924 | F38: 40275 | G38: 0 | H38: 0
A39: Total current assets | B39: =B38+B35+B34+B33+B32+B31+B37+B36 -> 898153 | C39: =C38+C35+C34+C33+C32+C31+C37+C36 -> 1182677 | D39: =D38+D35+D34+D33+D32+D31+D37+D36 -> 835068 | E39: =E38+E35+E34+E33+E32+E31+E37+E36 -> 1183043 | F39: =F38+F35+F34+F33+F32+F31+F37+F36 -> 1693429 | G39: =G38+G35+G34+G33+G32+G31+G37+G36 -> 3599532 | H39: =H38+H35+H34+H33+H32+H31+H37+H36 -> 1432270 | I39: =I38+I35+I34+I33+I32+I31+I37+I36 -> 2086377 | ... Q39: =Q38+Q35+Q34+Q33+Q32+Q31+Q37+Q36 -> 5361084
A41: Long-term assets
A42: Investments | B42: 44189 | C42: 23194 | D42: 21393 | E42: 9792 | F42: 42940 | G42: 15348 | H42: 2394 | I42: 2366 | L42: 44291 | M42: 99419 | N42: 61443 | O42: 76431 | P42: 0 | Q42: 48329
A43: Property and equipment, net | B43: 34551 | C43: 45151 | D43: 69137 | E43: 88143 | F43: 90156 | G43: 97354 | H43: 173343 | I43: 230276 | J43: 243051 | K43: 298640 | L43: 314656 | M43: 313753 | N43: 516897 | O43: 890796 | P43: 1047024 | Q43: 1081544
A44: Deferred Income Taxes | B44: 58475 | C44: 58576 | D44: 59503 | E44: 63611 | F44: 54106 | G44: 140468 | H44: 159556 | I44: 92333 | J44: 85687 | L44: 241650 | M44: 225221 | N44: 177039 | O44: 175003 | P44: 184260 | Q44: 188646
A45: Intangible assets, net | B45: 43316 | C45: 48396 | D45: 54648 | E45: 65774 | F45: 50748 | G45: 427986 | H45: 1032635 | I45: 1034085 | J45: 1045878 | K45: 1052105 | L45: 1059046 | M45: 1072386 | N45: 1220410 | O45: 1427139 | P45: 1414252 | Q45: 1379268
A46: Goodwill | B46: 0 | C46: 0 | D46: 0 | E46: 0 | F46: 0 | G46: 1279715 | H46: 1331643 | I46: 1331643 | J46: 1331643 | K46: 1331643 | L46: 1331643 | M46: 1331643 | N46: 1417941 | O46: 1417941 | P46: 1331643 | Q46: 1331643
A47: Other assets | B47: 3447 | C47: 4405 | D47: 3576 | E47: 10146 | F47: 7496 | G47: 10874 | H47: 21630 | I47: 13932 | J47: 16462 | K47: 53973 | L47: 70475 | M47: 80252 | N47: 134478 | O47: 110216 | P47: 100406 | Q47: 159431
A48: Total long-term assets | B48: =B47+B46+B45+B43+B44+B42 -> 183978 | C48: =C47+C46+C45+C43+C44+C42 -> 179722 | D48: =D47+D46+D45+D43+D44+D42 -> 208257 | E48: =E47+E46+E45+E43+E44+E42 -> 237466 | F48: =F47+F46+F45+F43+F44+F42 -> 245446 | G48: =G47+G46+G45+G43+G44+G42 -> 1971745 | H48: =H47+H46+H45+H43+H44+H42 -> 2721201 | I48: =I47+I46+I45+I43+I44+I42 -> 2704635 | ... Q48: =Q47+Q46+Q45+Q43+Q44+Q42 -> 4188861
A49: Total assets | B49: =B48+B39 -> 1082131 | C49: =C48+C39 -> 1362399 | D49: =D48+D39 -> 1043325 | E49: =E48+E39 -> 1420509 | F49: =F48+F39 -> 1938875 | G49: =G48+G39 -> 5571277 | H49: =H48+H39 -> 4153471 | I49: =I48+I39 -> 4791012 | ... Q49: =Q48+Q39 -> 9549945
A51: Current liabilitiies
A52: Short term debt
A53: Accounts payable | B53: 85674 | C53: 113446 | D53: 127330 | E53: 119376 | F53: 127641 | G53: 144763 | H53: 193270 | I53: 245910 | J53: 248760 | K53: 274045 | L53: 296800 | M53: 404263 | N53: 444265 | O53: 564379 | P53: 466775 | Q53: 565974
A54: Accrued liabilities | B54: 23811 | C54: 31966 | D54: 38916 | E54: 59113 | F54: 40271 | G54: 81786 | H54: 79526 | I54: 87475 | J54: 112507 | K54: 114075 | L54: 142653 | M54: 210964 | N54: 172991 | O54: 183988 | P54: 220764 | Q54: 306085
A55: Accrued distributor terminations | B55: 407 | G55: 11018 | H55: 8184 | I55: 91 | J55: 0
A56: Deferred revenue | B56: 10140 | C56: 11583 | D56: 12695 | E56: 13832 | F56: 49926 | G56: 32271 | H56: 41672 | I56: 43236 | J56: 44045 | L56: 45429 | M56: 42530 | N56: 43311 | O56: 41914 | P56: 45809 | Q56: 45323
A57: Customer deposit liabilities
A58: Accrued promotional allowances | B58: 0 | C58: 87746 | D58: 91208 | E58: 99470 | F58: 114047 | G58: 115530 | H58: 110237 | I58: 137998 | J58: 145741 | K58: 166761 | L58: 186658 | M58: 211461 | N58: 255631 | O58: 269061 | P58: 267711 | Q58: 384070
A59: Accrued compensation | B59: 7603 | C59: 10353 | D59: 12926 | E59: 14864 | F59: 17983 | G59: 22159 | H59: 30043 | I59: 34996 | J59: 39903 | L59: 55015 | M59: 65459 | N59: 72463 | O59: 87392 | P59: 92454 | Q59: 114023
A60: Income taxes payable | B60: 925 | C60: 10996 | D60: 5470 | E60: 9359 | F60: 5848 | G60: 2750 | H60: 7657 | I60: 10645 | J60: 10189 | K60: 14717 | L60: 23433 | M60: 30399 | N60: 13317 | O60: 14955 | P60: 4006 | Q60: 32305
A61: Current portion of long-term debt | B61: 274 | C61: 0 | D61: 0
A62: Total current liabilities | B62: =B52+B61+B60+B58+B54+B53+B57+B55+B56+B59 -> 128834 | C62: =C52+C61+C60+C58+C54+C53+C57+C55+C56+C59 -> 266090 | D62: =D52+D61+D60+D58+D54+D53+D57+D55+D56+D59 -> 288545 | E62: =E52+E61+E60+E58+E54+E53+E57+E55+E56+E59 -> 316014 | F62: =F52+F61+F60+F58+F54+F53+F57+F55+F56+F59 -> 355716 | G62: =G52+G61+G60+G58+G54+G53+G57+G55+G56+G59 -> 410277 | H62: =H52+H61+H60+H58+H54+H53+H57+H55+H56+H59 -> 470589 | I62: =I52+I61+I60+I58+I54+I53+I57+I55+I56+I59 -> 560351 | ... Q62: =Q52+Q61+Q60+Q58+Q54+Q53+Q57+Q55+Q56+Q59 -> 1447780
A64: Long-term liabilities
A65: Long-term debt | P65: 373951 | Q65: 0
A66: Deferred revenue | B66: 124899 | C66: 117151 | D66: 110383 | E66: 112216 | F66: 68009 | G66: 351590 | H66: 353173 | I66: 334354 | J66: 312224 | K66: 287469 | L66: 264436 | M66: 243249 | N66: 223800 | O66: 204251 | P66: 179008 | Q66: 159991
A67: Deferred income taxes | B67: 0 | C67: 0 | D67: 0 | E67: 0 | F67: 0 | G67: 0 | H67: 0
A68: Other Liabilities | I68: 1095 | J68: 2621 | L68: 27432 | M68: 29508 | N68: 42286 | O68: 91838 | P68: 110893 | Q68: 127066
A69: Total long term liabilities | B69: =B66+B65+B67+B68 -> 124899 | C69: =C66+C65+C67+C68 -> 117151 | D69: =D66+D65+D67+D68 -> 110383 | E69: =E66+E65+E67+E68 -> 112216 | F69: =F66+F65+F67+F68 -> 68009 | G69: =G66+G65+G67+G68 -> 351590 | H69: =H66+H65+H67+H68 -> 353173 | I69: =I66+I65+I67+I68 -> 335449 | ... Q69: =Q66+Q65+Q67+Q68 -> 287057
A70: Total liabilities | B70: =B69+B62 -> 253733 | C70: =C69+C62 -> 383241 | D70: =D69+D62 -> 398928 | E70: =E69+E62 -> 428230 | F70: =F69+F62 -> 423725 | G70: =G69+G62 -> 761867 | H70: =H69+H62 -> 823762 | I70: =I69+I62 -> 895800 | ... Q70: =Q69+Q62 -> 1734837
A72: Equity
A73: Common stock | B73: 494 | C73: 994 | D73: 1019 | E73: 1030 | F73: 1035 | G73: 3105 | H73: 3116 | I73: 3146 | J73: 3155 | K73: 3182 | L73: 3193 | M73: 3200 | N73: 6418 | O73: 5613 | P73: 5632 | Q73: 5665
A74: Additional paid-in capital | B74: 187040 | C74: 229301 | D74: 287953 | E74: 368069 | F74: 426145 | G74: 3989787 | H74: 4051245 | I74: 4150628 | J74: 4238170 | K74: 4397511 | L74: 4537982 | M74: 4652620 | N74: 4776804 | O74: 4975115 | P74: 5144922 | Q74: 5430847
A75: Retained earnings / accumulated deficit | B75: 882425 | C75: 1168644 | D75: 1508664 | E75: 1847325 | F75: 2330510 | G75: 1394863 | H75: 2107548 | I75: 2928226 | J75: 3914645 | K75: 5022480 | L75: 6432074 | M75: 7809549 | N75: 9001173 | O75: 5939736 | P75: 7448784 | Q75: 9354216
A76: Accumulated other comprehensive income (loss) | B76: 281 | C76: -1547 | D76: 2074 | E76: -1233 | F76: -11453 | G76: -21878 | H76: -23249 | I76: -16659 | J76: -32864 | K76: -32387 | L76: 3034 | M76: -69165 | N76: -159073 | O76: -125337 | P76: -269487 | Q76: -60841
A77: Treasury stock | B77: -241842 | C77: -418234 | D77: -1155313 | E77: -1222912 | F77: -1231087 | G77: -556467 | H77: -2808951 | I77: -3170129 | J77: -4512205 | K77: -5219505 | L77: -5815423 | M77: -5829253 | N77: -6600281 | O77: -2566383 | P77: -6372133 | Q77: -6475779
A78: Total stockholders' equity | B78: =B77+B76+B75+B74+B73 -> 828398 | C78: =C77+C76+C75+C74+C73 -> 979158 | D78: =D77+D76+D75+D74+D73 -> 644397 | E78: =E77+E76+E75+E74+E73 -> 992279 | F78: =F77+F76+F75+F74+F73 -> 1515150 | G78: =G77+G76+G75+G74+G73 -> 4809410 | H78: =H77+H76+H75+H74+H73 -> 3329709 | I78: =I77+I76+I75+I74+I73 -> 3895212 | ... Q78: =Q77+Q76+Q75+Q74+Q73 -> 8254108
A79: Total liabilities and stockholders' equity | B79: =B78+B70 -> 1082131 | C79: =C78+C70 -> 1362399 | D79: =D78+D70 -> 1043325 | E79: =E78+E70 -> 1420509 | F79: =F78+F70 -> 1938875 | G79: =G78+G70 -> 5571277 | H79: =H78+H70 -> 4153471 | I79: =I78+I70 -> 4791012 | ... Q79: =Q78+Q70 -> 9988945
A81: Monster-US
A82: Income Statement ($'000)
B83: 2010 | C83: =B83+1 -> 2011 | D83: =C83+1 -> 2012 | E83: =D83+1 -> 2013 | F83: =E83+1 -> 2014 | G83: =F83+1 -> 2015 | H83: =G83+1 -> 2016 | I83: =H83+1 -> 2017 | J83: =I83+1 -> 2018 | ... N83: =M83+1 -> 2022 | O83: FY2023A | P83: FY2024A | Q83: FY2025A
A84: Net sales | B84: =B6/B$6 -> 1 | C84: =C6/C$6 -> 1 | D84: =D6/D$6 -> 1 | E84: =E6/E$6 -> 1 | F84: =F6/F$6 -> 1 | G84: =G6/G$6 -> 1 | H84: =H6/H$6 -> 1 | I84: =I6/I$6 -> 1 | ... N84: =N6/N$6 -> 1 | O84: =O6/$O$6 -> 1 | P84: =P6/$P$6 -> 1 | Q84: =Q6/$Q$6 -> 1
A85: Cost of sales | B85: =B7/B$6 -> 0.47832035 | C85: =C7/C$6 -> 0.47493351 | D85: =D7/D$6 -> 0.48286749 | E85: =E7/E$6 -> 0.47786842 | F85: =F7/F$6 -> 0.4564372 | G85: =G7/G$6 -> 0.4004545 | H85: =H7/H$6 -> 0.36315195 | I85: =I7/I$6 -> 0.36549081 | ... N85: =N7/N$6 -> 0.49698275 | O85: =(O7/$O$6) -> 0.46860061 | P85: =(P7/$P$6) -> 0.45962428 | Q85: =(Q7/$Q$6) -> 0.44152358
A86: Gross profit | B86: =B8/B$6 -> 0.52167965 | C86: =C8/C$6 -> 0.52506649 | D86: =D8/D$6 -> 0.51713251 | E86: =E8/E$6 -> 0.52213158 | F86: =F8/F$6 -> 0.5435628 | G86: =G8/G$6 -> 0.5995455 | H86: =H8/H$6 -> 0.63684805 | I86: =I8/I$6 -> 0.63450919 | ... N86: =N8/N$6 -> 0.50301725 | O86: =O8/$O$6 -> 0.53139939 | P86: =P8/$P$6 -> 0.54037572 | Q86: =Q8/$Q$6 -> 0.55847642
A88: Selling, general and administrative
A89: Freight-Out-Cots | B89: =B11/B$6 -> 0.03635131 | C89: =C11/C$6 -> 0.035520746 | D89: =D11/D$6 -> 0.036929163 | E89: =E11/E$6 -> 0.037392696 | F89: =F11/F$6 -> 0.03760852 | G89: =G11/G$6 -> 0.031955172 | H89: =H11/H$6 -> 0.027415292 | I89: =I11/I$6 -> 0.02727776 | ... N89: =N11/N$6 -> 0.039486298 | O89: =(O11/$O$6) -> 0.031316408 | P89: =(P11/$P$6) -> 0.029922422 | Q89: =(Q11/$Q$6) -> 0.028573692
A90: Advertising and Promotional | B90: =B12/B$6 -> 0.080448364 | C90: =C12/C$6 -> 0.087363421 | D90: =D12/D$6 -> 0.08026391 | E90: =E12/E$6 -> 0.080928478 | F90: =F12/F$6 -> 0.069577791 | G90: =G12/G$6 -> 0.077022983 | H90: =H12/H$6 -> 0.088738972 | I90: =I12/I$6 -> 0.096169686 | ... N90: =N12/N$6 -> 0.072998946 | O90: =(O12/$O$6) -> 0.07407535 | P90: =(P12/$P$6) -> 0.077955783 | Q90: =(Q12/$Q$6) -> 0.072326404
A91: Other Expenses | B91: =B13/B$6 -> 0.13813958 | C91: =C13/C$6 -> 0.13420736 | D91: =D13/D$6 -> 0.13273778 | E91: =E13/E$6 -> 0.14877619 | F91: =F13/F$6 -> 0.13311266 | G91: =G13/G$6 -> 0.22163593 | H91: =H13/H$6 -> 0.16477443 | I91: =I13/I$6 -> 0.15523776 | ... N91: =N13/N$6 -> 0.13942941 | O91: =(O13/$O$6) -> 0.15242954 | P91: =(P13/$P$6) -> 0.17487453 | Q91: =(Q13/$Q$6) -> 0.16588909
A92: Total Operating expenses | B92: =B14/B$6 -> 0.25493925 | C92: =C14/C$6 -> 0.25709153 | D92: =D14/D$6 -> 0.24993085 | E92: =E14/E$6 -> 0.26709737 | F92: =F14/F$6 -> 0.24029897 | G92: =G14/G$6 -> 0.33061408 | H92: =H14/H$6 -> 0.2809287 | I92: =I14/I$6 -> 0.27868521 | ... N92: =N14/N$6 -> 0.25191466 | O92: =(O14/$O$6) -> 0.25782129 | P92: =(P14/$P$6) -> 0.28275274 | Q92: =(Q14/$Q$6) -> 0.26678918
A93: Operating income (loss) | B93: =B15/B$6 -> 0.26674039 | C93: =C15/C$6 -> 0.26797497 | D93: =D15/D$6 -> 0.26720166 | E93: =E15/E$6 -> 0.25503421 | F93: =F15/F$6 -> 0.30326383 | G93: =G15/G$6 -> 0.26893142 | H93: =H15/H$6 -> 0.35591936 | I93: =I15/I$6 -> 0.35582398 | ... N93: =N15/N$6 -> 0.25110259 | O93: =(O15/$O$6) -> 0.2735781 | P93: =(P15/$P$6) -> 0.25762298 | Q93: =(Q15/$Q$6) -> 0.29168724
A95: Interest income | B95: 0 | C95: 0 | D95: 0 | E95: 0 | F95: 0 | G95: 0 | H95: 0 | I95: 0 | J95: 0 | K95: 0 | L95: 0 | M95: 0 | N95: 0 | O95: 0 | P95: 0 | Q95: 0
A96: Interest expense | B96: 0 | C96: 0 | D96: 0 | E96: 0 | F96: 0 | G96: 0 | H96: 0 | I96: 0 | J96: 0 | K96: 0 | L96: 0 | M96: 0 | N96: 0 | O96: 0 | P96: 0 | Q96: 0
A97: Other income (expense), net | B97: 0 | C97: 0 | D97: 0 | E97: 0 | F97: 0 | G97: =-G19/G$6 -> 0.00077316823 | H97: =-H19/H$6 -> 0.0018538116 | I97: =I19/I$6 -> 0.00084178157 | J97: =J19/J$6 -> 0.0025354705 | K97: =K19/K$6 -> 0.0031001098 | L97: =-L19/L$6 -> 0.00152132 | M97: =M19/M$6 -> 0.00071318335 | N97: =-N19/N$6 -> 0.0020213752 | O97: =O19/$O$6 -> 0.016124169 | P97: =P19/$P$6 -> 0.007896343 | Q97: =Q19/$Q$6 -> 0.007616637
A98: Income before income taxes | B98: =B20/B$6 -> 0.26674039 | C98: =C20/C$6 -> 0.26797497 | D98: =D20/D$6 -> 0.26720166 | E98: =E20/E$6 -> 0.25503421 | F98: =F20/F$6 -> 0.30326383 | G98: =G20/G$6 -> 0.26970459 | H98: =H20/H$6 -> 0.35777317 | I98: =I20/I$6 -> 0.3549822 | ... N98: =N20/N$6 -> 0.25312397 | O98: =O20/$O$6 -> 0.25745393 | P98: =P20/$P$6 -> 0.24972663 | Q98: =Q20/$Q$6 -> 0.2840706
A100: Provision for income taxes | B100: =B22/B$6 -> 0.10527539 | C100: =C22/C$6 -> 0.10042742 | D100: =D22/D$6 -> 0.10148677 | E100: =E22/E$6 -> 0.10026273 | F100: =F22/F$6 -> 0.10653841 | G100: =G22/G$6 -> 0.12665083 | H100: =H22/H$6 -> 0.12035182 | I100: =I22/I$6 -> 0.1130721 | ... N100: =N22/N$6 -> 0.060265724 | O100: =(O22/$O$6) -> 0.061273438 | P100: =(P22/$P$6) -> 0.06411713 | Q100: =(Q22/$Q$6) -> 0.06957718
A101: Net income (loss) | B101: =B23/B$6 -> 0.161465 | C101: =C23/C$6 -> 0.16754754 | D101: =D23/D$6 -> 0.16571489 | E101: =E23/E$6 -> 0.15477149 | F101: =F23/F$6 -> 0.19672542 | G101: =G23/G$6 -> 0.14305375 | H101: =H23/H$6 -> 0.23742135 | I101: =I23/I$6 -> 0.2419101 | ... Q101: =Q23/Q$6 -> 0.21449342
A106: Monster-US
A107: Balance Sheet ($'000)
B108: 2010 | C108: =B108+1 -> 2011 | D108: =C108+1 -> 2012 | E108: =D108+1 -> 2013 | F108: =E108+1 -> 2014 | G108: =F108+1 -> 2015 | H108: =G108+1 -> 2016 | I108: =H108+1 -> 2017 | J108: =I108+1 -> 2018 | ... N108: =M108+1 -> 2022 | O108: 2023 | P108: =O108+1 -> 2024 | Q108: =P108+1 -> 2025
A109: Current assets
A110: Cash and cash equivalents | B110: =B31/B$49 -> 0.32791039 | C110: =C31/C$49 -> 0.26374873 | D110: =D31/D$49 -> 0.21327391 | E110: =E31/E$49 -> 0.14878399 | F110: =F31/F$49 -> 0.1909989 | G110: =G31/G$49 -> 0.39047008 | H110: =H31/H$49 -> 0.090907581 | I110: =I31/I$49 -> 0.11033619 | ... Q110: =Q31/Q$49 -> 0.21865225
A111: Short-term investments | B111: =B32/B$49 -> 0.22608076 | C111: =C32/C$49 -> 0.30188073 | D111: =D32/D$49 -> 0.093012245 | E111: =E32/E$49 -> 0.28317103 | F111: =F32/F$49 -> 0.40288002 | G111: =G32/G$49 -> 0.13365158 | H111: =H32/H$49 -> 0.053101129 | I111: =I32/I$49 -> 0.14045738 | ... Q111: =Q32/Q$49 -> 0.070899256
A112: Accounts receivable, net | B112: =B33/B$49 -> 0.093921161 | C112: =C33/C$49 -> 0.16055575 | D112: =D33/D$49 -> 0.22688041 | E112: =E33/E$49 -> 0.20850273 | F112: =F33/F$49 -> 0.14480304 | G112: =G33/G$49 -> 0.085789129 | H112: =H33/H$49 -> 0.13796918 | I112: =I33/I$49 -> 0.093816505 | ... Q112: =Q33/Q$49 -> 0.1694326
A113: Inventories | B113: =B34/B$49 -> 0.1416104 | C113: =C34/C$49 -> 0.11421984 | D113: =D34/D$49 -> 0.19467184 | E113: =E34/E$49 -> 0.15589412 | F113: =F34/F$49 -> 0.090038295 | G113: =G34/G$49 -> 0.02802248 | H113: =H34/H$49 -> 0.03899654 | I113: =I34/I$49 -> 0.053380163 | ... Q113: =Q34/Q$49 -> 0.083730639
A114: Prepaid expenses and other current assets | B114: =B35/B$49 -> 0.015730073 | C114: =C35/C$49 -> 0.015349395 | D114: =D35/D$49 -> 0.023945559 | E114: =E35/E$49 -> 0.015048127 | F114: =F35/F$49 -> 0.010146606 | G114: =G35/G$49 -> 0.0048403625 | H114: =H35/H$49 -> 0.007839708 | I114: =I35/I$49 -> 0.0085320179 | ... Q114: =Q35/Q$49 -> 0.010843099
A115: Intangibles held-for-sale | B115: =B36/B$49 -> 0 | C115: =C36/C$49 -> 0 | D115: =D36/D$49 -> 0 | E115: =E36/E$49 -> 0 | F115: =F36/F$49 -> 0.0093244794 | G115: =G36/G$49 -> 0 | H115: =H36/H$49 -> 0 | I115: =I36/I$49 -> 0 | ... Q115: =Q36/Q$49 -> 0
A116: Prepaid Income Taxes | B116: =B37/B$49 -> 0.0092336325 | C116: =C37/C$49 -> 0.00027157976 | D116: =D37/D$49 -> 0.032309204 | E116: =E37/E$49 -> 0.0067004151 | F116: =F37/F$49 -> 0.0044443298 | G116: =G37/G$49 -> 0.0033137825 | H116: =H37/H$49 -> 0.016022743 | I116: =I37/I$49 -> 0.028955052 | ... Q116: =Q37/Q$49 -> 0.0078154377
A117: Deferred income tax | B117: =B38/B$49 -> 0.015499048 | C117: =C38/C$49 -> 0.012058142 | D117: =D38/D$49 -> 0.016297894 | E117: =E38/E$49 -> 0.014729931 | F117: =F38/F$49 -> 0.020772355 | G117: =G38/G$49 -> 0 | H117: =H38/H$49 -> 0 | I117: =I38/I$49 -> 0 | ... Q117: =Q38/Q$49 -> 0
A118: Total current assets | B118: =B39/B$49 -> 0.82998546 | C118: =C39/C$49 -> 0.86808417 | D118: =D39/D$49 -> 0.80039106 | E118: =E39/E$49 -> 0.83283034 | F118: =F39/F$49 -> 0.87340803 | G118: =G39/G$49 -> 0.64608742 | H118: =H39/H$49 -> 0.34483688 | I118: =I39/I$49 -> 0.43547731 | ... Q118: =Q39/Q$49 -> 0.56137329
A120: Long-term assets
...

Sheet Index Analysis
A1: Index Analysis
A3: Monster-US
A4: Income Statement ($'000)
B5: 2010 | C5: =B5+1 -> 2011 | D5: =C5+1 -> 2012 | E5: =D5+1 -> 2013 | F5: =E5+1 -> 2014 | G5: =F5+1 -> 2015 | H5: =G5+1 -> 2016 | I5: =H5+1 -> 2017 | J5: =I5+1 -> 2018 | ... N5: =M5+1 -> 2022 | O5: FY2023A | P5: FY2024A | Q5: FY2025A
A6: Net sales | B6: 1303942 | C6: 1703230 | D6: 2060702 | E6: 2246428 | F6: 2464867 | G6: 2722564 | H6: 3049393 | I6: 3369045 | J6: 3807183 | K6: 4200819 | L6: 4598638 | M6: 5541352 | N6: 6311050 | O6: 7140027 | P6: 7492709 | Q6: 8294343
A7: Cost of sales | B7: 623702 | C7: 808921 | D7: 995046 | E7: 1073497 | F7: 1125057 | G7: 1090263 | H7: 1107393 | I7: 1231355 | J7: 1511808 | K7: 1682234 | L7: 1874758 | M7: 2432839 | N7: 3136483 | O7: 3345821 | P7: 3443831 | Q7: 3662148
A8: Gross profit | B8: =B6-B7 -> 680240 | C8: =C6-C7 -> 894309 | D8: =D6-D7 -> 1065656 | E8: =E6-E7 -> 1172931 | F8: =F6-F7 -> 1339810 | G8: =G6-G7 -> 1632301 | H8: =H6-H7 -> 1942000 | I8: =I6-I7 -> 2137690 | ... Q8: =Q6-Q7 -> 4632195
A10: Selling, general and administrative | B10: 0 | C10: 0 | D10: 0 | E10: 0 | F10: 0 | G10: 0 | H10: 0 | I10: 0 | J10: 0 | K10: 0 | L10: 0 | M10: 0 | N10: 0 | O10: 0 | P10: 0 | Q10: 0
A11: Freight-Out-Cots | B11: 47400 | C11: 60500 | D11: 76100 | E11: 84000 | F11: 92700 | G11: 87000 | H11: 83600 | I11: 91900 | J11: 128500 | K11: 122500 | L11: 134100 | M11: 213900 | N11: 249200 | O11: 223600 | P11: 224200 | Q11: 237000
A12: Advertising and Promotional | B12: 104900 | C12: 148800 | D12: 165400 | E12: 181800 | F12: 171500 | G12: 209700 | H12: 270600 | I12: 324000 | J12: 353900 | K12: 391600 | L12: 345700 | M12: 417600 | N12: 460700 | O12: 528900 | P12: 584100 | Q12: 599900
A13: Other Expenses | B13: 180126 | C13: 228586 | D13: 273533 | E13: 334215 | F13: 328105 | G13: 603418 | H13: 502462 | I13: 523003 | J13: 529356 | K13: 601546 | L13: 610927 | M13: 679546 | N13: 879946 | O13: 1088351 | P13: 1310284 | Q13: 1375941
A14: Total Operating expenses | B14: =B13+B12+B11+B10 -> 332426 | C14: =C13+C12+C11+C10 -> 437886 | D14: =D13+D12+D11+D10 -> 515033 | E14: =E13+E12+E11+E10 -> 600015 | F14: =F13+F12+F11+F10 -> 592305 | G14: =G13+G12+G11+G10 -> 900118 | H14: =H13+H12+H11+H10 -> 856662 | I14: =I13+I12+I11+I10 -> 938903 | ... Q14: =Q13+Q12+Q11+Q10 -> 2212841
A15: Operating income (loss) | B15: =B8-B14 -> 347814 | C15: =C8-C14 -> 456423 | D15: =D8-D14 -> 550623 | E15: =E8-E14 -> 572916 | F15: =F8-F14 -> 747505 | G15: =G8-G14 -> 732183 | H15: =H8-H14 -> 1085338 | I15: =I8-I14 -> 1198787 | ... Q15: =Q8-Q14 -> 2419354
A17: Interest income | B17: 0 | C17: 0 | D17: 0 | E17: 0 | F17: 0 | G17: 0 | H17: 0 | I17: 0 | J17: 0 | K17: 0 | L17: 0 | M17: 0 | N17: 0 | O17: 0 | P17: 0 | Q17: 0
A18: Interest expense | B18: 0 | C18: 0 | D18: 0 | E18: 0 | F18: 0 | G18: 0 | H18: 0 | I18: 0 | J18: 0 | K18: 0 | L18: 0 | M18: 0 | N18: 0 | O18: 0 | P18: 0 | Q18: 0
A19: Other income (expense), net | B19: 0 | C19: 0 | D19: 0 | E19: 0 | F19: 0 | G19: -2105 | H19: -5653 | I19: 2836 | J19: 9653 | K19: 13023 | L19: -6996 | M19: 3952 | N19: -12757 | O19: 115127 | P19: 59165 | Q19: 63175
A20: Income before income taxes | B20: =B15-B18+B17-B19 -> 347814 | C20: =C15-C18+C17-C19 -> 456423 | D20: =D15-D18+D17-D19 -> 550623 | E20: =E15-E18+E17-E19 -> 572916 | F20: =F15-F18+F17-F19 -> 747505 | G20: =G15-G18+G17-G19 -> 734288 | H20: =H15-H18+H17-H19 -> 1090991 | I20: =I15-I18+I17-I19 -> 1195951 | ... Q20: =Q15-Q18+Q17-Q19 -> 2356179
A22: Provision for income taxes | B22: 137273 | C22: 171051 | D22: 209134 | E22: 225233 | F22: 262603 | G22: 344815 | H22: 367000 | I22: 380945 | J22: 300268 | K22: 308127 | L22: 216563 | M22: 423944 | N22: 380340 | O22: 437494 | P22: 480411 | Q22: 577097
A23: Net income (loss) | B23: =B20-B22 -> 210541 | C23: =C20-C22 -> 285372 | D23: =D20-D22 -> 341489 | E23: =E20-E22 -> 347683 | F23: =F20-F22 -> 484902 | G23: =G20-G22 -> 389473 | H23: =H20-H22 -> 723991 | I23: =I20-I22 -> 815006 | ... Q23: =Q20-Q22 -> 1779082
A27: Monster-US
A28: Balance Sheet ($'000)
B29: 2010 | C29: =B29+1 -> 2011 | D29: =C29+1 -> 2012 | E29: =D29+1 -> 2013 | F29: =E29+1 -> 2014 | G29: =F29+1 -> 2015 | H29: =G29+1 -> 2016 | I29: =H29+1 -> 2017 | J29: =I29+1 -> 2018 | ... N29: =M29+1 -> 2022 | O29: 2023 | P29: =O29+1 -> 2024 | Q29: =P29+1 -> 2025
A30: Current assets
A31: Cash and cash equivalents | B31: 354842 | C31: 359331 | D31: 222514 | E31: 211349 | F31: 370323 | G31: 2175417 | H31: 377582 | I31: 528622 | J31: 637513 | K31: 797957 | L31: 1180413 | M31: 1326462 | N31: 1307141 | O31: 2297675 | P31: 1533287 | Q31: 2088117
A32: Short-term investments | B32: 244649 | C32: 411282 | D32: 97042 | E32: 402247 | F32: 781134 | G32: 744610 | H32: 220554 | I32: 672933 | J32: 320650 | K32: 533063 | L32: 881354 | M32: 1749727 | N32: 1362314 | O32: 955605 | P32: 0 | Q32: 677084
A33: Accounts receivable, net | B33: 101635 | C33: 218741 | D33: 236710 | E33: =291638+4542 -> 296180 | F33: =280203+552 -> 280755 | G33: =352955+125000 -> 477955 | H33: =448051+125000 -> 573051 | I33: 449476 | J33: 484562 | K33: 540330 | L33: 666012 | M33: 896658 | N33: 1016203 | O33: 1193964 | P33: 1221646 | Q33: 1618072
A34: Inventories | B34: 153241 | C34: 155613 | D34: 203106 | E34: 221449 | F34: 174573 | G34: 156121 | H34: 161971 | I34: 255745 | J34: 277705 | K34: 360731 | L34: 333085 | M34: 593357 | N34: 935631 | O34: 971406 | P34: 737107 | Q34: 799623
A35: Prepaid expenses and other current assets | B35: 17022 | C35: 20912 | D35: 24983 | E35: 21376 | F35: 19673 | G35: 26967 | H35: 32562 | I35: 40877 | J35: 44909 | K35: 54868 | L35: 55358 | M35: 82668 | N35: 109823 | O35: 116195 | P35: 107262 | Q35: 103551
A36: Intangibles held-for-sale | E36: 0 | F36: 18079 | G36: 0 | H36: 0
A37: Prepaid Income Taxes | B37: 9992 | C37: 370 | D37: 33709 | E37: 9518 | F37: 8617 | G37: 18462 | H37: 66550 | I37: 138724 | J37: 38831 | L37: 24733 | M37: 33238 | N37: 33785 | O37: 54151 | P37: 42202 | Q37: 74637
A38: Deferred income tax | B38: 16772 | C38: 16428 | D38: 17004 | E38: 20924 | F38: 40275 | G38: 0 | H38: 0
A39: Total current assets | B39: =B38+B35+B34+B33+B32+B31+B37+B36 -> 898153 | C39: =C38+C35+C34+C33+C32+C31+C37+C36 -> 1182677 | D39: =D38+D35+D34+D33+D32+D31+D37+D36 -> 835068 | E39: =E38+E35+E34+E33+E32+E31+E37+E36 -> 1183043 | F39: =F38+F35+F34+F33+F32+F31+F37+F36 -> 1693429 | G39: =G38+G35+G34+G33+G32+G31+G37+G36 -> 3599532 | H39: =H38+H35+H34+H33+H32+H31+H37+H36 -> 1432270 | I39: =I38+I35+I34+I33+I32+I31+I37+I36 -> 2086377 | ... Q39: =Q38+Q35+Q34+Q33+Q32+Q31+Q37+Q36 -> 5361084
A41: Long-term assets
A42: Investments | B42: 44189 | C42: 23194 | D42: 21393 | E42: 9792 | F42: 42940 | G42: 15348 | H42: 2394 | I42: 2366 | L42: 44291 | M42: 99419 | N42: 61443 | O42: 76431 | P42: 0 | Q42: 48329
A43: Property and equipment, net | B43: 34551 | C43: 45151 | D43: 69137 | E43: 88143 | F43: 90156 | G43: 97354 | H43: 173343 | I43: 230276 | J43: 243051 | K43: 298640 | L43: 314656 | M43: 313753 | N43: 516897 | O43: 890796 | P43: 1047024 | Q43: 1081544
A44: Deferred Income Taxes | B44: 58475 | C44: 58576 | D44: 59503 | E44: 63611 | F44: 54106 | G44: 140468 | H44: 159556 | I44: 92333 | J44: 85687 | L44: 241650 | M44: 225221 | N44: 177039 | O44: 175003 | P44: 184260 | Q44: 188646
A45: Intangible assets, net | B45: 43316 | C45: 48396 | D45: 54648 | E45: 65774 | F45: 50748 | G45: 427986 | H45: 1032635 | I45: 1034085 | J45: 1045878 | K45: 1052105 | L45: 1059046 | M45: 1072386 | N45: 1220410 | O45: 1427139 | P45: 1414252 | Q45: 1379268
A46: Goodwill | B46: 0 | C46: 0 | D46: 0 | E46: 0 | F46: 0 | G46: 1279715 | H46: 1331643 | I46: 1331643 | J46: 1331643 | K46: 1331643 | L46: 1331643 | M46: 1331643 | N46: 1417941 | O46: 1417941 | P46: 1331643 | Q46: 1331643
A47: Other assets | B47: 3447 | C47: 4405 | D47: 3576 | E47: 10146 | F47: 7496 | G47: 10874 | H47: 21630 | I47: 13932 | J47: 16462 | K47: 53973 | L47: 70475 | M47: 80252 | N47: 134478 | O47: 110216 | P47: 100406 | Q47: 159431
A48: Total long-term assets | B48: =B47+B46+B45+B43+B44+B42 -> 183978 | C48: =C47+C46+C45+C43+C44+C42 -> 179722 | D48: =D47+D46+D45+D43+D44+D42 -> 208257 | E48: =E47+E46+E45+E43+E44+E42 -> 237466 | F48: =F47+F46+F45+F43+F44+F42 -> 245446 | G48: =G47+G46+G45+G43+G44+G42 -> 1971745 | H48: =H47+H46+H45+H43+H44+H42 -> 2721201 | I48: =I47+I46+I45+I43+I44+I42 -> 2704635 | ... Q48: =Q47+Q46+Q45+Q43+Q44+Q42 -> 4188861
A49: Total assets | B49: =B48+B39 -> 1082131 | C49: =C48+C39 -> 1362399 | D49: =D48+D39 -> 1043325 | E49: =E48+E39 -> 1420509 | F49: =F48+F39 -> 1938875 | G49: =G48+G39 -> 5571277 | H49: =H48+H39 -> 4153471 | I49: =I48+I39 -> 4791012 | ... Q49: =Q48+Q39 -> 9549945
A51: Current liabilitiies
A52: Short term debt
A53: Accounts payable | B53: 85674 | C53: 113446 | D53: 127330 | E53: 119376 | F53: 127641 | G53: 144763 | H53: 193270 | I53: 245910 | J53: 248760 | K53: 274045 | L53: 296800 | M53: 404263 | N53: 444265 | O53: 564379 | P53: 466775 | Q53: 565974
A54: Accrued liabilities | B54: 23811 | C54: 31966 | D54: 38916 | E54: 59113 | F54: 40271 | G54: 81786 | H54: 79526 | I54: 87475 | J54: 112507 | K54: 114075 | L54: 142653 | M54: 210964 | N54: 172991 | O54: 183988 | P54: 220764 | Q54: 306085
A55: Accrued distributor terminations | B55: 407 | G55: 11018 | H55: 8184 | I55: 91 | J55: 0
A56: Deferred revenue | B56: 10140 | C56: 11583 | D56: 12695 | E56: 13832 | F56: 49926 | G56: 32271 | H56: 41672 | I56: 43236 | J56: 44045 | L56: 45429 | M56: 42530 | N56: 43311 | O56: 41914 | P56: 45809 | Q56: 45323
A57: Customer deposit liabilities
A58: Accrued promotional allowances | B58: 0 | C58: 87746 | D58: 91208 | E58: 99470 | F58: 114047 | G58: 115530 | H58: 110237 | I58: 137998 | J58: 145741 | K58: 166761 | L58: 186658 | M58: 211461 | N58: 255631 | O58: 269061 | P58: 267711 | Q58: 384070
A59: Accrued compensation | B59: 7603 | C59: 10353 | D59: 12926 | E59: 14864 | F59: 17983 | G59: 22159 | H59: 30043 | I59: 34996 | J59: 39903 | L59: 55015 | M59: 65459 | N59: 72463 | O59: 87392 | P59: 92454 | Q59: 114023
A60: Income taxes payable | B60: 925 | C60: 10996 | D60: 5470 | E60: 9359 | F60: 5848 | G60: 2750 | H60: 7657 | I60: 10645 | J60: 10189 | K60: 14717 | L60: 23433 | M60: 30399 | N60: 13317 | O60: 14955 | P60: 4006 | Q60: 32305
A61: Current portion of long-term debt | B61: 274 | C61: 0 | D61: 0
A62: Total current liabilities | B62: =B52+B61+B60+B58+B54+B53+B57+B55+B56+B59 -> 128834 | C62: =C52+C61+C60+C58+C54+C53+C57+C55+C56+C59 -> 266090 | D62: =D52+D61+D60+D58+D54+D53+D57+D55+D56+D59 -> 288545 | E62: =E52+E61+E60+E58+E54+E53+E57+E55+E56+E59 -> 316014 | F62: =F52+F61+F60+F58+F54+F53+F57+F55+F56+F59 -> 355716 | G62: =G52+G61+G60+G58+G54+G53+G57+G55+G56+G59 -> 410277 | H62: =H52+H61+H60+H58+H54+H53+H57+H55+H56+H59 -> 470589 | I62: =I52+I61+I60+I58+I54+I53+I57+I55+I56+I59 -> 560351 | ... Q62: =Q52+Q61+Q60+Q58+Q54+Q53+Q57+Q55+Q56+Q59 -> 1447780
A64: Long-term liabilities
A65: Long-term debt | P65: 373951 | Q65: 0
A66: Deferred revenue | B66: 124899 | C66: 117151 | D66: 110383 | E66: 112216 | F66: 68009 | G66: 351590 | H66: 353173 | I66: 334354 | J66: 312224 | K66: 287469 | L66: 264436 | M66: 243249 | N66: 223800 | O66: 204251 | P66: 179008 | Q66: 159991
A67: Deferred income taxes | B67: 0 | C67: 0 | D67: 0 | E67: 0 | F67: 0 | G67: 0 | H67: 0
A68: Other Liabilities | I68: 1095 | J68: 2621 | L68: 27432 | M68: 29508 | N68: 42286 | O68: 91838 | P68: 110893 | Q68: 127066
A69: Total long term liabilities | B69: =B66+B65+B67+B68 -> 124899 | C69: =C66+C65+C67+C68 -> 117151 | D69: =D66+D65+D67+D68 -> 110383 | E69: =E66+E65+E67+E68 -> 112216 | F69: =F66+F65+F67+F68 -> 68009 | G69: =G66+G65+G67+G68 -> 351590 | H69: =H66+H65+H67+H68 -> 353173 | I69: =I66+I65+I67+I68 -> 335449 | ... Q69: =Q66+Q65+Q67+Q68 -> 287057
A70: Total liabilities | B70: =B69+B62 -> 253733 | C70: =C69+C62 -> 383241 | D70: =D69+D62 -> 398928 | E70: =E69+E62 -> 428230 | F70: =F69+F62 -> 423725 | G70: =G69+G62 -> 761867 | H70: =H69+H62 -> 823762 | I70: =I69+I62 -> 895800 | ... Q70: =Q69+Q62 -> 1734837
A72: Equity
A73: Common stock | B73: 494 | C73: 994 | D73: 1019 | E73: 1030 | F73: 1035 | G73: 3105 | H73: 3116 | I73: 3146 | J73: 3155 | K73: 3182 | L73: 3193 | M73: 3200 | N73: 6418 | O73: 5613 | P73: 5632 | Q73: 5665
A74: Additional paid-in capital | B74: 187040 | C74: 229301 | D74: 287953 | E74: 368069 | F74: 426145 | G74: 3989787 | H74: 4051245 | I74: 4150628 | J74: 4238170 | K74: 4397511 | L74: 4537982 | M74: 4652620 | N74: 4776804 | O74: 4975115 | P74: 5144922 | Q74: 5430847
A75: Retained earnings / accumulated deficit | B75: 882425 | C75: 1168644 | D75: 1508664 | E75: 1847325 | F75: 2330510 | G75: 1394863 | H75: 2107548 | I75: 2928226 | J75: 3914645 | K75: 5022480 | L75: 6432074 | M75: 7809549 | N75: 9001173 | O75: 5939736 | P75: 7448784 | Q75: 9354216
A76: Accumulated other comprehensive income (loss) | B76: 281 | C76: -1547 | D76: 2074 | E76: -1233 | F76: -11453 | G76: -21878 | H76: -23249 | I76: -16659 | J76: -32864 | K76: -32387 | L76: 3034 | M76: -69165 | N76: -159073 | O76: -125337 | P76: -269487 | Q76: -60841
A77: Treasury stock | B77: -241842 | C77: -418234 | D77: -1155313 | E77: -1222912 | F77: -1231087 | G77: -556467 | H77: -2808951 | I77: -3170129 | J77: -4512205 | K77: -5219505 | L77: -5815423 | M77: -5829253 | N77: -6600281 | O77: -2566383 | P77: -6372133 | Q77: -6475779
A78: Total stockholders' equity | B78: =B77+B76+B75+B74+B73 -> 828398 | C78: =C77+C76+C75+C74+C73 -> 979158 | D78: =D77+D76+D75+D74+D73 -> 644397 | E78: =E77+E76+E75+E74+E73 -> 992279 | F78: =F77+F76+F75+F74+F73 -> 1515150 | G78: =G77+G76+G75+G74+G73 -> 4809410 | H78: =H77+H76+H75+H74+H73 -> 3329709 | I78: =I77+I76+I75+I74+I73 -> 3895212 | ... Q78: =Q77+Q76+Q75+Q74+Q73 -> 8254108
A79: Total liabilities and stockholders' equity | B79: =B78+B70 -> 1082131 | C79: =C78+C70 -> 1362399 | D79: =D78+D70 -> 1043325 | E79: =E78+E70 -> 1420509 | F79: =F78+F70 -> 1938875 | G79: =G78+G70 -> 5571277 | H79: =H78+H70 -> 4153471 | I79: =I78+I70 -> 4791012 | ... Q79: =Q78+Q70 -> 9988945
A84: Monster-US
A85: Income Statement ($'000)
B86: 2010 | C86: =B86+1 -> 2011 | D86: =C86+1 -> 2012 | E86: =D86+1 -> 2013 | F86: =E86+1 -> 2014 | G86: =F86+1 -> 2015 | H86: =G86+1 -> 2016 | I86: =H86+1 -> 2017 | J86: =I86+1 -> 2018 | ... N86: =M86+1 -> 2022 | O86: FY2023A | P86: FY2024A | Q86: FY2025A
A87: Net sales | B87: =B6/B6 -> 1 | C87: =C6/B6 -> 1.3062161 | D87: =D6/B6 -> 1.5803632 | E87: =E6/B6 -> 1.7227975 | F87: =F6/B6 -> 1.8903195 | G87: =G6/B6 -> 2.0879487 | H87: =H6/B6 -> 2.3385956 | I87: =I6/B6 -> 2.5837384 | J87: =J6/B6 -> 2.9197487 | K87: =K6/B6 -> 3.2216303 | L87: =L6/B6 -> 3.5267197 | M87: =M6/B6 -> 4.2496921 | N87: =N6/B6 -> 4.8399775 | O87: =O6/B6 -> 5.4757244 | P87: =P6/B6 -> 5.7461981 | Q87: =Q6/B6 -> 6.3609754
A88: Cost of sales | B88: =B7/B7 -> 1 | C88: =C7/B7 -> 1.2969671 | D88: =D7/B7 -> 1.5953869 | E88: =E7/B7 -> 1.7211697 | F88: =F7/B7 -> 1.8038374 | G88: =G7/B7 -> 1.7480512 | H88: =H7/B7 -> 1.7755162 | I88: =I7/B7 -> 1.9742682 | J88: =J7/B7 -> 2.4239268 | K88: =K7/B7 -> 2.6971759 | L88: =L7/B7 -> 3.0058554 | M88: =M7/B7 -> 3.9006433 | N88: =N7/B7 -> 5.0288166 | O88: =O7/B7 -> 5.3644545 | P88: =P7/B7 -> 5.5215969 | Q88: =Q7/B7 -> 5.871631
A89: Gross profit | B89: =B8/B8 -> 1 | C89: =C8/B8 -> 1.3146963 | D89: =D8/B8 -> 1.5665883 | E89: =E8/B8 -> 1.72429 | F89: =F8/B8 -> 1.9696137 | G89: =G8/B8 -> 2.3995957 | H89: =H8/B8 -> 2.8548748 | I89: =I8/B8 -> 3.1425526 | J89: =J8/B8 -> 3.3743605 | K89: =K8/B8 -> 3.7024947 | L89: =L8/B8 -> 4.0042926 | M89: =M8/B8 -> 4.5697298 | N89: =N8/B8 -> 4.6668338 | O89: =O8/B8 -> 5.5777461 | P89: =P8/B8 -> 5.9521316 | Q89: =Q8/B8 -> 6.8096481
A91: Selling, general and administrative
A92: Freight-Out-Cots | B92: =B11/B11 -> 1 | C92: =C11/B11 -> 1.2763713 | D92: =D11/B11 -> 1.6054852 | E92: =E11/B11 -> 1.7721519 | F92: =F11/B11 -> 1.9556962 | G92: =G11/B11 -> 1.835443 | H92: =H11/B11 -> 1.7637131 | I92: =I11/B11 -> 1.9388186 | J92: =J11/B11 -> 2.7109705 | K92: =K11/B11 -> 2.5843882 | L92: =L11/B11 -> 2.8291139 | M92: =M11/B11 -> 4.5126582 | N92: =N11/B11 -> 5.257384 | O92: =O11/B11 -> 4.7172996 | P92: =P11/B11 -> 4.7299578 | Q92: =Q11/B11 -> 5
A93: Advertising and Promotional | B93: =B12/B12 -> 1 | C93: =C12/B12 -> 1.4184938 | D93: =D12/B12 -> 1.5767398 | E93: =E12/B12 -> 1.7330791 | F93: =F12/B12 -> 1.6348904 | G93: =G12/B12 -> 1.9990467 | H93: =H12/B12 -> 2.5795996 | I93: =I12/B12 -> 3.0886559 | J93: =J12/B12 -> 3.3736892 | K93: =K12/B12 -> 3.7330791 | L93: =L12/B12 -> 3.2955195 | M93: =M12/B12 -> 3.9809342 | N93: =N12/B12 -> 4.3918017 | O93: =O12/B12 -> 5.0419447 | P93: =P12/B12 -> 5.5681602 | Q93: =Q12/B12 -> 5.7187798
A94: Other Expenses | B94: =B13/B13 -> 1 | C94: =C13/B13 -> 1.2690339 | D94: =D13/B13 -> 1.5185648 | E94: =E13/B13 -> 1.8554512 | F94: =F13/B13 -> 1.8215305 | G94: =G13/B13 -> 3.3499772 | H94: =H13/B13 -> 2.7895029 | I94: =I13/B13 -> 2.9035397 | J94: =J13/B13 -> 2.9388095 | K94: =K13/B13 -> 3.3395845 | L94: =L13/B13 -> 3.3916647 | M94: =M13/B13 -> 3.7726147 | N94: =N13/B13 -> 4.8851693 | O94: =O13/B13 -> 6.0421649 | P94: =P13/B13 -> 7.2742636 | Q94: =Q13/B13 -> 7.6387695
A95: Total Operating expenses | B95: =B14/B14 -> 1 | C95: =C14/B14 -> 1.3172435 | D95: =D14/B14 -> 1.5493162 | E95: =E14/B14 -> 1.8049581 | F95: =F14/B14 -> 1.781765 | G95: =G14/B14 -> 2.7077244 | H95: =H14/B14 -> 2.5770006 | I95: =I14/B14 -> 2.824397 | J95: =J14/B14 -> 3.0435526 | K95: =K14/B14 -> 3.3560732 | L95: =L14/B14 -> 3.2811122 | M95: =M14/B14 -> 3.9438732 | N95: =N14/B14 -> 4.7825561 | O95: =O14/B14 -> 5.5376264 | P95: =P14/B14 -> 6.3730996 | Q95: =Q14/B14 -> 6.6566424
A96: Operating income (loss) | B96: =B15/B15 -> 1 | C96: =C15/B15 -> 1.3122617 | D96: =D15/B15 -> 1.5830961 | E96: =E15/B15 -> 1.6471907 | F96: =F15/B15 -> 2.1491516 | G96: =G15/B15 -> 2.1050993 | H96: =H15/B15 -> 3.1204552 | I96: =I15/B15 -> 3.4466324 | J96: =J15/B15 -> 3.6905329 | K96: =K15/B15 -> 4.0335898 | L96: =L15/B15 -> 4.695478 | M96: =M15/B15 -> 5.1678972 | N96: =N15/B15 -> 4.5562312 | O96: =O15/B15 -> 5.6160908 | P96: =P15/B15 -> 5.5497881 | Q96: =Q15/B15 -> 6.9558845
A98: Interest income
A99: Interest expense
A100: Other income (expense), net
A101: Income before income taxes | B101: =B20/B20 -> 1 | C101: =C20/B20 -> 1.3122617 | D101: =D20/B20 -> 1.5830961 | E101: =E20/B20 -> 1.6471907 | F101: =F20/B20 -> 2.1491516 | G101: =G20/B20 -> 2.1111514 | H101: =H20/B20 -> 3.1367081 | I101: =I20/B20 -> 3.4384786 | J101: =J20/B20 -> 3.6627795 | K101: =K20/B20 -> 3.9961474 | L101: =L20/B20 -> 4.7155922 | M101: =M20/B20 -> 5.1565348 | N101: =N20/B20 -> 4.5929089 | O101: =O20/B20 -> 5.2850892 | P101: =P20/B20 -> 5.3796828 | Q101: =Q20/B20 -> 6.77425
A103: Provision for income taxes | B103: =B22/B22 -> 1 | C103: =C22/B22 -> 1.2460644 | D103: =D22/B22 -> 1.5234897 | E103: =E22/B22 -> 1.6407669 | F103: =F22/B22 -> 1.9129982 | G103: =G22/B22 -> 2.5118924 | H103: =H22/B22 -> 2.6735046 | I103: =I22/B22 -> 2.7750905 | J103: =J22/B22 -> 2.1873784 | K103: =K22/B22 -> 2.2446293 | L103: =L22/B22 -> 1.5776081 | M103: =M22/B22 -> 3.0883276 | N103: =N22/B22 -> 2.7706832 | O103: =O22/B22 -> 3.1870361 | P103: =P22/B22 -> 3.4996758 | Q103: =Q22/B22 -> 4.2040095
A104: Net income (loss) | B104: =B23/B23 -> 1 | C104: =C23/B23 -> 1.3554225 | D104: =D23/B23 -> 1.6219596 | E104: =E23/B23 -> 1.6513791 | F104: =F23/B23 -> 2.3031239 | G104: =G23/B23 -> 1.8498677 | H104: =H23/B23 -> 3.4387174 | I104: =I23/B23 -> 3.8710085 | J104: =J23/B23 -> 4.6247429 | K104: =K23/B23 -> 5.1381394 | L104: =L23/B23 -> 6.7615619 | M104: =M23/B23 -> 6.5050085 | N104: =N23/B23 -> 5.7810023 | O104: =O23/B23 -> 6.6530225 | P104: =P23/B23 -> 6.6054498 | Q104: =Q23/B23 -> 8.4500501
A108: Monster-US
A109: Balance Sheet ($'000)
B110: 2010 | C110: =B110+1 -> 2011 | D110: =C110+1 -> 2012 | E110: =D110+1 -> 2013 | F110: =E110+1 -> 2014 | G110: =F110+1 -> 2015 | H110: =G110+1 -> 2016 | I110: =H110+1 -> 2017 | J110: =I110+1 -> 2018 | ... N110: =M110+1 -> 2022 | O110: 2023 | P110: =O110+1 -> 2024 | Q110: =P110+1 -> 2025
A111: Current assets
A112: Cash and cash equivalents | B112: =B31/B31 -> 1 | C112: =C31/B31 -> 1.0126507 | D112: =D31/B31 -> 0.62707909 | E112: =E31/B31 -> 0.59561439 | F112: =F31/B31 -> 1.0436279 | G112: =G31/B31 -> 6.1306638 | H112: =H31/B31 -> 1.0640849 | I112: =I31/B31 -> 1.4897391 | J112: =J31/B31 -> 1.7966109 | K112: =K31/B31 -> 2.2487671 | L112: =L31/B31 -> 3.3265876 | M112: =M31/B31 -> 3.7381764 | N112: =N31/B31 -> 3.6837268 | O112: =O31/B31 -> 6.4752059 | P112: =P31/B31 -> 4.3210415 | Q112: =Q31/B31 -> 5.8846388
A113: Short-term investments | B113: =B32/B32 -> 1 | C113: =C32/B32 -> 1.6811105 | D113: =D32/B32 -> 0.39665807 | E113: =E32/B32 -> 1.64418 | F113: =F32/B32 -> 3.1928763 | G113: =G32/B32 -> 3.0435849 | H113: =H32/B32 -> 0.90151196 | I113: =I32/B32 -> 2.750606 | J113: =J32/B32 -> 1.3106532 | K113: =K32/B32 -> 2.1788889 | L113: =L32/B32 -> 3.6025244 | M113: =M32/B32 -> 7.1519892 | N113: =N32/B32 -> 5.568443 | O113: =O32/B32 -> 3.9060245 | P113: =P32/B32 -> 0 | Q113: =Q32/B32 -> 2.7675731
A114: Accounts receivable, net | B114: =B33/B33 -> 1 | C114: =C33/B33 -> 2.1522212 | D114: =D33/B33 -> 2.3290205 | E114: =E33/B33 -> 2.9141536 | F114: =F33/B33 -> 2.762385 | G114: =G33/B33 -> 4.7026615 | H114: =H33/B33 -> 5.6383234 | I114: =I33/B33 -> 4.4224529 | J114: =J33/B33 -> 4.7676686 | K114: =K33/B33 -> 5.3163772 | L114: =L33/B33 -> 6.5529788 | M114: =M33/B33 -> 8.8223348 | N114: =N33/B33 -> 9.9985536 | O114: =O33/B33 -> 11.747567 | P114: =P33/B33 -> 12.019934 | Q114: =Q33/B33 -> 15.920421
A115: Inventories | B115: =B34/B34 -> 1 | C115: =C34/B34 -> 1.0154789 | D115: =D34/B34 -> 1.3254025 | E115: =E34/B34 -> 1.4451028 | F115: =F34/B34 -> 1.1392056 | G115: =G34/B34 -> 1.0187939 | H115: =H34/B34 -> 1.0569691 | I115: =I34/B34 -> 1.6689071 | J115: =J34/B34 -> 1.8122108 | K115: =K34/B34 -> 2.354011 | L115: =L34/B34 -> 2.1736024 | M115: =M34/B34 -> 3.8720512 | N115: =N34/B34 -> 6.1056179 | O115: =O34/B34 -> 6.3390737 | P115: =P34/B34 -> 4.8101161 | Q115: =Q34/B34 -> 5.2180748
A116: Prepaid expenses and other current assets | B116: =B35/B35 -> 1 | C116: =C35/B35 -> 1.2285278 | D116: =D35/B35 -> 1.4676889 | E116: =E35/B35 -> 1.2557866 | F116: =F35/B35 -> 1.1557396 | G116: =G35/B35 -> 1.5842439 | H116: =H35/B35 -> 1.9129362 | I116: =I35/B35 -> 2.4014217 | J116: =J35/B35 -> 2.6382916 | K116: =K35/B35 -> 3.223358 | L116: =L35/B35 -> 3.2521443 | M116: =M35/B35 -> 4.8565386 | N116: =N35/B35 -> 6.451827 | O116: =O35/B35 -> 6.8261661 | P116: =P35/B35 -> 6.3013747 | Q116: =Q35/B35 -> 6.0833627
A117: Intangibles held-for-sale
A118: Prepaid Income Taxes | B118: =B37/B37 -> 1 | C118: =C37/B37 -> 0.037029624 | D118: =D37/B37 -> 3.3735989 | E118: =E37/B37 -> 0.95256205 | F118: =F37/B37 -> 0.86238991 | G118: =G37/B37 -> 1.8476781 | H118: =H37/B37 -> 6.6603283 | I118: =I37/B37 -> 13.883507 | J118: =J37/B37 -> 3.886209 | K118: =K37/B37 -> 0 | L118: =L37/B37 -> 2.4752802 | M118: =M37/B37 -> 3.3264612 | N118: =N37/B37 -> 3.381205 | O118: =O37/B37 -> 5.4194355 | P118: =P37/B37 -> 4.2235789 | Q118: =Q37/B37 -> 7.4696757
A119: Deferred income tax | B119: =B38/B38 -> 1 | C119: =C38/B38 -> 0.97948963 | D119: =D38/B38 -> 1.0138326 | E119: =E38/B38 -> 1.2475554 | F119: =F38/B38 -> 2.4013236 | G119: =G38/B38 -> 0 | H119: =H38/B38 -> 0 | I119: =I38/B38 -> 0 | J119: =J38/B38 -> 0 | K119: =K38/B38 -> 0 | L119: =L38/B38 -> 0 | M119: =M38/B38 -> 0 | N119: =N38/B38 -> 0 | O119: =O38/B38 -> 0 | P119: =P38/B38 -> 0 | Q119: =Q38/B38 -> 0
A120: Total current assets | B120: =B39/B39 -> 1 | C120: =C39/B39 -> 1.3167879 | D120: =D39/B39 -> 0.92976141 | E120: =E39/B39 -> 1.3171954 | F120: =F39/B39 -> 1.8854572 | G120: =G39/B39 -> 4.0077047 | H120: =H39/B39 -> 1.5946838 | I120: =I39/B39 -> 2.3229639 | J120: =J39/B39 -> 2.0087557 | K120: =K39/B39 -> 2.54628 | L120: =L39/B39 -> 3.4971269 | M120: =M39/B39 -> 5.2130428 | N120: =N39/B39 -> 5.3052175 | O120: =O39/B39 -> 6.2227661 | P120: =P39/B39 -> 4.0544362 | Q120: =Q39/B39 -> 5.9690097
A122: Long-term assets
...

Sheet Financial Ratios
A1: Profitability Ratios | O1: Income compared to revenue & cogs
A2: Liquidity Ratios | O2: Short term ability to meet obligations
A3: Efficiency Ratios | O3: Balance sheet and ability to generate revenue
A4: Leverage Ratios | O4: Shows how much debt is present compared to
A7: Monster-US
A8: Income Statement ($'000)
B9: 2010 | C9: =B9+1 -> 2011 | D9: =C9+1 -> 2012 | E9: =D9+1 -> 2013 | F9: =E9+1 -> 2014 | G9: =F9+1 -> 2015 | H9: =G9+1 -> 2016 | I9: =H9+1 -> 2017 | J9: =I9+1 -> 2018 | ... N9: =M9+1 -> 2022 | O9: FY2023A | P9: FY2024A | Q9: FY2025A
A10: Net sales | B10: 1303942 | C10: 1703230 | D10: 2060702 | E10: 2246428 | F10: 2464867 | G10: 2722564 | H10: 3049393 | I10: 3369045 | J10: 3807183 | K10: 4200819 | L10: 4598638 | M10: 5541352 | N10: 6311050 | O10: 7140027 | P10: 7492709 | Q10: 8294343
A11: Cost of sales | B11: 623702 | C11: 808921 | D11: 995046 | E11: 1073497 | F11: 1125057 | G11: 1090263 | H11: 1107393 | I11: 1231355 | J11: 1511808 | K11: 1682234 | L11: 1874758 | M11: 2432839 | N11: 3136483 | O11: 3345821 | P11: 3443831 | Q11: 3662148
A12: Gross profit | B12: =B10-B11 -> 680240 | C12: =C10-C11 -> 894309 | D12: =D10-D11 -> 1065656 | E12: =E10-E11 -> 1172931 | F12: =F10-F11 -> 1339810 | G12: =G10-G11 -> 1632301 | H12: =H10-H11 -> 1942000 | I12: =I10-I11 -> 2137690 | ... Q12: =Q10-Q11 -> 4632195
A14: Selling, general and administrative | B14: 0 | C14: 0 | D14: 0 | E14: 0 | F14: 0 | G14: 0 | H14: 0 | I14: 0 | J14: 0 | K14: 0 | L14: 0 | M14: 0 | N14: 0 | O14: 0 | P14: 0 | Q14: 0
A15: Freight-Out-Cots | B15: 47400 | C15: 60500 | D15: 76100 | E15: 84000 | F15: 92700 | G15: 87000 | H15: 83600 | I15: 91900 | J15: 128500 | K15: 122500 | L15: 134100 | M15: 213900 | N15: 249200 | O15: 223600 | P15: 224200 | Q15: 237000
A16: Advertising and Promotional | B16: 104900 | C16: 148800 | D16: 165400 | E16: 181800 | F16: 171500 | G16: 209700 | H16: 270600 | I16: 324000 | J16: 353900 | K16: 391600 | L16: 345700 | M16: 417600 | N16: 460700 | O16: 528900 | P16: 584100 | Q16: 599900
A17: Other Expenses | B17: 180126 | C17: 228586 | D17: 273533 | E17: 334215 | F17: 328105 | G17: 603418 | H17: 502462 | I17: 523003 | J17: 529356 | K17: 601546 | L17: 610927 | M17: 679546 | N17: 879946 | O17: 1088351 | P17: 1310284 | Q17: 1375941
A18: Total Operating expenses | B18: =B17+B16+B15+B14 -> 332426 | C18: =C17+C16+C15+C14 -> 437886 | D18: =D17+D16+D15+D14 -> 515033 | E18: =E17+E16+E15+E14 -> 600015 | F18: =F17+F16+F15+F14 -> 592305 | G18: =G17+G16+G15+G14 -> 900118 | H18: =H17+H16+H15+H14 -> 856662 | I18: =I17+I16+I15+I14 -> 938903 | ... Q18: =Q17+Q16+Q15+Q14 -> 2212841
A19: Operating income (loss) | B19: =B12-B18 -> 347814 | C19: =C12-C18 -> 456423 | D19: =D12-D18 -> 550623 | E19: =E12-E18 -> 572916 | F19: =F12-F18 -> 747505 | G19: =G12-G18 -> 732183 | H19: =H12-H18 -> 1085338 | I19: =I12-I18 -> 1198787 | ... Q19: =Q12-Q18 -> 2419354
A21: Interest income | B21: 0 | C21: 0 | D21: 0 | E21: 0 | F21: 0 | G21: 0 | H21: 0 | I21: 0 | J21: 0 | K21: 0 | L21: 0 | M21: 0 | N21: 0 | O21: 0 | P21: 0 | Q21: 0
A22: Interest expense | B22: 0 | C22: 0 | D22: 0 | E22: 0 | F22: 0 | G22: 0 | H22: 0 | I22: 0 | J22: 0 | K22: 0 | L22: 0 | M22: 0 | N22: 0 | O22: 0 | P22: 0 | Q22: 0
A23: Other income (expense), net | B23: 0 | C23: 0 | D23: 0 | E23: 0 | F23: 0 | G23: -2105 | H23: -5653 | I23: 2836 | J23: 9653 | K23: 13023 | L23: -6996 | M23: 3952 | N23: -12757 | O23: 115127 | P23: 59165 | Q23: 63175
A24: Income before income taxes | B24: =B19-B22+B21-B23 -> 347814 | C24: =C19-C22+C21-C23 -> 456423 | D24: =D19-D22+D21-D23 -> 550623 | E24: =E19-E22+E21-E23 -> 572916 | F24: =F19-F22+F21-F23 -> 747505 | G24: =G19-G22+G21-G23 -> 734288 | H24: =H19-H22+H21-H23 -> 1090991 | I24: =I19-I22+I21-I23 -> 1195951 | ... Q24: =Q19-Q22+Q21-Q23 -> 2356179
A26: Provision for income taxes | B26: 137273 | C26: 171051 | D26: 209134 | E26: 225233 | F26: 262603 | G26: 344815 | H26: 367000 | I26: 380945 | J26: 300268 | K26: 308127 | L26: 216563 | M26: 423944 | N26: 380340 | O26: 437494 | P26: 480411 | Q26: 577097
A27: Net income (loss) | B27: =B24-B26 -> 210541 | C27: =C24-C26 -> 285372 | D27: =D24-D26 -> 341489 | E27: =E24-E26 -> 347683 | F27: =F24-F26 -> 484902 | G27: =G24-G26 -> 389473 | H27: =H24-H26 -> 723991 | I27: =I24-I26 -> 815006 | ... Q27: =Q24-Q26 -> 1779082
A31: Monster-US
A32: Balance Sheet ($'000)
B33: 2010 | C33: =B33+1 -> 2011 | D33: =C33+1 -> 2012 | E33: =D33+1 -> 2013 | F33: =E33+1 -> 2014 | G33: =F33+1 -> 2015 | H33: =G33+1 -> 2016 | I33: =H33+1 -> 2017 | J33: =I33+1 -> 2018 | ... N33: =M33+1 -> 2022 | O33: 2023 | P33: =O33+1 -> 2024 | Q33: =P33+1 -> 2025
A34: Current assets
A35: Cash and cash equivalents | B35: 354842 | C35: 359331 | D35: 222514 | E35: 211349 | F35: 370323 | G35: 2175417 | H35: 377582 | I35: 528622 | J35: 637513 | K35: 797957 | L35: 1180413 | M35: 1326462 | N35: 1307141 | O35: 2297675 | P35: 1533287 | Q35: 2088117
A36: Short-term investments | B36: 244649 | C36: 411282 | D36: 97042 | E36: 402247 | F36: 781134 | G36: 744610 | H36: 220554 | I36: 672933 | J36: 320650 | K36: 533063 | L36: 881354 | M36: 1749727 | N36: 1362314 | O36: 955605 | P36: 0 | Q36: 677084
A37: Accounts receivable, net | B37: 101635 | C37: 218741 | D37: 236710 | E37: =291638+4542 -> 296180 | F37: =280203+552 -> 280755 | G37: =352955+125000 -> 477955 | H37: =448051+125000 -> 573051 | I37: 449476 | J37: 484562 | K37: 540330 | L37: 666012 | M37: 896658 | N37: 1016203 | O37: 1193964 | P37: 1221646 | Q37: 1618072
A38: Inventories | B38: 153241 | C38: 155613 | D38: 203106 | E38: 221449 | F38: 174573 | G38: 156121 | H38: 161971 | I38: 255745 | J38: 277705 | K38: 360731 | L38: 333085 | M38: 593357 | N38: 935631 | O38: 971406 | P38: 737107 | Q38: 799623
A39: Prepaid expenses and other current assets | B39: 17022 | C39: 20912 | D39: 24983 | E39: 21376 | F39: 19673 | G39: 26967 | H39: 32562 | I39: 40877 | J39: 44909 | K39: 54868 | L39: 55358 | M39: 82668 | N39: 109823 | O39: 116195 | P39: 107262 | Q39: 103551
A40: Intangibles held-for-sale | E40: 0 | F40: 18079 | G40: 0 | H40: 0
A41: Prepaid Income Taxes | B41: 9992 | C41: 370 | D41: 33709 | E41: 9518 | F41: 8617 | G41: 18462 | H41: 66550 | I41: 138724 | J41: 38831 | L41: 24733 | M41: 33238 | N41: 33785 | O41: 54151 | P41: 42202 | Q41: 74637
A42: Deferred income tax | B42: 16772 | C42: 16428 | D42: 17004 | E42: 20924 | F42: 40275 | G42: 0 | H42: 0
A43: Total current assets | B43: =B42+B39+B38+B37+B36+B35+B41+B40 -> 898153 | C43: =C42+C39+C38+C37+C36+C35+C41+C40 -> 1182677 | D43: =D42+D39+D38+D37+D36+D35+D41+D40 -> 835068 | E43: =E42+E39+E38+E37+E36+E35+E41+E40 -> 1183043 | F43: =F42+F39+F38+F37+F36+F35+F41+F40 -> 1693429 | G43: =G42+G39+G38+G37+G36+G35+G41+G40 -> 3599532 | H43: =H42+H39+H38+H37+H36+H35+H41+H40 -> 1432270 | I43: =I42+I39+I38+I37+I36+I35+I41+I40 -> 2086377 | ... Q43: =Q42+Q39+Q38+Q37+Q36+Q35+Q41+Q40 -> 5361084
A45: Long-term assets
A46: Investments | B46: 44189 | C46: 23194 | D46: 21393 | E46: 9792 | F46: 42940 | G46: 15348 | H46: 2394 | I46: 2366 | L46: 44291 | M46: 99419 | N46: 61443 | O46: 76431 | P46: 0 | Q46: 48329
A47: Property and equipment, net | B47: 34551 | C47: 45151 | D47: 69137 | E47: 88143 | F47: 90156 | G47: 97354 | H47: 173343 | I47: 230276 | J47: 243051 | K47: 298640 | L47: 314656 | M47: 313753 | N47: 516897 | O47: 890796 | P47: 1047024 | Q47: 1081544
A48: Deferred Income Taxes | B48: 58475 | C48: 58576 | D48: 59503 | E48: 63611 | F48: 54106 | G48: 140468 | H48: 159556 | I48: 92333 | J48: 85687 | L48: 241650 | M48: 225221 | N48: 177039 | O48: 175003 | P48: 184260 | Q48: 188646
A49: Intangible assets, net | B49: 43316 | C49: 48396 | D49: 54648 | E49: 65774 | F49: 50748 | G49: 427986 | H49: 1032635 | I49: 1034085 | J49: 1045878 | K49: 1052105 | L49: 1059046 | M49: 1072386 | N49: 1220410 | O49: 1427139 | P49: 1414252 | Q49: 1379268
A50: Goodwill | B50: 0 | C50: 0 | D50: 0 | E50: 0 | F50: 0 | G50: 1279715 | H50: 1331643 | I50: 1331643 | J50: 1331643 | K50: 1331643 | L50: 1331643 | M50: 1331643 | N50: 1417941 | O50: 1417941 | P50: 1331643 | Q50: 1331643
A51: Other assets | B51: 3447 | C51: 4405 | D51: 3576 | E51: 10146 | F51: 7496 | G51: 10874 | H51: 21630 | I51: 13932 | J51: 16462 | K51: 53973 | L51: 70475 | M51: 80252 | N51: 134478 | O51: 110216 | P51: 100406 | Q51: 159431
A52: Total long-term assets | B52: =B51+B50+B49+B47+B48+B46 -> 183978 | C52: =C51+C50+C49+C47+C48+C46 -> 179722 | D52: =D51+D50+D49+D47+D48+D46 -> 208257 | E52: =E51+E50+E49+E47+E48+E46 -> 237466 | F52: =F51+F50+F49+F47+F48+F46 -> 245446 | G52: =G51+G50+G49+G47+G48+G46 -> 1971745 | H52: =H51+H50+H49+H47+H48+H46 -> 2721201 | I52: =I51+I50+I49+I47+I48+I46 -> 2704635 | ... Q52: =Q51+Q50+Q49+Q47+Q48+Q46 -> 4188861
A53: Total assets | B53: =B52+B43 -> 1082131 | C53: =C52+C43 -> 1362399 | D53: =D52+D43 -> 1043325 | E53: =E52+E43 -> 1420509 | F53: =F52+F43 -> 1938875 | G53: =G52+G43 -> 5571277 | H53: =H52+H43 -> 4153471 | I53: =I52+I43 -> 4791012 | ... Q53: =Q52+Q43 -> 9549945
A55: Current liabilitiies
A56: Short term debt
A57: Accounts payable | B57: 85674 | C57: 113446 | D57: 127330 | E57: 119376 | F57: 127641 | G57: 144763 | H57: 193270 | I57: 245910 | J57: 248760 | K57: 274045 | L57: 296800 | M57: 404263 | N57: 444265 | O57: 564379 | P57: 466775 | Q57: 565974
A58: Accrued liabilities | B58: 23811 | C58: 31966 | D58: 38916 | E58: 59113 | F58: 40271 | G58: 81786 | H58: 79526 | I58: 87475 | J58: 112507 | K58: 114075 | L58: 142653 | M58: 210964 | N58: 172991 | O58: 183988 | P58: 220764 | Q58: 306085
A59: Accrued distributor terminations | B59: 407 | G59: 11018 | H59: 8184 | I59: 91 | J59: 0
A60: Deferred revenue | B60: 10140 | C60: 11583 | D60: 12695 | E60: 13832 | F60: 49926 | G60: 32271 | H60: 41672 | I60: 43236 | J60: 44045 | L60: 45429 | M60: 42530 | N60: 43311 | O60: 41914 | P60: 45809 | Q60: 45323
A61: Customer deposit liabilities
A62: Accrued promotional allowances | B62: 0 | C62: 87746 | D62: 91208 | E62: 99470 | F62: 114047 | G62: 115530 | H62: 110237 | I62: 137998 | J62: 145741 | K62: 166761 | L62: 186658 | M62: 211461 | N62: 255631 | O62: 269061 | P62: 267711 | Q62: 384070
A63: Accrued compensation | B63: 7603 | C63: 10353 | D63: 12926 | E63: 14864 | F63: 17983 | G63: 22159 | H63: 30043 | I63: 34996 | J63: 39903 | L63: 55015 | M63: 65459 | N63: 72463 | O63: 87392 | P63: 92454 | Q63: 114023
A64: Income taxes payable | B64: 925 | C64: 10996 | D64: 5470 | E64: 9359 | F64: 5848 | G64: 2750 | H64: 7657 | I64: 10645 | J64: 10189 | K64: 14717 | L64: 23433 | M64: 30399 | N64: 13317 | O64: 14955 | P64: 4006 | Q64: 32305
A65: Current portion of long-term debt | B65: 274 | C65: 0 | D65: 0
A66: Total current liabilities | B66: =B56+B65+B64+B62+B58+B57+B61+B59+B60+B63 -> 128834 | C66: =C56+C65+C64+C62+C58+C57+C61+C59+C60+C63 -> 266090 | D66: =D56+D65+D64+D62+D58+D57+D61+D59+D60+D63 -> 288545 | E66: =E56+E65+E64+E62+E58+E57+E61+E59+E60+E63 -> 316014 | F66: =F56+F65+F64+F62+F58+F57+F61+F59+F60+F63 -> 355716 | G66: =G56+G65+G64+G62+G58+G57+G61+G59+G60+G63 -> 410277 | H66: =H56+H65+H64+H62+H58+H57+H61+H59+H60+H63 -> 470589 | I66: =I56+I65+I64+I62+I58+I57+I61+I59+I60+I63 -> 560351 | ... Q66: =Q56+Q65+Q64+Q62+Q58+Q57+Q61+Q59+Q60+Q63 -> 1447780
A68: Long-term liabilities
A69: Long-term debt | P69: 373951 | Q69: 0
A70: Deferred revenue | B70: 124899 | C70: 117151 | D70: 110383 | E70: 112216 | F70: 68009 | G70: 351590 | H70: 353173 | I70: 334354 | J70: 312224 | K70: 287469 | L70: 264436 | M70: 243249 | N70: 223800 | O70: 204251 | P70: 179008 | Q70: 159991
A71: Deferred income taxes | B71: 0 | C71: 0 | D71: 0 | E71: 0 | F71: 0 | G71: 0 | H71: 0
A72: Other Liabilities | I72: 1095 | J72: 2621 | L72: 27432 | M72: 29508 | N72: 42286 | O72: 91838 | P72: 110893 | Q72: 127066
A73: Total long term liabilities | B73: =B70+B69+B71+B72 -> 124899 | C73: =C70+C69+C71+C72 -> 117151 | D73: =D70+D69+D71+D72 -> 110383 | E73: =E70+E69+E71+E72 -> 112216 | F73: =F70+F69+F71+F72 -> 68009 | G73: =G70+G69+G71+G72 -> 351590 | H73: =H70+H69+H71+H72 -> 353173 | I73: =I70+I69+I71+I72 -> 335449 | ... Q73: =Q70+Q69+Q71+Q72 -> 287057
A74: Total liabilities | B74: =B73+B66 -> 253733 | C74: =C73+C66 -> 383241 | D74: =D73+D66 -> 398928 | E74: =E73+E66 -> 428230 | F74: =F73+F66 -> 423725 | G74: =G73+G66 -> 761867 | H74: =H73+H66 -> 823762 | I74: =I73+I66 -> 895800 | ... Q74: =Q73+Q66 -> 1734837
A76: Equity
A77: Common stock | B77: 494 | C77: 994 | D77: 1019 | E77: 1030 | F77: 1035 | G77: 3105 | H77: 3116 | I77: 3146 | J77: 3155 | K77: 3182 | L77: 3193 | M77: 3200 | N77: 6418 | O77: 5613 | P77: 5632 | Q77: 5665
A78: Additional paid-in capital | B78: 187040 | C78: 229301 | D78: 287953 | E78: 368069 | F78: 426145 | G78: 3989787 | H78: 4051245 | I78: 4150628 | J78: 4238170 | K78: 4397511 | L78: 4537982 | M78: 4652620 | N78: 4776804 | O78: 4975115 | P78: 5144922 | Q78: 5430847
A79: Retained earnings / accumulated deficit | B79: 882425 | C79: 1168644 | D79: 1508664 | E79: 1847325 | F79: 2330510 | G79: 1394863 | H79: 2107548 | I79: 2928226 | J79: 3914645 | K79: 5022480 | L79: 6432074 | M79: 7809549 | N79: 9001173 | O79: 5939736 | P79: 7448784 | Q79: 9354216
A80: Accumulated other comprehensive income (loss) | B80: 281 | C80: -1547 | D80: 2074 | E80: -1233 | F80: -11453 | G80: -21878 | H80: -23249 | I80: -16659 | J80: -32864 | K80: -32387 | L80: 3034 | M80: -69165 | N80: -159073 | O80: -125337 | P80: -269487 | Q80: -60841
A81: Treasury stock | B81: -241842 | C81: -418234 | D81: -1155313 | E81: -1222912 | F81: -1231087 | G81: -556467 | H81: -2808951 | I81: -3170129 | J81: -4512205 | K81: -5219505 | L81: -5815423 | M81: -5829253 | N81: -6600281 | O81: -2566383 | P81: -6372133 | Q81: -6475779
A82: Total stockholders' equity | B82: =B81+B80+B79+B78+B77 -> 828398 | C82: =C81+C80+C79+C78+C77 -> 979158 | D82: =D81+D80+D79+D78+D77 -> 644397 | E82: =E81+E80+E79+E78+E77 -> 992279 | F82: =F81+F80+F79+F78+F77 -> 1515150 | G82: =G81+G80+G79+G78+G77 -> 4809410 | H82: =H81+H80+H79+H78+H77 -> 3329709 | I82: =I81+I80+I79+I78+I77 -> 3895212 | ... Q82: =Q81+Q80+Q79+Q78+Q77 -> 8254108
A83: Total liabilities and stockholders' equity | B83: =B82+B74 -> 1082131 | C83: =C82+C74 -> 1362399 | D83: =D82+D74 -> 1043325 | E83: =E82+E74 -> 1420509 | F83: =F82+F74 -> 1938875 | G83: =G82+G74 -> 5571277 | H83: =H82+H74 -> 4153471 | I83: =I82+I74 -> 4791012 | ... Q83: =Q82+Q74 -> 9988945
A87: Monster-US
A88: Financial Ratios ($'000)
B89: 2010 | C89: =B89+1 -> 2011 | D89: =C89+1 -> 2012 | E89: =D89+1 -> 2013 | F89: =E89+1 -> 2014 | G89: =F89+1 -> 2015 | H89: =G89+1 -> 2016 | I89: =H89+1 -> 2017 | J89: =I89+1 -> 2018 | ... N89: =M89+1 -> 2022 | O89: 2023 | P89: 2024 | Q89: 2025
A90: Profitability Ratios:
A91: Revenue 15yr CAGR | Q91: =(Q10/B10)^(1/15)-1 -> 0.13127515
A92: Revenue Growth rate | C92: =C10/B10-1 -> 0.30621607 | D92: =D10/C10-1 -> 0.20987888 | E92: =E10/D10-1 -> 0.090127539 | F92: =F10/E10-1 -> 0.097238371 | G92: =G10/F10-1 -> 0.10454803 | H92: =H10/G10-1 -> 0.12004456 | I92: =I10/H10-1 -> 0.1048248 | J92: =J10/I10-1 -> 0.13004813 | ... Q92: =Q10/P10-1 -> 0.10698854
A93: Gross Profit % | B93: =B12/B10 -> 0.52167965 | C93: =C12/C10 -> 0.52506649 | D93: =D12/D10 -> 0.51713251 | E93: =E12/E10 -> 0.52213158 | F93: =F12/F10 -> 0.5435628 | G93: =G12/G10 -> 0.5995455 | H93: =H12/H10 -> 0.63684805 | I93: =I12/I10 -> 0.63450919 | ... Q93: =Q12/Q10 -> 0.55847642
A94: EBIT Margin % | B94: =B19/B10 -> 0.26674039 | C94: =C19/C10 -> 0.26797497 | D94: =D19/D10 -> 0.26720166 | E94: =E19/E10 -> 0.25503421 | F94: =F19/F10 -> 0.30326383 | G94: =G19/G10 -> 0.26893142 | H94: =H19/H10 -> 0.35591936 | I94: =I19/I10 -> 0.35582398 | ... Q94: =Q19/Q10 -> 0.29168724
A95: Net Profit Margin % | B95: =B27/B10 -> 0.161465 | C95: =C27/C10 -> 0.16754754 | D95: =D27/D10 -> 0.16571489 | E95: =E27/E10 -> 0.15477149 | F95: =F27/F10 -> 0.19672542 | G95: =G27/G10 -> 0.14305375 | H95: =H27/H10 -> 0.23742135 | I95: =I27/I10 -> 0.2419101 | ... Q95: =Q27/Q10 -> 0.21449342
A96: ROE % | C96: =C27/AVERAGE(B82:C82) -> 0.31575453 | D96: =D27/AVERAGE(C82:D82) -> 0.42066822 | E96: =E27/AVERAGE(D82:E82) -> 0.42486479 | F96: =F27/AVERAGE(E82:F82) -> 0.38677227 | G96: =G27/AVERAGE(F82:G82) -> 0.12316209 | H96: =H27/AVERAGE(G82:H82) -> 0.17790402 | I96: =I27/AVERAGE(H82:I82) -> 0.22560966 | J96: =J27/AVERAGE(I82:J82) -> 0.25944134 | ... Q96: =Q27/AVERAGE(P82:Q82) -> 0.25036642 | R96: Average equity
A97: ROA % | C97: =C27/AVERAGE(B53:C53) -> 0.23347801 | D97: =D27/AVERAGE(C53:D53) -> 0.28389707 | E97: =E27/AVERAGE(D53:E53) -> 0.28222924 | F97: =F27/AVERAGE(E53:F53) -> 0.28868507 | G97: =G27/AVERAGE(F53:G53) -> 0.10371907 | H97: =H27/AVERAGE(G53:H53) -> 0.14889661 | I97: =I27/AVERAGE(H53:I53) -> 0.18223658 | J97: =J27/AVERAGE(I53:J53) -> 0.20899509 | ... Q97: =Q27/AVERAGE(P53:Q53) -> 0.20604302 | R97: Average assets
A100: Liquidity Ratios:
A101: Current Ratio | B101: =B43/B66 -> 6.9713973 | C101: =C43/C66 -> 4.4446503 | D101: =D43/D66 -> 2.8940651 | E101: =E43/E66 -> 3.7436411 | F101: =F43/F66 -> 4.7606208 | G101: =G43/G66 -> 8.7734189 | H101: =H43/H66 -> 3.0435688 | I101: =I43/I66 -> 3.7233395 | ... Q101: =Q43/Q66 -> 3.7029687
A102: Acid Test Ratio | B102: =(B43-B38)/B66 -> 5.781952 | C102: =(C43-C38)/C66 -> 3.8598369 | D102: =(D43-D38)/D66 -> 2.1901679 | E102: =(E43-E38)/E66 -> 3.0428842 | F102: =(F43-F38)/F66 -> 4.2698557 | G102: =(G43-G38)/G66 -> 8.3928931 | H102: =(H43-H38)/H66 -> 2.699381 | I102: =(I43-I38)/I66 -> 3.266938 | ... Q102: =(Q43-Q38)/Q66 -> 3.1506589
A103: Net Working Capital | B103: =B43-B66 -> 769319 | C103: =C43-C66 -> 916587 | D103: =D43-D66 -> 546523 | E103: =E43-E66 -> 867029 | F103: =F43-F66 -> 1337713 | G103: =G43-G66 -> 3189255 | H103: =H43-H66 -> 961681 | I103: =I43-I66 -> 1526026 | ... Q103: =Q43-Q66 -> 3913304
A105: Efficiency Ratios:
A106: Inventory Turnover Ratio. times | C106: =C11/AVERAGE(B38:C38) -> 5.2382096 | D106: =D11/AVERAGE(C38:D38) -> 5.5477742 | E106: =E11/AVERAGE(D38:E38) -> 5.0570456 | F106: =F11/AVERAGE(E38:F38) -> 5.6817904 | G106: =G11/AVERAGE(F38:G38) -> 6.5937876 | H106: =H11/AVERAGE(G38:H38) -> 6.9627215 | I106: =I11/AVERAGE(H38:I38) -> 5.8956564 | J106: =J11/AVERAGE(I38:J38) -> 5.6680401 | ... Q106: =Q11/AVERAGE(P38:Q38) -> 4.7661567 | R106: COGS/Average inventory | S106: ..
A107: Accounts Receivables Turnover Ratio. times | C107: =C10/AVERAGE(B37:C37) -> 10.632694 | D107: =D10/AVERAGE(C37:D37) -> 9.0490613 | E107: =E10/AVERAGE(D37:E37) -> 8.4311134 | F107: =F10/AVERAGE(E37:F37) -> 8.5446957 | G107: =G10/AVERAGE(F37:G37) -> 7.1768238 | H107: =H10/AVERAGE(G37:H37) -> 5.802808 | I107: =I10/AVERAGE(H37:I37) -> 6.5896451 | J107: =J10/AVERAGE(I37:J37) -> 8.1520945 | ... Q107: =Q10/AVERAGE(P37:Q37) -> 5.8416667 | R107: Revenue/Average Receivables | S107: ..
A108: Accounts Payable Turnover Ratio. times | C108: =C11/AVERAGE(B57:C57) -> 8.1249598 | D108: =D11/AVERAGE(C57:D57) -> 8.2653254 | E108: =E11/AVERAGE(D57:E57) -> 8.702642 | F108: =F11/AVERAGE(E57:F57) -> 9.1091463 | G108: =G11/AVERAGE(F57:G57) -> 8.0047503 | H108: =H11/AVERAGE(G57:H57) -> 6.5519816 | I108: =I11/AVERAGE(H57:I57) -> 5.6075186 | J108: =J11/AVERAGE(I57:J57) -> 6.1123901 | ... Q108: =Q11/AVERAGE(P57:Q57) -> 7.0920388 | R108: Cogs/Average Accounts Payable | S108: ..
A109: Inventory Processing Period. days | C109: =360/C106 -> 68.725772 | D109: =360/D106 -> 64.890889 | E109: =360/E106 -> 71.18781 | F109: =360/F106 -> 63.36031 | G109: =360/G106 -> 54.596845 | H109: =360/H106 -> 51.703921 | I109: =360/I106 -> 61.061903 | J109: =360/J106 -> 63.514018 | ... Q109: =360/Q106 -> 75.532556 | R109: 360/COGS/Average inventory | S109: ..
A110: Accounts Receivables Collection Period. Days | C110: =360/C107 -> 33.857835 | D110: =360/D107 -> 39.783132 | E110: =360/E107 -> 42.698987 | F110: =360/F107 -> 42.131401 | G110: =360/G107 -> 50.161465 | H110: =360/H107 -> 62.03893 | I110: =360/I107 -> 54.631167 | J110: =360/J107 -> 44.16043 | ... Q110: =360/Q107 -> 61.626248 | R110: 360/Revenue/Average Receivables | S110: ..
A111: Accounts Payable Payment Period. Days | C111: =360/C108 -> 44.307911 | D111: =360/D108 -> 43.555454 | E111: =360/E108 -> 41.366748 | F111: =360/F108 -> 39.520718 | G111: =360/G108 -> 44.973295 | H111: =360/H108 -> 54.945209 | I111: =360/I108 -> 64.19952 | J111: =360/J108 -> 58.896765 | ... Q111: =360/Q108 -> 50.761143 | R111: 360/COGS/Average Accounts Payable | S111: ..
A112: Asset Turnover Ratio. times | C112: =C10/AVERAGE(B53:C53) -> 1.393503 | D112: =D10/AVERAGE(C53:D53) -> 1.7131658 | E112: =E10/AVERAGE(D53:E53) -> 1.8235222 | F112: =F10/AVERAGE(E53:F53) -> 1.4674518 | G112: =G10/AVERAGE(F53:G53) -> 0.72503566 | H112: =H10/AVERAGE(G53:H53) -> 0.62714078 | I112: =I10/AVERAGE(H53:I53) -> 0.75332359 | J112: =J10/AVERAGE(I53:J53) -> 0.81717592 | ... Q112: =Q10/AVERAGE(P53:Q53) -> 0.96060301 | R112: Revenue/Average Assets | S112: ..
A115: Leverage Ratios:
A116: Debt to Equity | B116: 0 | C116: 0 | D116: 0 | E116: 0 | F116: 0 | G116: 0 | H116: 0 | I116: 0 | J116: 0 | K116: 0 | L116: 0 | M116: 0 | N116: 0 | O116: 0 | P116: 0 | Q116: 0
A117: Long-Term Debt to Total Capital % | B117: 0 | C117: 0 | D117: 0 | E117: 0 | F117: 0 | G117: 0 | H117: 0 | I117: 0 | J117: 0 | K117: 0 | L117: 0 | M117: 0 | N117: 0 | O117: 0 | P117: 0 | Q117: 0

Sheet Investment Analysis (1)
A1: Solvency and Net Asset Value (NAV)
A2: Investment Performance Ratio (Market ratios)
A3: Sustainable Growth Rate (SGR)
A4: Du Pont Analysis
A6: Monster-US
A7: Income Statement ($'000)
B8: 2010 | C8: =B8+1 -> 2011 | D8: =C8+1 -> 2012 | E8: =D8+1 -> 2013 | F8: =E8+1 -> 2014 | G8: =F8+1 -> 2015 | H8: =G8+1 -> 2016 | I8: =H8+1 -> 2017 | J8: =I8+1 -> 2018 | ... N8: =M8+1 -> 2022 | O8: FY2023A | P8: FY2024A | Q8: FY2025A
A9: Net sales | B9: 1303942 | C9: 1703230 | D9: 2060702 | E9: 2246428 | F9: 2464867 | G9: 2722564 | H9: 3049393 | I9: 3369045 | J9: 3807183 | K9: 4200819 | L9: 4598638 | M9: 5541352 | N9: 6311050 | O9: 7140027 | P9: 7492709 | Q9: 8294343
A10: Cost of sales | B10: 623702 | C10: 808921 | D10: 995046 | E10: 1073497 | F10: 1125057 | G10: 1090263 | H10: 1107393 | I10: 1231355 | J10: 1511808 | K10: 1682234 | L10: 1874758 | M10: 2432839 | N10: 3136483 | O10: 3345821 | P10: 3443831 | Q10: 3662148
A11: Gross profit | B11: =B9-B10 -> 680240 | C11: =C9-C10 -> 894309 | D11: =D9-D10 -> 1065656 | E11: =E9-E10 -> 1172931 | F11: =F9-F10 -> 1339810 | G11: =G9-G10 -> 1632301 | H11: =H9-H10 -> 1942000 | I11: =I9-I10 -> 2137690 | ... Q11: =Q9-Q10 -> 4632195
A13: Selling, general and administrative | B13: 0 | C13: 0 | D13: 0 | E13: 0 | F13: 0 | G13: 0 | H13: 0 | I13: 0 | J13: 0 | K13: 0 | L13: 0 | M13: 0 | N13: 0 | O13: 0 | P13: 0 | Q13: 0
A14: Freight-Out-Cots | B14: 47400 | C14: 60500 | D14: 76100 | E14: 84000 | F14: 92700 | G14: 87000 | H14: 83600 | I14: 91900 | J14: 128500 | K14: 122500 | L14: 134100 | M14: 213900 | N14: 249200 | O14: 223600 | P14: 224200 | Q14: 237000
A15: Advertising and Promotional | B15: 104900 | C15: 148800 | D15: 165400 | E15: 181800 | F15: 171500 | G15: 209700 | H15: 270600 | I15: 324000 | J15: 353900 | K15: 391600 | L15: 345700 | M15: 417600 | N15: 460700 | O15: 528900 | P15: 584100 | Q15: 599900
A16: Other Expenses | B16: 180126 | C16: 228586 | D16: 273533 | E16: 334215 | F16: 328105 | G16: 603418 | H16: 502462 | I16: 523003 | J16: 529356 | K16: 601546 | L16: 610927 | M16: 679546 | N16: 879946 | O16: 1088351 | P16: 1310284 | Q16: 1375941
A17: Total Operating expenses | B17: =B16+B15+B14+B13 -> 332426 | C17: =C16+C15+C14+C13 -> 437886 | D17: =D16+D15+D14+D13 -> 515033 | E17: =E16+E15+E14+E13 -> 600015 | F17: =F16+F15+F14+F13 -> 592305 | G17: =G16+G15+G14+G13 -> 900118 | H17: =H16+H15+H14+H13 -> 856662 | I17: =I16+I15+I14+I13 -> 938903 | ... Q17: =Q16+Q15+Q14+Q13 -> 2212841
A18: Operating income (loss) | B18: =B11-B17 -> 347814 | C18: =C11-C17 -> 456423 | D18: =D11-D17 -> 550623 | E18: =E11-E17 -> 572916 | F18: =F11-F17 -> 747505 | G18: =G11-G17 -> 732183 | H18: =H11-H17 -> 1085338 | I18: =I11-I17 -> 1198787 | ... Q18: =Q11-Q17 -> 2419354
A20: Interest income | B20: 0 | C20: 0 | D20: 0 | E20: 0 | F20: 0 | G20: 0 | H20: 0 | I20: 0 | J20: 0 | K20: 0 | L20: 0 | M20: 0 | N20: 0 | O20: 0 | P20: 0 | Q20: 0
A21: Interest expense | B21: 0 | C21: 0 | D21: 0 | E21: 0 | F21: 0 | G21: 0 | H21: 0 | I21: 0 | J21: 0 | K21: 0 | L21: 0 | M21: 0 | N21: 0 | O21: 0 | P21: 0 | Q21: 0
A22: Other income (expense), net | B22: 0 | C22: 0 | D22: 0 | E22: 0 | F22: 0 | G22: -2105 | H22: -5653 | I22: 2836 | J22: 9653 | K22: 13023 | L22: -6996 | M22: 3952 | N22: -12757 | O22: 115127 | P22: 59165 | Q22: 63175
A23: Income before income taxes | B23: =B18-B21+B20-B22 -> 347814 | C23: =C18-C21+C20-C22 -> 456423 | D23: =D18-D21+D20-D22 -> 550623 | E23: =E18-E21+E20-E22 -> 572916 | F23: =F18-F21+F20-F22 -> 747505 | G23: =G18-G21+G20-G22 -> 734288 | H23: =H18-H21+H20-H22 -> 1090991 | I23: =I18-I21+I20-I22 -> 1195951 | ... Q23: =Q18-Q21+Q20-Q22 -> 2356179
A25: Provision for income taxes | B25: 137273 | C25: 171051 | D25: 209134 | E25: 225233 | F25: 262603 | G25: 344815 | H25: 367000 | I25: 380945 | J25: 300268 | K25: 308127 | L25: 216563 | M25: 423944 | N25: 380340 | O25: 437494 | P25: 480411 | Q25: 577097
A26: Net income (loss) | B26: =B23-B25 -> 210541 | C26: =C23-C25 -> 285372 | D26: =D23-D25 -> 341489 | E26: =E23-E25 -> 347683 | F26: =F23-F25 -> 484902 | G26: =G23-G25 -> 389473 | H26: =H23-H25 -> 723991 | I26: =I23-I25 -> 815006 | ... Q26: =Q23-Q25 -> 1779082
A28: Basic weighted average shares | B28: 88514 | C28: 176212 | D28: 173712 | E28: 166679 | F28: 167257 | G28: 188816 | H28: 587874 | I28: 566782 | J28: 557166 | K28: 542191 | L28: 529639 | M28: 528763 | N28: 1053558 | O28: 1044887 | P28: 1004566 | Q28: =975887*2 -> 1951774
A29: Diluted weighted average shares | B29: 93021 | C29: 186674 | D29: 183083 | E29: 173387 | F29: 174285 | G29: 192586 | H29: 599819 | I29: 577141 | J29: 564254 | K29: 546608 | L29: 534807 | M29: 535639 | N29: 1066442 | O29: 1057981 | P29: 1013107 | Q29: =984451*2 -> 1968902
A31: Monster-US
A32: Balance Sheet ($'000)
B33: 2010 | C33: =B33+1 -> 2011 | D33: =C33+1 -> 2012 | E33: =D33+1 -> 2013 | F33: =E33+1 -> 2014 | G33: =F33+1 -> 2015 | H33: =G33+1 -> 2016 | I33: =H33+1 -> 2017 | J33: =I33+1 -> 2018 | ... N33: =M33+1 -> 2022 | O33: 2023 | P33: =O33+1 -> 2024 | Q33: =P33+1 -> 2025
A34: Current assets
A35: Cash and cash equivalents | B35: 354842 | C35: 359331 | D35: 222514 | E35: 211349 | F35: 370323 | G35: 2175417 | H35: 377582 | I35: 528622 | J35: 637513 | K35: 797957 | L35: 1180413 | M35: 1326462 | N35: 1307141 | O35: 2297675 | P35: 1533287 | Q35: 2088117
A36: Short-term investments | B36: 244649 | C36: 411282 | D36: 97042 | E36: 402247 | F36: 781134 | G36: 744610 | H36: 220554 | I36: 672933 | J36: 320650 | K36: 533063 | L36: 881354 | M36: 1749727 | N36: 1362314 | O36: 955605 | P36: 0 | Q36: 677084
A37: Accounts receivable, net | B37: 101635 | C37: 218741 | D37: 236710 | E37: =291638+4542 -> 296180 | F37: =280203+552 -> 280755 | G37: =352955+125000 -> 477955 | H37: =448051+125000 -> 573051 | I37: 449476 | J37: 484562 | K37: 540330 | L37: 666012 | M37: 896658 | N37: 1016203 | O37: 1193964 | P37: 1221646 | Q37: 1618072
A38: Inventories | B38: 153241 | C38: 155613 | D38: 203106 | E38: 221449 | F38: 174573 | G38: 156121 | H38: 161971 | I38: 255745 | J38: 277705 | K38: 360731 | L38: 333085 | M38: 593357 | N38: 935631 | O38: 971406 | P38: 737107 | Q38: 799623
A39: Prepaid expenses and other current assets | B39: 17022 | C39: 20912 | D39: 24983 | E39: 21376 | F39: 19673 | G39: 26967 | H39: 32562 | I39: 40877 | J39: 44909 | K39: 54868 | L39: 55358 | M39: 82668 | N39: 109823 | O39: 116195 | P39: 107262 | Q39: 103551
A40: Intangibles held-for-sale | E40: 0 | F40: 18079 | G40: 0 | H40: 0
A41: Prepaid Income Taxes | B41: 9992 | C41: 370 | D41: 33709 | E41: 9518 | F41: 8617 | G41: 18462 | H41: 66550 | I41: 138724 | J41: 38831 | L41: 24733 | M41: 33238 | N41: 33785 | O41: 54151 | P41: 42202 | Q41: 74637
A42: Deferred income tax | B42: 16772 | C42: 16428 | D42: 17004 | E42: 20924 | F42: 40275 | G42: 0 | H42: 0
A43: Total current assets | B43: =B42+B39+B38+B37+B36+B35+B41+B40 -> 898153 | C43: =C42+C39+C38+C37+C36+C35+C41+C40 -> 1182677 | D43: =D42+D39+D38+D37+D36+D35+D41+D40 -> 835068 | E43: =E42+E39+E38+E37+E36+E35+E41+E40 -> 1183043 | F43: =F42+F39+F38+F37+F36+F35+F41+F40 -> 1693429 | G43: =G42+G39+G38+G37+G36+G35+G41+G40 -> 3599532 | H43: =H42+H39+H38+H37+H36+H35+H41+H40 -> 1432270 | I43: =I42+I39+I38+I37+I36+I35+I41+I40 -> 2086377 | ... Q43: =Q42+Q39+Q38+Q37+Q36+Q35+Q41+Q40 -> 5361084
A45: Long-term assets
A46: Investments | B46: 44189 | C46: 23194 | D46: 21393 | E46: 9792 | F46: 42940 | G46: 15348 | H46: 2394 | I46: 2366 | L46: 44291 | M46: 99419 | N46: 61443 | O46: 76431 | P46: 0 | Q46: 48329
A47: Property and equipment, net | B47: 34551 | C47: 45151 | D47: 69137 | E47: 88143 | F47: 90156 | G47: 97354 | H47: 173343 | I47: 230276 | J47: 243051 | K47: 298640 | L47: 314656 | M47: 313753 | N47: 516897 | O47: 890796 | P47: 1047024 | Q47: 1081544
A48: Deferred Income Taxes | B48: 58475 | C48: 58576 | D48: 59503 | E48: 63611 | F48: 54106 | G48: 140468 | H48: 159556 | I48: 92333 | J48: 85687 | L48: 241650 | M48: 225221 | N48: 177039 | O48: 175003 | P48: 184260 | Q48: 188646
A49: Intangible assets, net | B49: 43316 | C49: 48396 | D49: 54648 | E49: 65774 | F49: 50748 | G49: 427986 | H49: 1032635 | I49: 1034085 | J49: 1045878 | K49: 1052105 | L49: 1059046 | M49: 1072386 | N49: 1220410 | O49: 1427139 | P49: 1414252 | Q49: 1379268
A50: Goodwill | B50: 0 | C50: 0 | D50: 0 | E50: 0 | F50: 0 | G50: 1279715 | H50: 1331643 | I50: 1331643 | J50: 1331643 | K50: 1331643 | L50: 1331643 | M50: 1331643 | N50: 1417941 | O50: 1417941 | P50: 1331643 | Q50: 1331643
A51: Other assets | B51: 3447 | C51: 4405 | D51: 3576 | E51: 10146 | F51: 7496 | G51: 10874 | H51: 21630 | I51: 13932 | J51: 16462 | K51: 53973 | L51: 70475 | M51: 80252 | N51: 134478 | O51: 110216 | P51: 100406 | Q51: 159431
A52: Total long-term assets | B52: =B51+B50+B49+B47+B48+B46 -> 183978 | C52: =C51+C50+C49+C47+C48+C46 -> 179722 | D52: =D51+D50+D49+D47+D48+D46 -> 208257 | E52: =E51+E50+E49+E47+E48+E46 -> 237466 | F52: =F51+F50+F49+F47+F48+F46 -> 245446 | G52: =G51+G50+G49+G47+G48+G46 -> 1971745 | H52: =H51+H50+H49+H47+H48+H46 -> 2721201 | I52: =I51+I50+I49+I47+I48+I46 -> 2704635 | ... Q52: =Q51+Q50+Q49+Q47+Q48+Q46 -> 4188861
A53: Total assets | B53: =B52+B43 -> 1082131 | C53: =C52+C43 -> 1362399 | D53: =D52+D43 -> 1043325 | E53: =E52+E43 -> 1420509 | F53: =F52+F43 -> 1938875 | G53: =G52+G43 -> 5571277 | H53: =H52+H43 -> 4153471 | I53: =I52+I43 -> 4791012 | ... Q53: =Q52+Q43 -> 9549945
A55: Current liabilitiies
A56: Short term debt
A57: Accounts payable | B57: 85674 | C57: 113446 | D57: 127330 | E57: 119376 | F57: 127641 | G57: 144763 | H57: 193270 | I57: 245910 | J57: 248760 | K57: 274045 | L57: 296800 | M57: 404263 | N57: 444265 | O57: 564379 | P57: 466775 | Q57: 565974
A58: Accrued liabilities | B58: 23811 | C58: 31966 | D58: 38916 | E58: 59113 | F58: 40271 | G58: 81786 | H58: 79526 | I58: 87475 | J58: 112507 | K58: 114075 | L58: 142653 | M58: 210964 | N58: 172991 | O58: 183988 | P58: 220764 | Q58: 306085
A59: Accrued distributor terminations | B59: 407 | G59: 11018 | H59: 8184 | I59: 91 | J59: 0
A60: Deferred revenue | B60: 10140 | C60: 11583 | D60: 12695 | E60: 13832 | F60: 49926 | G60: 32271 | H60: 41672 | I60: 43236 | J60: 44045 | L60: 45429 | M60: 42530 | N60: 43311 | O60: 41914 | P60: 45809 | Q60: 45323
A61: Customer deposit liabilities
A62: Accrued promotional allowances | B62: 0 | C62: 87746 | D62: 91208 | E62: 99470 | F62: 114047 | G62: 115530 | H62: 110237 | I62: 137998 | J62: 145741 | K62: 166761 | L62: 186658 | M62: 211461 | N62: 255631 | O62: 269061 | P62: 267711 | Q62: 384070
A63: Accrued compensation | B63: 7603 | C63: 10353 | D63: 12926 | E63: 14864 | F63: 17983 | G63: 22159 | H63: 30043 | I63: 34996 | J63: 39903 | L63: 55015 | M63: 65459 | N63: 72463 | O63: 87392 | P63: 92454 | Q63: 114023
A64: Income taxes payable | B64: 925 | C64: 10996 | D64: 5470 | E64: 9359 | F64: 5848 | G64: 2750 | H64: 7657 | I64: 10645 | J64: 10189 | K64: 14717 | L64: 23433 | M64: 30399 | N64: 13317 | O64: 14955 | P64: 4006 | Q64: 32305
A65: Current portion of long-term debt | B65: 274 | C65: 0 | D65: 0
A66: Total current liabilities | B66: =B56+B65+B64+B62+B58+B57+B61+B59+B60+B63 -> 128834 | C66: =C56+C65+C64+C62+C58+C57+C61+C59+C60+C63 -> 266090 | D66: =D56+D65+D64+D62+D58+D57+D61+D59+D60+D63 -> 288545 | E66: =E56+E65+E64+E62+E58+E57+E61+E59+E60+E63 -> 316014 | F66: =F56+F65+F64+F62+F58+F57+F61+F59+F60+F63 -> 355716 | G66: =G56+G65+G64+G62+G58+G57+G61+G59+G60+G63 -> 410277 | H66: =H56+H65+H64+H62+H58+H57+H61+H59+H60+H63 -> 470589 | I66: =I56+I65+I64+I62+I58+I57+I61+I59+I60+I63 -> 560351 | ... Q66: =Q56+Q65+Q64+Q62+Q58+Q57+Q61+Q59+Q60+Q63 -> 1447780
A68: Long-term liabilities
A69: Long-term debt | P69: 373951 | Q69: 0
A70: Deferred revenue | B70: 124899 | C70: 117151 | D70: 110383 | E70: 112216 | F70: 68009 | G70: 351590 | H70: 353173 | I70: 334354 | J70: 312224 | K70: 287469 | L70: 264436 | M70: 243249 | N70: 223800 | O70: 204251 | P70: 179008 | Q70: 159991
A71: Deferred income taxes | B71: 0 | C71: 0 | D71: 0 | E71: 0 | F71: 0 | G71: 0 | H71: 0
A72: Other Liabilities | I72: 1095 | J72: 2621 | L72: 27432 | M72: 29508 | N72: 42286 | O72: 91838 | P72: 110893 | Q72: 127066
A73: Total long term liabilities | B73: =B70+B69+B71+B72 -> 124899 | C73: =C70+C69+C71+C72 -> 117151 | D73: =D70+D69+D71+D72 -> 110383 | E73: =E70+E69+E71+E72 -> 112216 | F73: =F70+F69+F71+F72 -> 68009 | G73: =G70+G69+G71+G72 -> 351590 | H73: =H70+H69+H71+H72 -> 353173 | I73: =I70+I69+I71+I72 -> 335449 | ... Q73: =Q70+Q69+Q71+Q72 -> 287057
A74: Total liabilities | B74: =B73+B66 -> 253733 | C74: =C73+C66 -> 383241 | D74: =D73+D66 -> 398928 | E74: =E73+E66 -> 428230 | F74: =F73+F66 -> 423725 | G74: =G73+G66 -> 761867 | H74: =H73+H66 -> 823762 | I74: =I73+I66 -> 895800 | ... Q74: =Q73+Q66 -> 1734837
A76: Equity
A77: Common stock | B77: 494 | C77: 994 | D77: 1019 | E77: 1030 | F77: 1035 | G77: 3105 | H77: 3116 | I77: 3146 | J77: 3155 | K77: 3182 | L77: 3193 | M77: 3200 | N77: 6418 | O77: 5613 | P77: 5632 | Q77: 5665
A78: Additional paid-in capital | B78: 187040 | C78: 229301 | D78: 287953 | E78: 368069 | F78: 426145 | G78: 3989787 | H78: 4051245 | I78: 4150628 | J78: 4238170 | K78: 4397511 | L78: 4537982 | M78: 4652620 | N78: 4776804 | O78: 4975115 | P78: 5144922 | Q78: 5430847
A79: Retained earnings / accumulated deficit | B79: 882425 | C79: 1168644 | D79: 1508664 | E79: 1847325 | F79: 2330510 | G79: 1394863 | H79: 2107548 | I79: 2928226 | J79: 3914645 | K79: 5022480 | L79: 6432074 | M79: 7809549 | N79: 9001173 | O79: 5939736 | P79: 7448784 | Q79: 9354216
A80: Accumulated other comprehensive income (loss) | B80: 281 | C80: -1547 | D80: 2074 | E80: -1233 | F80: -11453 | G80: -21878 | H80: -23249 | I80: -16659 | J80: -32864 | K80: -32387 | L80: 3034 | M80: -69165 | N80: -159073 | O80: -125337 | P80: -269487 | Q80: -60841
A81: Treasury stock | B81: -241842 | C81: -418234 | D81: -1155313 | E81: -1222912 | F81: -1231087 | G81: -556467 | H81: -2808951 | I81: -3170129 | J81: -4512205 | K81: -5219505 | L81: -5815423 | M81: -5829253 | N81: -6600281 | O81: -2566383 | P81: -6372133 | Q81: -6475779
A82: Total stockholders' equity | B82: =B81+B80+B79+B78+B77 -> 828398 | C82: =C81+C80+C79+C78+C77 -> 979158 | D82: =D81+D80+D79+D78+D77 -> 644397 | E82: =E81+E80+E79+E78+E77 -> 992279 | F82: =F81+F80+F79+F78+F77 -> 1515150 | G82: =G81+G80+G79+G78+G77 -> 4809410 | H82: =H81+H80+H79+H78+H77 -> 3329709 | I82: =I81+I80+I79+I78+I77 -> 3895212 | ... Q82: =Q81+Q80+Q79+Q78+Q77 -> 8254108
A83: Total liabilities and stockholders' equity | B83: =B82+B74 -> 1082131 | C83: =C82+C74 -> 1362399 | D83: =D82+D74 -> 1043325 | E83: =E82+E74 -> 1420509 | F83: =F82+F74 -> 1938875 | G83: =G82+G74 -> 5571277 | H83: =H82+H74 -> 4153471 | I83: =I82+I74 -> 4791012 | ... Q83: =Q82+Q74 -> 9988945
S86: 15yr cagr
A87: Share price August 2026 | B87: 1.77 | C87: 3.23 | D87: 5.54 | E87: 5.12 | F87: 5.35 | G87: 12.88 | H87: 13.36 | I87: 13.23 | J87: 14.9 | K87: 16.2 | L87: 19.67 | M87: 23.62 | N87: 24.64 | O87: 28.8 | P87: 60.66 | Q87: 93.49 | S87: =(Q87/B87)^(1/15)-1 -> 0.30272514
Q88: 46.68
A90: Monster-US
A91: Investment Ratios ($'000)
B92: 2010 | C92: =B92+1 -> 2011 | D92: =C92+1 -> 2012 | E92: =D92+1 -> 2013 | F92: =E92+1 -> 2014 | G92: =F92+1 -> 2015 | H92: =G92+1 -> 2016 | I92: =H92+1 -> 2017 | J92: =I92+1 -> 2018 | ... N92: =M92+1 -> 2022 | O92: 2023 | P92: =O92+1 -> 2024 | Q92: =P92+1 -> 2025
A93: Name
A94: Solvency | B94: =B53-B74 -> 828398 | C94: =C53-C74 -> 979158 | D94: =D53-D74 -> 644397 | E94: =E53-E74 -> 992279 | F94: =F53-F74 -> 1515150 | G94: =G53-G74 -> 4809410 | H94: =H53-H74 -> 3329709 | I94: =I53-I74 -> 3895212 | ... Q94: =Q53-Q74 -> 7815108 | U94: Total Assets> Total liability
A95: Net Asset Value | U95: Net Asset value/Number of shares in issue -> excluding the Non controlling shareholders interest (NCI)
A97: Dividend yield | B97: 0 | C97: 0 | D97: 0 | E97: 0 | F97: 0 | G97: 0 | H97: 0 | I97: 0 | J97: 0 | K97: 0 | L97: 0 | M97: 0 | N97: 0 | O97: 0 | P97: 0 | Q97: 0 | S97: Average growth | U97: Dividend per share/ Market price per share
A98: Capital gains/Capital yield | C98: =C87/B87-1 -> 0.82485876 | D98: =D87/C87-1 -> 0.71517028 | E98: =E87/D87-1 -> -0.075812274 | F98: =F87/E87-1 -> 0.044921875 | G98: =G87/F87-1 -> 1.4074766 | H98: =H87/G87-1 -> 0.037267081 | I98: =I87/H87-1 -> -0.0097305389 | J98: =J87/I87-1 -> 0.12622827 | ... Q98: =Q87/P87-1 -> 0.54121332 | S98: =SUM(C98:Q98)/14 -> 0.3880084 | U98: (Price1 - Price0)/Price0
Q99: =Q88/P87-1 -> -0.23046489
A100: Headline Earnings Per Share | B100: =B26/B28 -> 2.3786181 | C100: =C26/C28 -> 1.6194811 | D100: =D26/D28 -> 1.9658343 | E100: =E26/E28 -> 2.0859436 | F100: =F26/F28 -> 2.8991432 | G100: =G26/G28 -> 2.0627118 | H100: =H26/H28 -> 1.2315411 | I100: =I26/I28 -> 1.4379532 | ... P100: =P26/P28 -> 1.3843968 | Q100: =Q26/(Q28/2) -> 1.823041 | U100: Headline earnings/Weighted No. of Class A shares in issue
A101: Price earnings ratio (Mid August) | Q101: =Q26/Q28 -> 0.91152049
A103: Payout ratio | Q103: 0 | U103: Dividends per share/headline earnings per share
A104: Retention ratio | Q104: =1-Q103 -> 1 | U104: 1- Payout ratio
A106: Price earnings ratio | B106: =B87/B100 -> 0.74412955 | C106: =C87/C100 -> 1.994466 | D106: =D87/D100 -> 2.818142 | E106: =E87/E100 -> 2.4545246 | F106: =F87/F100 -> 1.8453728 | G106: =G87/G100 -> 6.2442071 | H106: =H87/H100 -> 10.848197 | I106: =I87/I100 -> 9.2005775 | ... Q106: =Q87/Q100 -> 51.282445 | U106: Market price end of year/ Headline earnings per share
A107: Price earnings ratio (Mid August) | Q107: =Q88/Q101 -> 51.211136
A109: Earnings yield | B109: =B100/B87 -> 1.343852 | C109: =C100/C87 -> 0.50138733 | D109: =D100/D87 -> 0.35484373 | E109: =E100/E87 -> 0.40741087 | F109: =F100/F87 -> 0.54189593 | G109: =G100/G87 -> 0.16014844 | H109: =H100/H87 -> 0.092181221 | I109: =I100/I87 -> 0.10868883 | ... Q109: =Q100/Q87 -> 0.01949985 | U109: EPS/Market price per share
A110: Price earnings ratio (Mid August) | Q110: =Q101/Q88 -> 0.019527003
A112: Market value added/ MVA per share | B112: =(B87*B28)-B82 -> -671728.22 | C112: =(C87*C28)-C82 -> -409993.24 | D112: =(D87*D28)-D82 -> 317967.48 | E112: =(E87*E28)-E82 -> -138882.52 | F112: =(F87*F28)-F82 -> -620325.05 | G112: =(G87*G28)-G82 -> -2377459.9 | H112: =(H87*H28)-H82 -> 4524287.6 | I112: =(I87*I28)-I82 -> 3603313.9 | ... Q112: =(Q87*Q28)-Q82 -> 1.7421724e+08 | U112: Market capitalisation - (Total equity - NCI)
A113: Market Price to Book | B113: =(B87*B28)/B82 -> 0.1891238 | C113: =(C87*C28)/C82 -> 0.58127979 | D113: =(D87*D28)/D82 -> 1.4934341 | E113: =(E87*E28)/E82 -> 0.86003682 | F113: =(F87*F28)/F82 -> 0.59058506 | G113: =(G87*G28)/G82 -> 0.50566495 | H113: =(H87*H28)/H82 -> 2.3587637 | I113: =(I87*I28)/I82 -> 1.9250623 | ... Q113: =(Q87*Q28)/Q82 -> 22.106732 | U113: Market capitalisation/ Equity (Net of NCI)
A115: Sustainable growth ratio | C115: =$Q$104*'Financial Ratios'!C96 -> 0.31575453 | D115: =$Q$104*'Financial Ratios'!D96 -> 0.42066822 | E115: =$Q$104*'Financial Ratios'!E96 -> 0.42486479 | F115: =$Q$104*'Financial Ratios'!F96 -> 0.38677227 | G115: =$Q$104*'Financial Ratios'!G96 -> 0.12316209 | H115: =$Q$104*'Financial Ratios'!H96 -> 0.17790402 | I115: =$Q$104*'Financial Ratios'!I96 -> 0.22560966 | J115: =$Q$104*'Financial Ratios'!J96 -> 0.25944134 | ... Q115: =$Q$104*'Financial Ratios'!Q96 -> 0.25036642 | U115: ROE * Retention ratio
A116: Du pont analysis | C116: ='Financial Ratios'!C95*'Financial Ratios'!C112*('Investment Analysis (1)'!C53/'Investment Analysis (1)'!C82) -> 0.32486096 | D116: ='Financial Ratios'!D95*'Financial Ratios'!D112*('Investment Analysis (1)'!D53/'Investment Analysis (1)'!D82) -> 0.45964974 | E116: ='Financial Ratios'!E95*'Financial Ratios'!E112*('Investment Analysis (1)'!E53/'Investment Analysis (1)'!E82) -> 0.40402868 | F116: ='Financial Ratios'!F95*'Financial Ratios'!F112*('Investment Analysis (1)'!F53/'Investment Analysis (1)'!F82) -> 0.36941838 | G116: ='Financial Ratios'!G95*'Financial Ratios'!G112*('Investment Analysis (1)'!G53/'Investment Analysis (1)'!G82) -> 0.12014939 | H116: ='Financial Ratios'!H95*'Financial Ratios'!H112*('Investment Analysis (1)'!H53/'Investment Analysis (1)'!H82) -> 0.18573327 | I116: ='Financial Ratios'!I95*'Financial Ratios'!I112*('Investment Analysis (1)'!I53/'Investment Analysis (1)'!I82) -> 0.22414637 | J116: ='Financial Ratios'!J95*'Financial Ratios'!J112*('Investment Analysis (1)'!J53/'Investment Analysis (1)'!J82) -> 0.26201162 | ... Q116: ='Financial Ratios'!Q95*'Financial Ratios'!Q112*('Investment Analysis (1)'!Q53/'Investment Analysis (1)'!Q82) -> 0.23839033 | U116: ROE = Net margin*Total asset turnover*Equity multiplier

Sheet Monster Consolidated Statements
A1: Monster Beverage Corporation - Historical Financial Statements
A2: USD in $'000
A3: 1994 | B3: 1994 | C3: =B3+1 -> 1995 | D3: =C3+1 -> 1996 | E3: =D3+1 -> 1997 | F3: =E3+1 -> 1998 | G3: =F3+1 -> 1999 | H3: =G3+1 -> 2000 | I3: =H3+1 -> 2001 | J3: =I3+1 -> 2002 | ... AG3: =AF3+1 -> 2025
A5: INCOME STATEMENT | AI5: 31yr | AJ5: Check | AL5: 20yr | AM5: Check | AO5: 10yr | AP5: Check | AR5: 5yr | AS5: Check
A6: Net sales | B6: 28815.522 | C6: 33990.675 | D6: 35565.485 | E6: 43057.064 | F6: 53866.294 | G6: 72303.186 | H6: 79732.709 | I6: 92279.711 | J6: 92046.362 | K6: 110352.2 | L6: 180341.14 | M6: 348886.37 | N6: 605774 | O6: 904465 | P6: 1033780 | Q6: 1143299 | R6: 1303942 | S6: 1703230 | T6: 2060702 | U6: 2246428 | V6: 2464867 | W6: 2722564 | X6: 3049393 | Y6: 3369045 | Z6: 3807183 | AA6: 4200819 | AB6: 4598638 | AC6: 5541352 | AD6: 6311050 | AE6: 7140027 | AF6: 7492709 | AG6: 8294343 | AI6: =IFERROR((AG6/B6)^(1/31)-1,"") -> 0.20040445 | AJ6: =IFERROR(PRODUCT(1+C7,1+D7,1+E7,1+F7,1+G7,1+H7,1+I7,1+J7,1+K7,1+L7,1+M7,1+N7,1+O7,1+P7,1+Q7,1+R7,1+S7,1+T7,1+U7,1+V7,1+W7,1+X7,1+Y7,1+Z7,1+AA7,1+AB7,1+AC7,1+AD7,1+AE7,1+AF7,1+AG7)^(1/31)-1,"") -> 0.20040445 | AL6: =IFERROR((AG6/M6)^(1/20)-1,"") -> 0.17166889 | AM6: =IFERROR(PRODUCT(1+N7,1+O7,1+P7,1+Q7,1+R7,1+S7,1+T7,1+U7,1+V7,1+W7,1+X7,1+Y7,1+Z7,1+AA7,1+AB7,1+AC7,1+AD7,1+AE7,1+AF7,1+AG7)^(1/20)-1,"") -> 0.17166889 | AO6: =IFERROR((AG6/W6)^(1/10)-1,"") -> 0.11784191 | AP6: =IFERROR(PRODUCT(1+X7,1+Y7,1+Z7,1+AA7,1+AB7,1+AC7,1+AD7,1+AE7,1+AF7,1+AG7)^(1/10)-1,"") -> 0.11784191 | AR6: =IFERROR((AG6/AB6)^(1/5)-1,"") -> 0.12520215 | AS6: =IFERROR(PRODUCT(1+AC7,1+AD7,1+AE7,1+AF7,1+AG7)^(1/5)-1,"") -> 0.12520215
A7: % Growth | C7: =IFERROR((C6/B6-1),"") -> 0.17959602 | D7: =IFERROR((D6/C6-1),"") -> 0.046330648 | E7: =IFERROR((E6/D6-1),"") -> 0.21064183 | F7: =IFERROR((F6/E6-1),"") -> 0.25104429 | G7: =IFERROR((G6/F6-1),"") -> 0.3422714 | H7: =IFERROR((H6/G6-1),"") -> 0.10275513 | I7: =IFERROR((I6/H6-1),"") -> 0.1573633 | J7: =IFERROR((J6/I6-1),"") -> -0.002528714 | ... AG7: =IFERROR((AG6/AF6-1),"") -> 0.10698854 | AI7: 31yr | AJ7: Check | AL7: 20yr | AM7: Check | AO7: 10yr | AP7: Check | AR7: 5yr | AS7: Check
A8: Cost of sales | B8: 15886.142 | C8: 21855.369 | D8: 21671.064 | E8: 25222.881 | F8: 27332.028 | G8: 38776.532 | H8: 42646.677 | I8: 51455.207 | J8: 58802.669 | K8: 66577.168 | L8: 96874.75 | M8: 166343.12 | N8: 289180 | O8: 436452 | P8: 494986 | Q8: 530983 | R8: 623702 | S8: 808921 | T8: 995046 | U8: 1073497 | V8: 1125057 | W8: 1090263 | X8: 1107393 | Y8: 1231355 | Z8: 1511808 | AA8: 1682234 | AB8: 1874758 | AC8: 2432839 | AD8: 3136483 | AE8: 3345821 | AF8: 3443831 | AG8: 3662148 | AI8: =IFERROR((AG8/B8)^(1/31)-1,"") -> 0.19183653 | AJ8: =IFERROR(PRODUCT(1+C9,1+D9,1+E9,1+F9,1+G9,1+H9,1+I9,1+J9,1+K9,1+L9,1+M9,1+N9,1+O9,1+P9,1+Q9,1+R9,1+S9,1+T9,1+U9,1+V9,1+W9,1+X9,1+Y9,1+Z9,1+AA9,1+AB9,1+AC9,1+AD9,1+AE9,1+AF9,1+AG9)^(1/31)-1,"") -> 0.19183653 | AL8: =IFERROR((AG8/M8)^(1/20)-1,"") -> 0.16717655 | AM8: =IFERROR(PRODUCT(1+N9,1+O9,1+P9,1+Q9,1+R9,1+S9,1+T9,1+U9,1+V9,1+W9,1+X9,1+Y9,1+Z9,1+AA9,1+AB9,1+AC9,1+AD9,1+AE9,1+AF9,1+AG9)^(1/20)-1,"") -> 0.16717655 | AO8: =IFERROR((AG8/W8)^(1/10)-1,"") -> 0.128809 | AP8: =IFERROR(PRODUCT(1+X9,1+Y9,1+Z9,1+AA9,1+AB9,1+AC9,1+AD9,1+AE9,1+AF9,1+AG9)^(1/10)-1,"") -> 0.128809 | AR8: =IFERROR((AG8/AB8)^(1/5)-1,"") -> 0.14329456 | AS8: =IFERROR(PRODUCT(1+AC9,1+AD9,1+AE9,1+AF9,1+AG9)^(1/5)-1,"") -> 0.14329456
A9: % Growth | C9: =IFERROR((C8/B8-1),"") -> 0.37575058 | D9: =IFERROR((D8/C8-1),"") -> -0.0084329393 | E9: =IFERROR((E8/D8-1),"") -> 0.16389675 | F9: =IFERROR((F8/E8-1),"") -> 0.083620384 | G9: =IFERROR((G8/F8-1),"") -> 0.41872136 | H9: =IFERROR((H8/G8-1),"") -> 0.099806373 | I9: =IFERROR((I8/H8-1),"") -> 0.20654669 | J9: =IFERROR((J8/I8-1),"") -> 0.14279336 | ... AG9: =IFERROR((AG8/AF8-1),"") -> 0.063393645
A10: Gross profit | B10: =B6-B8 -> 12929.38 | C10: =C6-C8 -> 12135.306 | D10: =D6-D8 -> 13894.421 | E10: =E6-E8 -> 17834.183 | F10: =F6-F8 -> 26534.266 | G10: =G6-G8 -> 33526.654 | H10: =H6-H8 -> 37086.032 | I10: =I6-I8 -> 40824.504 | ... AG10: =AG6-AG8 -> 4632195
A11: % of Revenue | B11: =B10/$B$6 -> 0.44869498 | C11: =C10/C6 -> 0.35701868 | D11: =D10/D6 -> 0.39067149 | E11: =E10/E6 -> 0.41419877 | F11: =F10/F6 -> 0.49259498 | G11: =G10/G6 -> 0.46369539 | H11: =H10/H6 -> 0.46512946 | I11: =I10/I6 -> 0.44239956 | J11: =J10/J6 -> 0.36116249 | ... AG11: =AG10/AG6 -> 0.55847642
A13: Selling, general and administrative | B13: 13117.979 | C13: 12506.77 | D13: 12524.85 | E13: 15452.188 | F13: 20217.818 | G13: 25337.374 | H13: 29814.609 | I13: 34766.159 | J13: 27896.202 | K13: 33887.045 | L13: 49507.137 | M13: 79029.837 | N13: 0 | O13: 0 | P13: 0 | Q13: 0 | R13: 0 | S13: 0 | T13: 0 | U13: 0 | V13: 0 | W13: 0 | X13: 0 | Y13: 0 | Z13: 0 | AA13: 0 | AB13: 0 | AC13: 0 | AD13: 0 | AE13: 0 | AF13: 0 | AG13: 0
A14: % Growth | C14: =IFERROR((C13/B13-1),"") -> -0.046593229 | D14: =IFERROR((D13/C13-1),"") -> 0.0014456171 | E14: =IFERROR((E13/D13-1),"") -> 0.2337224 | F14: =IFERROR((F13/E13-1),"") -> 0.30841134 | G14: =IFERROR((G13/F13-1),"") -> 0.25322001 | H14: =IFERROR((H13/G13-1),"") -> 0.17670478 | I14: =IFERROR((I13/H13-1),"") -> 0.16607798 | J14: =IFERROR((J13/I13-1),"") -> -0.19760472 | ... AG14: =IFERROR((AG13/AF13-1),"")
A15: Freight-Out-Cots | N15: 36200 | O15: 40800 | P15: 45100 | Q15: 39800 | R15: 47400 | S15: 60500 | T15: 76100 | U15: 84000 | V15: 92700 | W15: 87000 | X15: 83600 | Y15: 91900 | Z15: 128500 | AA15: 122500 | AB15: 134100 | AC15: 213900 | AD15: 249200 | AE15: 223600 | AF15: 224200 | AG15: 237000
A16: % Growth
A17: Advertising and Promotional | N17: 35700 | O17: 66600 | P17: 84600 | Q17: 86700 | R17: 104900 | S17: 148800 | T17: 165400 | U17: 181800 | V17: 171500 | W17: 209700 | X17: 270600 | Y17: 324000 | Z17: 353900 | AA17: 391600 | AB17: 345700 | AC17: 417600 | AD17: 460700 | AE17: 528900 | AF17: 584100 | AG17: 599900
A18: % Growth
A19: Other Expenses | B19: 998.833 | C19: 935.244 | D19: 692.624 | E19: 500.086 | F19: 356.582 | G19: 688.226 | H19: 371.091 | I19: 507.441 | J19: 54.598 | K19: 61.855 | L19: 73.063 | M19: 70.063 | N19: 86115 | O19: 129627 | P19: 245503 | Q19: 148507 | R19: 180126 | S19: 228586 | T19: 273533 | U19: 334215 | V19: 328105 | W19: 603418 | X19: 502462 | Y19: 523003 | Z19: 529356 | AA19: 601546 | AB19: 610927 | AC19: 679546 | AD19: 879946 | AE19: 1088351 | AF19: 1310284 | AG19: 1375941
A20: % Growth | AI20: 31yr | AJ20: Check | AL20: 20yr | AM20: Check | AO20: 10yr | AP20: Check | AR20: 5yr | AS20: Check
A21: Total Operating expenses | B21: =B19+B13 -> 14116.812 | C21: =C19+C13 -> 13442.014 | D21: =D19+D13 -> 13217.474 | E21: =E19+E13 -> 15952.274 | F21: =F19+F13 -> 20574.4 | G21: =G19+G13 -> 26025.6 | H21: =H19+H13 -> 30185.7 | I21: =I19+I13 -> 35273.6 | ... M21: =M19+M13 -> 79099.9 | N21: =N19+N17+N15+N13 -> 158015 | O21: =O19+O17+O15+O13 -> 237027 | P21: =P19+P17+P15+P13 -> 375203 | Q21: =Q19+Q17+Q15+Q13 -> 275007 | R21: =R19+R17+R15+R13 -> 332426 | S21: =S19+S17+S15+S13 -> 437886 | T21: =T19+T17+T15+T13 -> 515033 | U21: =U19+U17+U15+U13 -> 600015 | ... AG21: =AG19+AG17+AG15+AG13 -> 2212841 | AI21: =IFERROR((AG21/B21)^(1/31)-1,"") -> 0.17709995 | AJ21: =IFERROR(PRODUCT(1+C22,1+D22,1+E22,1+F22,1+G22,1+H22,1+I22,1+J22,1+K22,1+L22,1+M22,1+N22,1+O22,1+P22,1+Q22,1+R22,1+S22,1+T22,1+U22,1+V22,1+W22,1+X22,1+Y22,1+Z22,1+AA22,1+AB22,1+AC22,1+AD22,1+AE22,1+AF22,1+AG22)^(1/31)-1,"") -> 0.17709995 | AL21: =IFERROR((AG21/M21)^(1/20)-1,"") -> 0.18124155 | AM21: =IFERROR(PRODUCT(1+N22,1+O22,1+P22,1+Q22,1+R22,1+S22,1+T22,1+U22,1+V22,1+W22,1+X22,1+Y22,1+Z22,1+AA22,1+AB22,1+AC22,1+AD22,1+AE22,1+AF22,1+AG22)^(1/20)-1,"") -> 0.18124155 | AO21: =IFERROR((AG21/W21)^(1/10)-1,"") -> 0.094120301 | AP21: =IFERROR(PRODUCT(1+X22,1+Y22,1+Z22,1+AA22,1+AB22,1+AC22,1+AD22,1+AE22,1+AF22,1+AG22)^(1/10)-1,"") -> 0.094120301 | AR21: =IFERROR((AG21/AB21)^(1/5)-1,"") -> 0.15198501 | AS21: =IFERROR(PRODUCT(1+AC22,1+AD22,1+AE22,1+AF22,1+AG22)^(1/5)-1,"") -> 0.15198501
A22: % Growth | C22: =IFERROR((C21/B21-1),"") -> -0.047801019 | D22: =IFERROR((D21/C21-1),"") -> -0.016704342 | E22: =IFERROR((E21/D21-1),"") -> 0.20690792 | F22: =IFERROR((F21/E21-1),"") -> 0.28974715 | G22: =IFERROR((G21/F21-1),"") -> 0.26495062 | H22: =IFERROR((H21/G21-1),"") -> 0.15984646 | I22: =IFERROR((I21/H21-1),"") -> 0.16855332 | J22: =IFERROR((J21/I21-1),"") -> -0.20760002 | ... AG22: =IFERROR((AG21/AF21-1),"") -> 0.044490565
A23: Operating income (loss) | B23: =B10-B21 -> -1187.432 | C23: =C10-C21 -> -1306.708 | D23: =D10-D21 -> 676.947 | E23: =E10-E21 -> 1881.909 | F23: =F10-F21 -> 5959.866 | G23: =G10-G21 -> 7501.054 | H23: =H10-H21 -> 6900.332 | I23: =I10-I21 -> 5550.904 | ... AG23: =AG10-AG21 -> 2419354
A24: % of Revenue | B24: =-B23/B$6 -> 0.041208068 | C24: =-C23/C$6 -> 0.038443132 | D24: =D23/D$6 -> 0.019033819 | E24: =E23/E$6 -> 0.043707323 | F24: =F23/F$6 -> 0.11064184 | G24: =G23/G$6 -> 0.10374445 | H24: =H23/H$6 -> 0.086543303 | I24: =I23/I$6 -> 0.060153028 | J24: =J23/J$6 -> 0.057502468 | K24: =K23/K$6 -> 0.089043339 | ... AG24: =AG23/AG$6 -> 0.29168724
A26: Interest income | B26: -58.325 | C26: -19.725 | D26: -8.919 | E26: -3.481 | F26: -72.352 | G26: -118.413 | H26: -12.914 | I26: -8.992 | J26: -2.974 | K26: 0 | L26: 0 | M26: 1427.803 | N26: 3660 | O26: 8770 | P26: 0 | Q26: 0 | R26: 0 | S26: 0 | T26: 0 | U26: 0 | V26: 0 | W26: 0 | X26: 0 | Y26: 0 | Z26: 0 | AA26: 0 | AB26: 0 | AC26: 0 | AD26: 0 | AE26: 0 | AF26: 0 | AG26: 0
A27: Interest expense | B27: 344.923 | C27: 459.542 | D27: 585.733 | E27: 525.294 | F27: 387.446 | G27: 170.506 | H27: 382.152 | I27: 527.594 | J27: 230.732 | K27: 72.592 | L27: 41.988 | M27: -76.531 | N27: 0 | O27: 0 | P27: 0 | Q27: 0 | R27: 0 | S27: 0 | T27: 0 | U27: 0 | V27: 0 | W27: 0 | X27: 0 | Y27: 0 | Z27: 0 | AA27: 0 | AB27: 0 | AC27: 0 | AD27: 0 | AE27: 0 | AF27: 0 | AG27: 0
A28: Other income (expense), net | B28: -28.766 | C28: -399.232 | D28: -259.433 | E28: 69.745 | F28: 14.719 | G28: 0 | H28: 0 | I28: 0 | J28: 0 | K28: 0 | L28: 0 | M28: 0 | N28: 0 | O28: 0 | P28: 0 | Q28: 0 | R28: 0 | S28: 0 | T28: 0 | U28: 0 | V28: 0 | W28: -2105 | X28: -5653 | Y28: 2836 | Z28: 9653 | AA28: 13023 | AB28: -6996 | AC28: 3952 | AD28: -12757 | AE28: 115127 | AF28: 59165 | AG28: 63175
A29: Income before income taxes | B29: =B23-B27+B26-B28 -> -1561.914 | C29: =C23-C27+C26-C28 -> -1386.743 | D29: =D23-D27+D26-D28 -> 341.728 | E29: =E23-E27+E26-E28 -> 1283.389 | F29: =F23-F27+F26-F28 -> 5485.349 | G29: =G23-G27+G26-G28 -> 7212.135 | H29: =H23-H27+H26-H28 -> 6505.266 | I29: =I23-I27+I26-I28 -> 5014.318 | ... AG29: =AG23-AG27+AG26-AG28 -> 2356179
A30: % of Revenue | B30: =-B29/B$6 -> 0.054203911 | C30: =-C29/C$6 -> 0.040797748 | D30: =D29/D$6 -> 0.0096084167 | E30: =E29/E$6 -> 0.0298067 | F30: =F29/F$6 -> 0.10183268 | G30: =G29/G$6 -> 0.099748509 | H30: =H29/H$6 -> 0.081588423 | I30: =I29/I$6 -> 0.05433825 | J30: =J29/J$6 -> 0.054963465 | K30: =K29/K$6 -> 0.088385518 | ... AG30: =AG29/AG$6 -> 0.2840706
A32: Provision for income taxes | B32: -37.917 | C32: 2.4 | D32: 2.4 | E32: 40.2 | F32: 2066.922 | G32: 2971.118 | H32: 2615.986 | I32: 2012.902 | J32: 2035.98 | K32: 3823.099 | L32: 13457.41 | M32: 39316.061 | N32: 64290 | O32: 90350 | P32: 65445 | Q32: 126979 | R32: 137273 | S32: 171051 | T32: 209134 | U32: 225233 | V32: 262603 | W32: 344815 | X32: 367000 | Y32: 380945 | Z32: 300268 | AA32: 308127 | AB32: 216563 | AC32: 423944 | AD32: 380340 | AE32: 437494 | AF32: 480411 | AG32: 577097
A33: Net income (loss) | B33: =B29-B32 -> -1523.997 | C33: =C29-C32 -> -1389.143 | D33: =D29-D32 -> 339.328 | E33: =E29-E32 -> 1243.189 | F33: =F29-F32 -> 3418.427 | G33: =G29-G32 -> 4241.017 | H33: =H29-H32 -> 3889.28 | I33: =I29-I32 -> 3001.416 | ... AG33: =AG29-AG32 -> 1779082
A34: % of Revenue | B34: =-B33/B$6 -> 0.052888058 | C34: =-C33/C$6 -> 0.040868356 | D34: =D33/D$6 -> 0.0095409355 | E34: =E33/E$6 -> 0.028873056 | F34: =F33/F$6 -> 0.063461336 | G34: =G33/G$6 -> 0.058656018 | H34: =H33/H$6 -> 0.048778977 | I34: =I33/I$6 -> 0.032525199 | J34: =J33/J$6 -> 0.032844394 | K34: =K33/K$6 -> 0.053740997 | ... AG34: =AG33/AG$6 -> 0.21449342
A36: Basic EPS | B36: =IFERROR(B33/B41,"") -> -0.1670524 | C36: =IFERROR(C33/C41,"") -> -0.15227043 | D36: =IFERROR(D33/D41,"") -> 0.036811995 | E36: =IFERROR(E33/E41,"") -> 0.13623048 | F36: =IFERROR(F33/F41,"") -> 0.36417819 | G36: =IFERROR(G33/G41,"") -> 0.42560075 | H36: =IFERROR(H33/H41,"") -> 0.39057847 | I36: =IFERROR(I33/I41,"") -> 0.29904867 | ... AG36: =IFERROR(AG33/AG41,"") -> 1.823041
A37: Diluted EPS | B37: =IFERROR(B33/B42,"") -> -0.1670524 | C37: =IFERROR(C33/C42,"") -> -0.15227043 | D37: =IFERROR(D33/D42,"") -> 0.036811995 | E37: =IFERROR(E33/E42,"") -> 0.13383969 | F37: =IFERROR(F33/F42,"") -> 0.32772663 | G37: =IFERROR(G33/G42,"") -> 0.40349889 | H37: =IFERROR(H33/H42,"") -> 0.37376427 | I37: =IFERROR(I33/I42,"") -> 0.29097857 | ... AG37: =IFERROR(AG33/AG42,"") -> 1.8071819
A38: % Growth | C38: =C36/B36-1 -> -0.088487051 | D38: =D36/C36-1 -> -1.2417541 | E38: =E36/D36-1 -> 2.7007091 | F38: =F36/E36-1 -> 1.6732503 | G38: =G36/F36-1 -> 0.16866075 | H38: =H36/G36-1 -> -0.082289055 | I38: =I36/H36-1 -> -0.23434421 | J38: =J36/I36-1 -> 0.0056618497 | ... AG38: =AG36/AF36-1 -> 0.31684856
A39: % Growth | C39: =C37/B37-1 -> -0.088487051 | D39: =D37/C37-1 -> -1.2417541 | E39: =E37/D37-1 -> 2.6357631 | F39: =F37/E37-1 -> 1.4486505 | G39: =G37/F37-1 -> 0.23120567 | H39: =H37/G37-1 -> -0.073691936 | I39: =I37/H37-1 -> -0.22149175 | J39: =J37/I37-1 -> 0.0048540231 | ... AG39: =AG37/AF37-1 -> 0.31649163
A41: Basic weighted average shares | B41: 9122.868 | C41: 9122.868 | D41: 9217.865 | E41: 9125.63 | F41: 9386.688 | G41: 9964.778 | H41: 9957.743 | I41: 10036.547 | J41: 10052.499 | K41: 10278.71 | L41: 84945.017 | M41: 88416.868 | N41: 89936 | O41: 91178 | P41: 92515 | Q41: 89967 | R41: 88514 | S41: 176212 | T41: 173712 | U41: 166679 | V41: 167257 | W41: 188816 | X41: 587874 | Y41: 566782 | Z41: 557166 | AA41: 542191 | AB41: 529639 | AC41: 528763 | AD41: 1053558 | AE41: 1044887 | AF41: 1004566 | AG41: 975887
A42: Diluted weighted average shares | B42: 9122.868 | C42: 9122.868 | D42: 9217.865 | E42: 9288.642 | F42: 10430.727 | G42: 10510.604 | H42: 10405.703 | I42: 10314.904 | J42: 10339.604 | K42: 10762.157 | L42: 92667.291 | M42: 96578.425 | N42: 98586 | O42: 98874 | P42: 97530 | Q42: 94643 | R42: 93021 | S42: 186674 | T42: 183083 | U42: 173387 | V42: 174285 | W42: 192586 | X42: 599819 | Y42: 577141 | Z42: 564254 | AA42: 546608 | AB42: 534807 | AC42: 535639 | AD42: 1066442 | AE42: 1057981 | AF42: 1013107 | AG42: 984451
A47: BALANCE SHEET
A48: Current assets
A49: Cash and cash equivalents | C49: 87.916 | D49: 186.931 | E49: 395.231 | F49: 3806.089 | G49: 2009.155 | H49: 130.665 | I49: 247.657 | J49: 537.92 | K49: 1098.785 | L49: 20976.119 | M49: 61654.284 | N49: 35129 | O49: 12440 | P49: 256801 | Q49: 328349 | R49: 354842 | S49: 359331 | T49: 222514 | U49: 211349 | V49: 370323 | W49: 2175417 | X49: 377582 | Y49: 528622 | Z49: 637513 | AA49: 797957 | AB49: 1180413 | AC49: 1326462 | AD49: 1307141 | AE49: 2297675 | AF49: 1533287 | AG49: 2088117
A50: Short-term investments | M50: 11860.665 | N50: 101667 | O50: 63125 | P50: 29145 | Q50: 18487 | R50: 244649 | S50: 411282 | T50: 97042 | U50: 402247 | V50: 781134 | W50: 744610 | X50: 220554 | Y50: 672933 | Z50: 320650 | AA50: 533063 | AB50: 881354 | AC50: 1749727 | AD50: 1362314 | AE50: 955605 | AF50: 0 | AG50: 677084
A51: Accounts receivable, net | C51: 1729.155 | D51: 944.227 | E51: 1541.731 | F51: 1827.544 | G51: 3751.258 | H51: 6584.486 | I51: 4412.422 | J51: 5949.402 | K51: 5372.983 | L51: 12650.055 | M51: 28751.588 | N51: 54624 | O51: 81497 | P51: =45233+90722 -> 135955 | Q51: 108905 | R51: 101635 | S51: 218741 | T51: 236710 | U51: =291638+4542 -> 296180 | V51: =280203+552 -> 280755 | W51: =352955+125000 -> 477955 | X51: =448051+125000 -> 573051 | Y51: 449476 | Z51: 484562 | AA51: 540330 | AB51: 666012 | AC51: 896658 | AD51: 1016203 | AE51: 1193964 | AF51: 1221646 | AG51: 1618072
A52: % of Revenue | C52: =C51/C6 -> 0.050871452 | D52: =D51/D6 -> 0.02654897 | E52: =E51/E6 -> 0.035806691 | F52: =F51/F6 -> 0.033927413 | G52: =G51/G6 -> 0.051882333 | H52: =H51/H6 -> 0.082581993 | I52: =I51/I6 -> 0.047815733 | J52: =J51/J6 -> 0.064634841 | ... AG52: =AG51/AG6 -> 0.19508139
A53: Inventories | C53: 3120.519 | D53: 3111.124 | E53: 3915.983 | F53: 5211.077 | G53: 9894.414 | H53: 10907.895 | I53: 11956.68 | J53: 11643.734 | K53: 17643.786 | L53: 22406.054 | M53: 31399.628 | N53: 77013 | O53: 98140 | P53: 116326 | Q53: 108143 | R53: 153241 | S53: 155613 | T53: 203106 | U53: 221449 | V53: 174573 | W53: 156121 | X53: 161971 | Y53: 255745 | Z53: 277705 | AA53: 360731 | AB53: 333085 | AC53: 593357 | AD53: 935631 | AE53: 971406 | AF53: 737107 | AG53: 799623
A54: Prepaid expenses and other current assets | C54: 487.507 | D54: 331.869 | E54: 214.468 | F54: 244.318 | G54: 553.689 | H54: 823.387 | I54: 974.155 | J54: 1627.685 | K54: 481.777 | L54: 638.967 | M54: 477.237 | N54: 771 | O54: 3755 | P54: 8379 | Q54: 11270 | R54: 17022 | S54: 20912 | T54: 24983 | U54: 21376 | V54: 19673 | W54: 26967 | X54: 32562 | Y54: 40877 | Z54: 44909 | AA54: 54868 | AB54: 55358 | AC54: 82668 | AD54: 109823 | AE54: 116195 | AF54: 107262 | AG54: 103551
A55: Intangibles held-for-sale | U55: 0 | V55: 18079 | W55: 0 | X55: 0
A56: Prepaid Income Taxes | C56: 0 | D56: 0 | E56: 0 | F56: 0 | G56: 0 | H56: 0 | I56: 0 | J56: 0 | K56: 0 | L56: 0 | M56: 638 | N56: 0 | O56: 0 | P56: 4977 | Q56: 0 | R56: 9992 | S56: 370 | T56: 33709 | U56: 9518 | V56: 8617 | W56: 18462 | X56: 66550 | Y56: 138724 | Z56: 38831 | AB56: 24733 | AC56: 33238 | AD56: 33785 | AE56: 54151 | AF56: 42202 | AG56: 74637
A57: Deferred income tax | C57: 0 | D57: 0 | E57: 0 | F57: 0 | G57: 743.364 | H57: 881.618 | I57: 949.176 | J57: 1145.133 | K57: 2080.609 | L57: 3708.942 | M57: 5505 | N57: 5953 | O57: 11192 | P57: 9741 | Q57: 10350 | R57: 16772 | S57: 16428 | T57: 17004 | U57: 20924 | V57: 40275 | W57: 0 | X57: 0
A58: Total current assets | C58: =C57+C54+C53+C51+C50+C49+C56+C55 -> 5425.097 | D58: =D57+D54+D53+D51+D50+D49+D56+D55 -> 4574.151 | E58: =E57+E54+E53+E51+E50+E49+E56+E55 -> 6067.413 | F58: =F57+F54+F53+F51+F50+F49+F56+F55 -> 11089.028 | G58: =G57+G54+G53+G51+G50+G49+G56+G55 -> 16951.88 | H58: =H57+H54+H53+H51+H50+H49+H56+H55 -> 19328.051 | I58: =I57+I54+I53+I51+I50+I49+I56+I55 -> 18540.09 | J58: =J57+J54+J53+J51+J50+J49+J56+J55 -> 20903.874 | ... AG58: =AG57+AG54+AG53+AG51+AG50+AG49+AG56+AG55 -> 5361084
A60: Long-term assets
A61: Investments | C61: 0 | D61: 0 | E61: 0 | F61: 0 | G61: 0 | H61: 0 | I61: 0 | J61: 0 | K61: 0 | L61: 0 | M61: 0 | N61: 0 | O61: 227085 | P61: 89567 | Q61: 80836 | R61: 44189 | S61: 23194 | T61: 21393 | U61: 9792 | V61: 42940 | W61: 15348 | X61: 2394 | Y61: 2366 | AB61: 44291 | AC61: 99419 | AD61: 61443 | AE61: 76431 | AF61: 0 | AG61: 48329 | AI61: 31yr | AJ61: Check | AL61: 20yr | AM61: Check | AO61: 10yr | AP61: Check | AR61: 5yr | AS61: Check
A62: Property and equipment, net | C62: 784.884 | D62: 602.272 | E62: 412.496 | F62: 601.523 | G62: 504.191 | H62: 1863.044 | I62: 1945.146 | J62: 1862.807 | K62: 2803.282 | L62: 2964.064 | M62: 3742.958 | N62: 5565 | O62: 8567 | P62: 14389 | Q62: 33314 | R62: 34551 | S62: 45151 | T62: 69137 | U62: 88143 | V62: 90156 | W62: 97354 | X62: 173343 | Y62: 230276 | Z62: 243051 | AA62: 298640 | AB62: 314656 | AC62: 313753 | AD62: 516897 | AE62: 890796 | AF62: 1047024 | AG62: 1081544 | AI62: =IFERROR((AG62/C62)^(1/30)-1,"") -> 0.27245165 | AJ62: =IFERROR(PRODUCT(1+C63,1+D63,1+E63,1+F63,1+G63,1+H63,1+I63,1+J63,1+K63,1+L63,1+M63,1+N63,1+O63,1+P63,1+Q63,1+R63,1+S63,1+T63,1+U63,1+V63,1+W63,1+X63,1+Y63,1+Z63,1+AA63,1+AB63,1+AC63,1+AD63,1+AE63,1+AF63,1+AG63)^(1/30)-1,"") -> 0.27245165 | AL62: =IFERROR((AG62/M62)^(1/20)-1,"") -> 0.32752119 | AM62: =IFERROR(PRODUCT(1+N63,1+O63,1+P63,1+Q63,1+R63,1+S63,1+T63,1+U63,1+V63,1+W63,1+X63,1+Y63,1+Z63,1+AA63,1+AB63,1+AC63,1+AD63,1+AE63,1+AF63,1+AG63)^(1/20)-1,"") -> 0.32752119 | AO62: =IFERROR((AG62/W62)^(1/10)-1,"") -> 0.27223998 | AP62: =IFERROR(PRODUCT(1+X63,1+Y63,1+Z63,1+AA63,1+AB63,1+AC63,1+AD63,1+AE63,1+AF63,1+AG63)^(1/10)-1,"") -> 0.27223998 | AR62: =IFERROR((AG62/AB62)^(1/5)-1,"") -> 0.28009333 | AS62: =IFERROR(PRODUCT(1+AC63,1+AD63,1+AE63,1+AF63,1+AG63)^(1/5)-1,"") -> 0.28009333
A63: % Growth | D63: =IFERROR((D62/C62-1),"") -> -0.23266113 | E63: =IFERROR((E62/D62-1),"") -> -0.31510015 | F63: =IFERROR((F62/E62-1),"") -> 0.45825172 | G63: =IFERROR((G62/F62-1),"") -> -0.16180927 | H63: =IFERROR((H62/G62-1),"") -> 2.6951155 | I63: =IFERROR((I62/H62-1),"") -> 0.044068739 | J63: =IFERROR((J62/I62-1),"") -> -0.042330499 | K63: =IFERROR((K62/J62-1),"") -> 0.5048698 | ... AG63: =IFERROR((AG62/AF62-1),"") -> 0.032969636
A64: Deferred Income Taxes | C64: 0 | D64: 0 | E64: 0 | F64: 0 | G64: 0 | H64: 0 | I64: 0 | J64: 0 | K64: 0 | L64: 0 | M64: 0 | N64: 5001 | O64: 14006 | P64: 65748 | Q64: 65678 | R64: 58475 | S64: 58576 | T64: 59503 | U64: 63611 | V64: 54106 | W64: 140468 | X64: 159556 | Y64: 92333 | Z64: 85687 | AB64: 241650 | AC64: 225221 | AD64: 177039 | AE64: 175003 | AF64: 184260 | AG64: 188646
A65: Intangible assets, net | C65: 10794.052 | D65: 10459.144 | E65: 10208.116 | F65: 10003.417 | G65: 10768.493 | H65: 16887.914 | I65: 17350.221 | J65: 17360.455 | K65: 18293.704 | L65: 18351.804 | M65: 19103 | N65: 21202 | O65: 24066 | P65: 28365 | Q65: 33512 | R65: 43316 | S65: 48396 | T65: 54648 | U65: 65774 | V65: 50748 | W65: 427986 | X65: 1032635 | Y65: 1034085 | Z65: 1045878 | AA65: 1052105 | AB65: 1059046 | AC65: 1072386 | AD65: 1220410 | AE65: 1427139 | AF65: 1414252 | AG65: 1379268
D66: =IFERROR((D65/C65-1),"") -> -0.031027088 | E66: =IFERROR((E65/D65-1),"") -> -0.024000817 | F66: =IFERROR((F65/E65-1),"") -> -0.020052574 | G66: =IFERROR((G65/F65-1),"") -> 0.076481466 | H66: =IFERROR((H65/G65-1),"") -> 0.56827088 | I66: =IFERROR((I65/H65-1),"") -> 0.027375021 | J66: =IFERROR((J65/I65-1),"") -> 0.00058984839 | K66: =IFERROR((K65/J65-1),"") -> 0.053757174 | ... AG66: =IFERROR((AG65/AF65-1),"") -> -0.024736751
A67: Goodwill | C67: 0 | D67: 0 | E67: 60.252 | F67: 20.861 | G67: 0 | H67: 0 | I67: 0 | J67: 0 | K67: 0 | L67: 0 | M67: 0 | N67: 0 | O67: 0 | P67: 0 | Q67: 0 | R67: 0 | S67: 0 | T67: 0 | U67: 0 | V67: 0 | W67: 1279715 | X67: 1331643 | Y67: 1331643 | Z67: 1331643 | AA67: 1331643 | AB67: 1331643 | AC67: 1331643 | AD67: 1417941 | AE67: 1417941 | AF67: 1331643 | AG67: 1331643
D68: =IFERROR((D67/C67-1),"") | E68: =IFERROR((E67/D67-1),"") | F68: =IFERROR((F67/E67-1),"") -> -0.65377083 | G68: =IFERROR((G67/F67-1),"") -> -1 | H68: =IFERROR((H67/G67-1),"") | I68: =IFERROR((I67/H67-1),"") | J68: =IFERROR((J67/I67-1),"") | K68: =IFERROR((K67/J67-1),"") | ... AG68: =IFERROR((AG67/AF67-1),"") -> 0
A69: Other assets | C69: 517.386 | D69: 473.506 | E69: 185.082 | F69: 211.903 | G69: 484.388 | H69: 665.731 | I69: 725.825 | J69: 336.369 | K69: 222.102 | L69: 326.312 | M69: 757.215 | N69: 1447 | O69: 730 | P69: 2444 | Q69: 1226 | R69: 3447 | S69: 4405 | T69: 3576 | U69: 10146 | V69: 7496 | W69: 10874 | X69: 21630 | Y69: 13932 | Z69: 16462 | AA69: 53973 | AB69: 70475 | AC69: 80252 | AD69: 134478 | AE69: 110216 | AF69: 100406 | AG69: 159431
A70: Total long-term assets | C70: =C69+C67+C65+C62+C64+C61 -> 12096.322 | D70: =D69+D67+D65+D62+D64+D61 -> 11534.922 | E70: =E69+E67+E65+E62+E64+E61 -> 10865.946 | F70: =F69+F67+F65+F62+F64+F61 -> 10837.704 | G70: =G69+G67+G65+G62+G64+G61 -> 11757.072 | H70: =H69+H67+H65+H62+H64+H61 -> 19416.689 | I70: =I69+I67+I65+I62+I64+I61 -> 20021.192 | J70: =J69+J67+J65+J62+J64+J61 -> 19559.631 | ... AG70: =AG69+AG67+AG65+AG62+AG64+AG61 -> 4188861
A71: Total assets | C71: =C70+C58 -> 17521.419 | D71: =D70+D58 -> 16109.073 | E71: =E70+E58 -> 16933.359 | F71: =F70+F58 -> 21926.732 | G71: =G70+G58 -> 28708.952 | H71: =H70+H58 -> 38744.74 | I71: =I70+I58 -> 38561.282 | J71: =J70+J58 -> 40463.505 | ... AG71: =AG70+AG58 -> 9549945
A73: Current liabilitiies
A74: Short term debt | C74: 1474.335 | D74: 893.429
A75: Accounts payable | C75: 3382.765 | D75: 2139.05 | E75: 2195.2 | F75: 1870.253 | G75: 5936.873 | H75: 3681.956 | I75: 3919.741 | J75: 4732.261 | K75: 6521.402 | L75: 14542.753 | M75: 26613.663 | N75: 34362 | O75: 56766 | P75: 64787 | Q75: 48863 | R75: 85674 | S75: 113446 | T75: 127330 | U75: 119376 | V75: 127641 | W75: 144763 | X75: 193270 | Y75: 245910 | Z75: 248760 | AA75: 274045 | AB75: 296800 | AC75: 404263 | AD75: 444265 | AE75: 564379 | AF75: 466775 | AG75: 565974
A76: Accrued liabilities | C76: 155.959 | D76: 200.602 | E76: 488.807 | F76: 403.864 | G76: 345.794 | H76: 607.443 | I76: 871.841 | J76: 680.959 | K76: 1185.342 | L76: 1582.968 | M76: 2481.703 | N76: 16489 | O76: 9019 | P76: 12524 | Q76: 14174 | R76: 23811 | S76: 31966 | T76: 38916 | U76: 59113 | V76: 40271 | W76: 81786 | X76: 79526 | Y76: 87475 | Z76: 112507 | AA76: 114075 | AB76: 142653 | AC76: 210964 | AD76: 172991 | AE76: 183988 | AF76: 220764 | AG76: 306085
A77: Accrued distributor terminations | C77: 0 | D77: 0 | E77: 0 | F77: 0 | G77: 0 | H77: 0 | I77: 0 | J77: 0 | K77: 0 | L77: 0 | M77: 0 | N77: 0 | O77: 4312 | P77: 102282 | Q77: 2977 | R77: 407 | W77: 11018 | X77: 8184 | Y77: 91 | Z77: 0
A78: Deferred revenue | C78: 0 | D78: 0 | E78: 0 | F78: 0 | G78: 0 | H78: 0 | I78: 0 | J78: 0 | K78: 0 | L78: 0 | M78: 0 | N78: 0 | O78: 0 | P78: 0 | Q78: 9125 | R78: 10140 | S78: 11583 | T78: 12695 | U78: 13832 | V78: 49926 | W78: 32271 | X78: 41672 | Y78: 43236 | Z78: 44045 | AB78: 45429 | AC78: 42530 | AD78: 43311 | AE78: 41914 | AF78: 45809 | AG78: 45323
A79: Customer deposit liabilities | C79: 0 | D79: 0 | E79: 0 | F79: 0 | G79: 0 | H79: 0 | I79: 0 | J79: 0 | K79: 0 | L79: 0 | M79: 0 | N79: 3324
A80: Accrued promotional allowances | C80: 0 | D80: 0 | E80: 0 | F80: 0 | G80: 0 | H80: 0 | I80: 0 | J80: 0 | K80: 0 | L80: 0 | M80: 0 | N80: 0 | O80: 0 | P80: 0 | Q80: 0 | R80: 0 | S80: 87746 | T80: 91208 | U80: 99470 | V80: 114047 | W80: 115530 | X80: 110237 | Y80: 137998 | Z80: 145741 | AA80: 166761 | AB80: 186658 | AC80: 211461 | AD80: 255631 | AE80: 269061 | AF80: 267711 | AG80: 384070
A81: Accrued compensation | C81: 0 | D81: 0 | E81: 322.114 | F81: 476.001 | G81: 462.285 | H81: 281.629 | I81: 432.896 | J81: 310.064 | K81: 883.459 | L81: 1831.627 | M81: 3346 | N81: 4378 | O81: 5827 | P81: 6782 | Q81: 7623 | R81: 7603 | S81: 10353 | T81: 12926 | U81: 14864 | V81: 17983 | W81: 22159 | X81: 30043 | Y81: 34996 | Z81: 39903 | AB81: 55015 | AC81: 65459 | AD81: 72463 | AE81: 87392 | AF81: 92454 | AG81: 114023
A82: Income taxes payable | E82: 37.8 | F82: 1269.185 | G82: 346.636 | H82: 878.266 | I82: 0 | J82: 0 | K82: 647.263 | L82: 346.449 | M82: 0 | N82: 3991 | O82: 6294 | P82: 0 | Q82: 761 | R82: 925 | S82: 10996 | T82: 5470 | U82: 9359 | V82: 5848 | W82: 2750 | X82: 7657 | Y82: 10645 | Z82: 10189 | AA82: 14717 | AB82: 23433 | AC82: 30399 | AD82: 13317 | AE82: 14955 | AF82: 4006 | AG82: 32305
A83: Current portion of long-term debt | C83: 30.782 | D83: 4048.541 | E83: 520.835 | F83: 2072.818 | G83: 863.501 | H83: 234.655 | I83: 337.872 | J83: 230.74 | K83: 244.271 | L83: 437.366 | M83: 515.221 | N83: 299 | O83: 663 | P83: 959 | Q83: 206 | R83: 274 | S83: 0 | T83: 0
A84: Total current liabilities | C84: =C74+C83+C82+C80+C76+C75+C79+C77+C78+C81 -> 5043.841 | D84: =D74+D83+D82+D80+D76+D75+D79+D77+D78+D81 -> 7281.622 | E84: =E74+E83+E82+E80+E76+E75+E79+E77+E78+E81 -> 3564.756 | F84: =F74+F83+F82+F80+F76+F75+F79+F77+F78+F81 -> 6092.121 | G84: =G74+G83+G82+G80+G76+G75+G79+G77+G78+G81 -> 7955.089 | H84: =H74+H83+H82+H80+H76+H75+H79+H77+H78+H81 -> 5683.949 | I84: =I74+I83+I82+I80+I76+I75+I79+I77+I78+I81 -> 5562.35 | J84: =J74+J83+J82+J80+J76+J75+J79+J77+J78+J81 -> 5954.024 | ... AG84: =AG74+AG83+AG82+AG80+AG76+AG75+AG79+AG77+AG78+AG81 -> 1447780
A86: Long-term liabilities
A87: Long-term debt | C87: 4031.663 | E87: 3407.824 | F87: 1334.967 | G87: 902.716 | H87: 9731.956 | I87: 5851.105 | J87: 3606.04 | K87: 358.064 | L87: 146.486 | M87: 10.123 | N87: 4 | O87: 0 | P87: 0 | AF87: 373951 | AG87: 0
A88: Deferred revenue | F88: 557.461 | G88: 1225.271 | H88: 1274.139 | I88: 1814.278 | J88: 2532.697 | K88: 3107.649 | L88: 4563.439 | M88: 0 | N88: 20441 | O88: 39555 | P88: 138187 | Q88: 131388 | R88: 124899 | S88: 117151 | T88: 110383 | U88: 112216 | V88: 68009 | W88: 351590 | X88: 353173 | Y88: 334354 | Z88: 312224 | AA88: 287469 | AB88: 264436 | AC88: 243249 | AD88: 223800 | AE88: 204251 | AF88: 179008 | AG88: 159991
A89: Deferred income taxes | C89: 0 | D89: 0 | E89: 0 | F89: 0 | G89: 0 | H89: 0 | I89: 0 | J89: 0 | K89: 0 | L89: 0 | M89: 5414 | N89: 0 | O89: 0 | P89: 0 | Q89: 0 | R89: 0 | S89: 0 | T89: 0 | U89: 0 | V89: 0 | W89: 0 | X89: 0
A90: Other Liabilities | Y90: 1095 | Z90: 2621 | AB90: 27432 | AC90: 29508 | AD90: 42286 | AE90: 91838 | AF90: 110893 | AG90: 127066
A91: Total long term liabilities | C91: =C88+C87+C89+C90 -> 4031.663 | D91: =D88+D87+D89+D90 -> 0 | E91: =E88+E87+E89+E90 -> 3407.824 | F91: =F88+F87+F89+F90 -> 1892.428 | G91: =G88+G87+G89+G90 -> 2127.987 | H91: =H88+H87+H89+H90 -> 11006.095 | I91: =I88+I87+I89+I90 -> 7665.383 | J91: =J88+J87+J89+J90 -> 6138.737 | ... AG91: =AG88+AG87+AG89+AG90 -> 287057
A92: Total liabilities | C92: =C91+C84 -> 9075.504 | D92: =D91+D84 -> 7281.622 | E92: =E91+E84 -> 6972.58 | F92: =F91+F84 -> 7984.549 | G92: =G91+G84 -> 10083.076 | H92: =H91+H84 -> 16690.044 | I92: =I91+I84 -> 13227.733 | J92: =J91+J84 -> 12092.761 | ... AG92: =AG91+AG84 -> 1734837
A94: Equity
A95: Common stock | C95: 45.614 | D95: 45.614 | E95: 45.654 | F95: 49.56 | G95: 50.05 | H95: 50.744 | I95: 51.259 | J95: 51.299 | K95: 53.124 | L95: 55.599 | M95: 452 | N95: 464 | O95: 479 | P95: 484 | Q95: 486 | R95: 494 | S95: 994 | T95: 1019 | U95: 1030 | V95: 1035 | W95: 3105 | X95: 3116 | Y95: 3146 | Z95: 3155 | AA95: 3182 | AB95: 3193 | AC95: 3200 | AD95: 6418 | AE95: 5613 | AF95: 5632 | AG95: 5665
A96: Additional paid-in capital | C96: 10847.355 | D96: 10847.355 | E96: 10858.315 | F96: 11207.765 | G96: 11340.074 | H96: 11667.619 | I96: 11926.604 | J96: 11934.564 | K96: 12681.169 | L96: 15813.541 | M96: 19579 | N96: 48892 | O96: 96749 | P96: 117106 | Q96: 137040 | R96: 187040 | S96: 229301 | T96: 287953 | U96: 368069 | V96: 426145 | W96: 3989787 | X96: 4051245 | Y96: 4150628 | Z96: 4238170 | AA96: 4397511 | AB96: 4537982 | AC96: 4652620 | AD96: 4776804 | AE96: 4975115 | AF96: 5144922 | AG96: 5430847
A97: Retained earnings / accumulated deficit | C97: -2483.266 | D97: -2126.1 | E97: -875.949 | F97: 2752.099 | G97: 7235.752 | H97: 11150.878 | I97: 14170.231 | J97: 17199.426 | K97: 23129.83 | L97: 43516.634 | M97: 106293 | N97: 204242 | O97: 353648 | P97: 461680 | Q97: 670396 | R97: 882425 | S97: 1168644 | T97: 1508664 | U97: 1847325 | V97: 2330510 | W97: 1394863 | X97: 2107548 | Y97: 2928226 | Z97: 3914645 | AA97: 5022480 | AB97: 6432074 | AC97: 7809549 | AD97: 9001173 | AE97: 5939736 | AF97: 7448784 | AG97: 9354216
A98: Accumulated other comprehensive income (loss) | C98: 36.212 | D98: 60.582 | E98: -67.241 | F98: -67.241 | G98: 0 | O98: -47 | P98: -10825 | Q98: -4667 | R98: 281 | S98: -1547 | T98: 2074 | U98: -1233 | V98: -11453 | W98: -21878 | X98: -23249 | Y98: -16659 | Z98: -32864 | AA98: -32387 | AB98: 3034 | AC98: -69165 | AD98: -159073 | AE98: -125337 | AF98: -269487 | AG98: -60841
A99: Treasury stock | C99: 0 | D99: 0 | E99: 0 | F99: 0 | G99: 0 | H99: -814.545 | I99: -814.545 | J99: -814.545 | K99: -814.545 | L99: -814.545 | M99: -815 | N99: -28514 | O99: -28662 | P99: -132129 | Q99: -218302 | R99: -241842 | S99: -418234 | T99: -1155313 | U99: -1222912 | V99: -1231087 | W99: -556467 | X99: -2808951 | Y99: -3170129 | Z99: -4512205 | AA99: -5219505 | AB99: -5815423 | AC99: -5829253 | AD99: -6600281 | AE99: -2566383 | AF99: -6372133 | AG99: -6475779
A100: Total stockholders' equity | C100: =C99+C98+C97+C96+C95 -> 8445.915 | D100: =D99+D98+D97+D96+D95 -> 8827.451 | E100: =E99+E98+E97+E96+E95 -> 9960.779 | F100: =F99+F98+F97+F96+F95 -> 13942.183 | G100: =G99+G98+G97+G96+G95 -> 18625.876 | H100: =H99+H98+H97+H96+H95 -> 22054.696 | I100: =I99+I98+I97+I96+I95 -> 25333.549 | J100: =J99+J98+J97+J96+J95 -> 28370.744 | ... AG100: =AG99+AG98+AG97+AG96+AG95 -> 8254108
A101: Total liabilities and stockholders' equity | C101: =C100+C92 -> 17521.419 | D101: =D100+D92 -> 16109.073 | E101: =E100+E92 -> 16933.359 | F101: =F100+F92 -> 21926.732 | G101: =G100+G92 -> 28708.952 | H101: =H100+H92 -> 38744.74 | I101: =I100+I92 -> 38561.282 | J101: =J100+J92 -> 40463.505 | ... AG101: =AG100+AG92 -> 9988945
A104: CASH FLOW STATEMENT
A105: Net income (loss) | B105: -1407.347 | C105: -1349.693 | D105: 357.166 | E105: 1250.151 | F105: 3563.129 | G105: 4477.868 | H105: 3915.126 | I105: 3019.353 | J105: 3029.195 | K105: 5930.404 | L105: 20386.804 | M105: 62775.976 | N105: 97949 | O105: 149406 | P105: 108032 | Q105: 208716 | R105: 212029 | S105: 286219 | T105: 340020 | U105: 338661 | V105: 483185 | W105: 546733 | X105: 712685 | Y105: 820678 | Z105: 993004 | AA105: 1107835 | AB105: 1409594 | AC105: 1377475 | AD105: 1191624 | AE105: 1630988 | AF105: 1509048 | AG105: 1905432
A106: Depreciation and amortization | B106: 193.912 | C106: 246.969 | D106: 249.035 | E106: 270.114 | F106: 246.494 | G106: 258.343 | H106: 314.662 | I106: 436.459 | J106: 493.894 | K106: 584.197 | L106: 770.413 | M106: 1008.629 | N106: 1538 | O106: 2128 | P106: 3417 | Q106: 5839 | R106: 11728 | S106: 17032 | T106: 20563 | U106: 22762 | V106: 25651 | W106: 30860 | X106: 40845 | Y106: 48887 | Z106: 56979 | AA106: 60727 | AB106: 57030 | AC106: 50155 | AD106: 61241 | AE106: 68898 | AF106: 80434 | AG106: 114441
A107: Amortization of intangibles | B107: 493.336 | C107: 497.75 | D107: 396.755 | E107: 301.237 | F107: 296.584 | G107: 307.824 | H107: 371.073 | I107: 507.488 | J107: 54.558 | K107: 61.888 | L107: 73.046 | M107: 70.102 | N107: 56 | O107: 56 | P107: 55 | Q107: 68 | R107: 48 | S107: 52
A108: Impairment of operating equipment | L108: 587.877
A109: Gain (loss) on sale of plant and equipment | B109: -12.003 | C109: -2.129 | E109: 69.745 | F109: 0.317 | G109: 15.569 | H109: 52.786 | I109: -15.072 | J109: 5.318 | K109: 31.992 | L109: 120.2 | M109: 180.085 | N109: 174 | O109: 120 | P109: 101 | Q109: -144 | R109: 194 | S109: -18 | T109: 25 | U109: 506 | V109: -408 | W109: 193 | X109: -204 | Y109: -1161 | Z109: -783 | AA109: -252 | AB109: -350 | AC109: -1013 | AD109: -185 | AE109: 166 | AF109: 3328 | AG109: 2781
A110: Gain on sale of Monster Non-Energy | W110: -161470 | X110: 0 | Y110: 0
A111: Stock-based compensation | F111: 64.919 | G111: 73.026 | I111: 230.879 | N111: 8346 | O111: 10246 | P111: 13899 | Q111: 14040 | R111: 16862 | S111: 19424 | T111: 28413 | U111: 28764 | V111: 28552 | W111: 32719 | X111: 45848 | Y111: 52282 | Z111: 57111 | AA111: 63356 | AB111: 70289 | AC111: 70483 | AD111: 64109 | AE111: 68836 | AF111: 90985 | AG111: 125687
A112: Loss (gain) on put option | Q112: 0 | R112: -3768 | S112: 727 | T112: 1111 | U112: 838 | V112: 842 | W112: 250 | X112: 0 | Y112: 0
A113: Loss (gain) on investments | Q113: 3887 | R113: 4526 | S113: 43 | T113: -1897 | U113: -3553 | V113: -801 | W113: -250 | X113: 0 | Y113: 0
A114: Non-cash lease expense | AA114: 4087 | AB114: 3943 | AC114: 4107 | AD114: 7337 | AE114: 9043 | AF114: 13521 | AG114: 15398
A115: Loss on impairment of intangiles | AA115: 0 | AB115: 8700 | AC115: 0 | AD115: 2200 | AE115: 38700 | AF115: 127098 | AG115: 38411
A116: Gain on Bang Transaction | AE116: -45382 | AF116: 0 | AG116: 0
...

Sheet Monster Investment Analysis (2)
A1: Metric | B1: 2000 | C1: 2001 | D1: 2002 | E1: 2003 | F1: 2004 | G1: 2005 | H1: 2006 | I1: 2007 | J1: 2008 | K1: 2009 | L1: 2010 | M1: 2011 | N1: 2012 | O1: 2013 | P1: 2014 | Q1: 2015 | R1: 2016 | S1: 2017 | T1: 2018 | U1: 2019 | V1: 2020 | W1: 2021 | X1: 2022 | Y1: 2023 | Z1: 2024 | AA1: 2025
A3: Historical DuPont Analysis
A4: Net Income | B4: ='Monster Consolidated Statements'!H33 -> 3889.28 | C4: ='Monster Consolidated Statements'!I33 -> 3001.416 | D4: ='Monster Consolidated Statements'!J33 -> 3023.207 | E4: ='Monster Consolidated Statements'!K33 -> 5930.437 | F4: ='Monster Consolidated Statements'!L33 -> 20386.787 | G4: ='Monster Consolidated Statements'!M33 -> 65631.621 | H4: ='Monster Consolidated Statements'!N33 -> 97949 | I4: ='Monster Consolidated Statements'!O33 -> 149406 | ... AA4: ='Monster Consolidated Statements'!AG33 -> 1779082
A5: Revenue | B5: ='Monster Consolidated Statements'!H6 -> 79732.709 | C5: ='Monster Consolidated Statements'!I6 -> 92279.711 | D5: ='Monster Consolidated Statements'!J6 -> 92046.362 | E5: ='Monster Consolidated Statements'!K6 -> 110352.2 | F5: ='Monster Consolidated Statements'!L6 -> 180341.14 | G5: ='Monster Consolidated Statements'!M6 -> 348886.37 | H5: ='Monster Consolidated Statements'!N6 -> 605774 | I5: ='Monster Consolidated Statements'!O6 -> 904465 | ... AA5: ='Monster Consolidated Statements'!AG6 -> 8294343
A6: Average Total Assets | B6: =AVERAGE('Monster Consolidated Statements'!G71,'Monster Consolidated Statements'!H71) -> 33726.846 | C6: =AVERAGE('Monster Consolidated Statements'!H71,'Monster Consolidated Statements'!I71) -> 38653.011 | D6: =AVERAGE('Monster Consolidated Statements'!I71,'Monster Consolidated Statements'!J71) -> 39512.394 | E6: =AVERAGE('Monster Consolidated Statements'!J71,'Monster Consolidated Statements'!K71) -> 44230.266 | F6: =AVERAGE('Monster Consolidated Statements'!K71,'Monster Consolidated Statements'!L71) -> 65009.673 | G6: =AVERAGE('Monster Consolidated Statements'!L71,'Monster Consolidated Statements'!M71) -> 122955.95 | H6: =AVERAGE('Monster Consolidated Statements'!M71,'Monster Consolidated Statements'!N71) -> 236130.79 | I6: =AVERAGE('Monster Consolidated Statements'!N71,'Monster Consolidated Statements'!O71) -> 426487.5 | ... AA6: =AVERAGE('Monster Consolidated Statements'!AF71,'Monster Consolidated Statements'!AG71) -> 8634517
A7: Average Stockholders' Equity | B7: =AVERAGE('Monster Consolidated Statements'!G100,'Monster Consolidated Statements'!H100) -> 20340.286 | C7: =AVERAGE('Monster Consolidated Statements'!H100,'Monster Consolidated Statements'!I100) -> 23694.122 | D7: =AVERAGE('Monster Consolidated Statements'!I100,'Monster Consolidated Statements'!J100) -> 26852.146 | E7: =AVERAGE('Monster Consolidated Statements'!J100,'Monster Consolidated Statements'!K100) -> 31710.161 | F7: =AVERAGE('Monster Consolidated Statements'!K100,'Monster Consolidated Statements'!L100) -> 46810.404 | G7: =AVERAGE('Monster Consolidated Statements'!L100,'Monster Consolidated Statements'!M100) -> 92040.114 | H7: =AVERAGE('Monster Consolidated Statements'!M100,'Monster Consolidated Statements'!N100) -> 175296.5 | I7: =AVERAGE('Monster Consolidated Statements'!N100,'Monster Consolidated Statements'!O100) -> 323625.5 | ... AA7: =AVERAGE('Monster Consolidated Statements'!AF100,'Monster Consolidated Statements'!AG100) -> 7105913
A8: Net Profit Margin | B8: =IFERROR(B4/B5,0) -> 0.048778977 | C8: =IFERROR(C4/C5,0) -> 0.032525199 | D8: =IFERROR(D4/D5,0) -> 0.032844394 | E8: =IFERROR(E4/E5,0) -> 0.053740997 | F8: =IFERROR(F4/F5,0) -> 0.11304568 | G8: =IFERROR(G4/G5,0) -> 0.18811747 | H8: =IFERROR(H4/H5,0) -> 0.16169231 | I8: =IFERROR(I4/I5,0) -> 0.16518715 | ... AA8: =IFERROR(AA4/AA5,0) -> 0.21449342
A9: Asset Turnover | B9: =IFERROR(B5/B6,0) -> 2.3640725 | C9: =IFERROR(C5/C6,0) -> 2.3873874 | D9: =IFERROR(D5/D6,0) -> 2.3295567 | E9: =IFERROR(E5/E6,0) -> 2.4949476 | F9: =IFERROR(F5/F6,0) -> 2.7740662 | G9: =IFERROR(G5/G6,0) -> 2.8374908 | H9: =IFERROR(H5/H6,0) -> 2.5654173 | I9: =IFERROR(I5/I6,0) -> 2.1207304 | ... AA9: =IFERROR(AA5/AA6,0) -> 0.96060301
A10: Equity Multiplier | B10: =IFERROR(B6/B7,0) -> 1.6581304 | C10: =IFERROR(C6/C7,0) -> 1.6313333 | D10: =IFERROR(D6/D7,0) -> 1.4714799 | E10: =IFERROR(E6/E7,0) -> 1.3948295 | F10: =IFERROR(F6/F7,0) -> 1.3887868 | G10: =IFERROR(G6/G7,0) -> 1.3358952 | H10: =IFERROR(H6/H7,0) -> 1.3470365 | I10: =IFERROR(I6/I7,0) -> 1.3178427 | ... AA10: =IFERROR(AA6/AA7,0) -> 1.2151172
A11: ROE (DuPont) | B11: =B8*B9*B10 -> 0.19121068 | C11: =C8*C9*C10 -> 0.12667344 | D11: =D8*D9*D10 -> 0.11258716 | E11: =E8*E9*E10 -> 0.18702008 | F11: =F8*F9*F10 -> 0.43551829 | G11: =G8*G9*G10 -> 0.71307626 | H11: =H8*H9*H10 -> 0.55876187 | I11: =I8*I9*I10 -> 0.46166325 | ... AA11: =AA8*AA9*AA10 -> 0.25036642
A12: ROE (Direct Check) | B12: =IFERROR(B4/B7,0) -> 0.19121068 | C12: =IFERROR(C4/C7,0) -> 0.12667344 | D12: =IFERROR(D4/D7,0) -> 0.11258716 | E12: =IFERROR(E4/E7,0) -> 0.18702008 | F12: =IFERROR(F4/F7,0) -> 0.43551829 | G12: =IFERROR(G4/G7,0) -> 0.71307626 | H12: =IFERROR(H4/H7,0) -> 0.55876187 | I12: =IFERROR(I4/I7,0) -> 0.46166325 | ... AA12: =IFERROR(AA4/AA7,0) -> 0.25036642
A14: ROIC + Incremental ROIC + ROIC vs WACC
A15: Operating Income (EBIT) | B15: ='Monster Consolidated Statements'!H23 -> 6900.332 | C15: ='Monster Consolidated Statements'!I23 -> 5550.904 | D15: ='Monster Consolidated Statements'!J23 -> 5292.893 | E15: ='Monster Consolidated Statements'!K23 -> 9826.128 | F15: ='Monster Consolidated Statements'!L23 -> 33886.185 | G15: ='Monster Consolidated Statements'!M23 -> 103443.35 | H15: ='Monster Consolidated Statements'!N23 -> 158579 | I15: ='Monster Consolidated Statements'!O23 -> 230986 | ... AA15: ='Monster Consolidated Statements'!AG23 -> 2419354
A16: Effective Tax Rate | B16: =IFERROR('Monster Consolidated Statements'!H32/'Monster Consolidated Statements'!H29,0) -> 0.40213359 | C16: =IFERROR('Monster Consolidated Statements'!I32/'Monster Consolidated Statements'!I29,0) -> 0.40143086 | D16: =IFERROR('Monster Consolidated Statements'!J32/'Monster Consolidated Statements'!J29,0) -> 0.40243225 | E16: =IFERROR('Monster Consolidated Statements'!K32/'Monster Consolidated Statements'!K29,0) -> 0.39197056 | F16: =IFERROR('Monster Consolidated Statements'!L32/'Monster Consolidated Statements'!L29,0) -> 0.39762828 | G16: =IFERROR('Monster Consolidated Statements'!M32/'Monster Consolidated Statements'!M29,0) -> 0.37462534 | H16: =IFERROR('Monster Consolidated Statements'!N32/'Monster Consolidated Statements'!N29,0) -> 0.39626724 | I16: =IFERROR('Monster Consolidated Statements'!O32/'Monster Consolidated Statements'!O29,0) -> 0.37684146 | ... AA16: =IFERROR('Monster Consolidated Statements'!AG32/'Monster Consolidated Statements'!AG29,0) -> 0.24492918
A17: NOPAT | B17: =B15*(1-B16) -> 4125.4767 | C17: =C15*(1-C16) -> 3322.5998 | D17: =D15*(1-D16) -> 3162.8622 | E17: =E15*(1-E16) -> 5974.5751 | F17: =F15*(1-F16) -> 20412.079 | G17: =G15*(1-G16) -> 64690.849 | H17: =H15*(1-H16) -> 95739.338 | I17: =I15*(1-I16) -> 143940.9 | ... AA17: =AA15*(1-AA16) -> 1826783.6
A18: Total Debt | B18: =SUM('Monster Consolidated Statements'!H74,'Monster Consolidated Statements'!H83,'Monster Consolidated Statements'!H87) -> 9966.611 | C18: =SUM('Monster Consolidated Statements'!I74,'Monster Consolidated Statements'!I83,'Monster Consolidated Statements'!I87) -> 6188.977 | D18: =SUM('Monster Consolidated Statements'!J74,'Monster Consolidated Statements'!J83,'Monster Consolidated Statements'!J87) -> 3836.78 | E18: =SUM('Monster Consolidated Statements'!K74,'Monster Consolidated Statements'!K83,'Monster Consolidated Statements'!K87) -> 602.335 | F18: =SUM('Monster Consolidated Statements'!L74,'Monster Consolidated Statements'!L83,'Monster Consolidated Statements'!L87) -> 583.852 | G18: =SUM('Monster Consolidated Statements'!M74,'Monster Consolidated Statements'!M83,'Monster Consolidated Statements'!M87) -> 525.344 | H18: =SUM('Monster Consolidated Statements'!N74,'Monster Consolidated Statements'!N83,'Monster Consolidated Statements'!N87) -> 303 | I18: =SUM('Monster Consolidated Statements'!O74,'Monster Consolidated Statements'!O83,'Monster Consolidated Statements'!O87) -> 663 | ... AA18: =SUM('Monster Consolidated Statements'!AG74,'Monster Consolidated Statements'!AG83,'Monster Consolidated Statements'!AG87) -> 0
A19: Invested Capital | B19: =B18+'Monster Consolidated Statements'!H100-'Monster Consolidated Statements'!H49-'Monster Consolidated Statements'!H50 -> 31890.642 | C19: =C18+'Monster Consolidated Statements'!I100-'Monster Consolidated Statements'!I49-'Monster Consolidated Statements'!I50 -> 31274.869 | D19: =D18+'Monster Consolidated Statements'!J100-'Monster Consolidated Statements'!J49-'Monster Consolidated Statements'!J50 -> 31669.604 | E19: =E18+'Monster Consolidated Statements'!K100-'Monster Consolidated Statements'!K49-'Monster Consolidated Statements'!K50 -> 34553.128 | F19: =F18+'Monster Consolidated Statements'!L100-'Monster Consolidated Statements'!L49-'Monster Consolidated Statements'!L50 -> 38178.962 | G19: =G18+'Monster Consolidated Statements'!M100-'Monster Consolidated Statements'!M49-'Monster Consolidated Statements'!M50 -> 52519.395 | H19: =H18+'Monster Consolidated Statements'!N100-'Monster Consolidated Statements'!N49-'Monster Consolidated Statements'!N50 -> 88591 | I19: =I18+'Monster Consolidated Statements'!O100-'Monster Consolidated Statements'!O49-'Monster Consolidated Statements'!O50 -> 347265 | ... AA19: =AA18+'Monster Consolidated Statements'!AG100-'Monster Consolidated Statements'!AG49-'Monster Consolidated Statements'!AG50 -> 5488907
A20: Average Invested Capital | B20: =AVERAGE(SUM('Monster Consolidated Statements'!G74,'Monster Consolidated Statements'!G83,'Monster Consolidated Statements'!G87)+'Monster Consolidated Statements'!G100-'Monster Consolidated Statements'!G49-'Monster Consolidated Statements'!G50,B19) -> 25136.79 | C20: =AVERAGE(SUM('Monster Consolidated Statements'!H74,'Monster Consolidated Statements'!H83,'Monster Consolidated Statements'!H87)+'Monster Consolidated Statements'!H100-'Monster Consolidated Statements'!H49-'Monster Consolidated Statements'!H50,C19) -> 31582.755 | D20: =AVERAGE(SUM('Monster Consolidated Statements'!I74,'Monster Consolidated Statements'!I83,'Monster Consolidated Statements'!I87)+'Monster Consolidated Statements'!I100-'Monster Consolidated Statements'!I49-'Monster Consolidated Statements'!I50,D19) -> 31472.236 | E20: =AVERAGE(SUM('Monster Consolidated Statements'!J74,'Monster Consolidated Statements'!J83,'Monster Consolidated Statements'!J87)+'Monster Consolidated Statements'!J100-'Monster Consolidated Statements'!J49-'Monster Consolidated Statements'!J50,E19) -> 33111.366 | F20: =AVERAGE(SUM('Monster Consolidated Statements'!K74,'Monster Consolidated Statements'!K83,'Monster Consolidated Statements'!K87)+'Monster Consolidated Statements'!K100-'Monster Consolidated Statements'!K49-'Monster Consolidated Statements'!K50,F19) -> 36366.045 | G20: =AVERAGE(SUM('Monster Consolidated Statements'!L74,'Monster Consolidated Statements'!L83,'Monster Consolidated Statements'!L87)+'Monster Consolidated Statements'!L100-'Monster Consolidated Statements'!L49-'Monster Consolidated Statements'!L50,G19) -> 45349.178 | H20: =AVERAGE(SUM('Monster Consolidated Statements'!M74,'Monster Consolidated Statements'!M83,'Monster Consolidated Statements'!M87)+'Monster Consolidated Statements'!M100-'Monster Consolidated Statements'!M49-'Monster Consolidated Statements'!M50,H19) -> 70555.197 | I20: =AVERAGE(SUM('Monster Consolidated Statements'!N74,'Monster Consolidated Statements'!N83,'Monster Consolidated Statements'!N87)+'Monster Consolidated Statements'!N100-'Monster Consolidated Statements'!N49-'Monster Consolidated Statements'!N50,I19) -> 217928 | ... AA20: =AVERAGE(SUM('Monster Consolidated Statements'!AF74,'Monster Consolidated Statements'!AF83,'Monster Consolidated Statements'!AF87)+'Monster Consolidated Statements'!AF100-'Monster Consolidated Statements'!AF49-'Monster Consolidated Statements'!AF50,AA19) -> 5143644.5
A21: ROIC | B21: =IFERROR(B17/B20,0) -> 0.16412106 | C21: =IFERROR(C17/C20,0) -> 0.10520297 | D21: =IFERROR(D17/D20,0) -> 0.1004969 | E21: =IFERROR(E17/E20,0) -> 0.1804388 | F21: =IFERROR(F17/F20,0) -> 0.561295 | G21: =IFERROR(G17/G20,0) -> 1.4265054 | H21: =IFERROR(H17/H20,0) -> 1.3569424 | I21: =IFERROR(I17/I20,0) -> 0.6604975 | ... AA21: =IFERROR(AA17/AA20,0) -> 0.35515355
A22: Incremental ROIC | B22: =IFERROR((B17-('Monster Consolidated Statements'!G23*(1-IFERROR('Monster Consolidated Statements'!G32/'Monster Consolidated Statements'!G29,0))))/(B19-(SUM('Monster Consolidated Statements'!G74,'Monster Consolidated Statements'!G83,'Monster Consolidated Statements'!G87)+'Monster Consolidated Statements'!G100-'Monster Consolidated Statements'!G49-'Monster Consolidated Statements'!G50)),0) -> -0.021131346 | C22: =IFERROR((C17-B17)/(C19-B19),0) -> 1.303852 | D22: =IFERROR((D17-C17)/(D19-C19),0) -> -0.4046706 | E22: =IFERROR((E17-D17)/(E19-D19),0) -> 0.97509606 | F22: =IFERROR((F17-E17)/(F19-E19),0) -> 3.9818437 | G22: =IFERROR((G17-F17)/(G19-F19),0) -> 3.087687 | H22: =IFERROR((H17-G17)/(H19-G19),0) -> 0.86074599 | I22: =IFERROR((I17-H17)/(I19-H19),0) -> 0.18634096 | J22: =IFERROR((J17-I17)/(J19-I19),0) -> 0.23372376 | ... AA22: =IFERROR((AA17-Z17)/(AA19-Z19),0) -> 0.56781604
A24: Capital Allocation / Buyback Analysis
A25: Cash Flow from Operations | B25: ='Monster Consolidated Statements'!H135 -> -1122.84 | C25: ='Monster Consolidated Statements'!I135 -> 5202.706 | D25: ='Monster Consolidated Statements'!J135 -> 2726.669 | E25: ='Monster Consolidated Statements'!K135 -> 5484.414 | F25: ='Monster Consolidated Statements'!L135 -> 20050.517 | G25: ='Monster Consolidated Statements'!M135 -> 54649.436 | H25: ='Monster Consolidated Statements'!N135 -> 76414 | I25: ='Monster Consolidated Statements'!O135 -> 135451 | ... AA25: ='Monster Consolidated Statements'!AG135 -> 2098177
A26: PP&E CapEx | B26: =-'Monster Consolidated Statements'!H149 -> 1191.762 | C26: =-'Monster Consolidated Statements'!I149 -> 529.905 | D26: =-'Monster Consolidated Statements'!J149 -> 416.873 | E26: =-'Monster Consolidated Statements'!K149 -> 1627.49 | F26: =-'Monster Consolidated Statements'!L149 -> 1260.068 | G26: =-'Monster Consolidated Statements'!M149 -> 1519.76 | H26: =-'Monster Consolidated Statements'!N149 -> 2746 | I26: =-'Monster Consolidated Statements'!O149 -> 4108 | ... AA26: =-'Monster Consolidated Statements'!AG149 -> 132275
A27: Intangible CapEx | B27: =-'Monster Consolidated Statements'!H150 -> 6490.494 | C27: =-'Monster Consolidated Statements'!I150 -> 118.651 | D27: =-'Monster Consolidated Statements'!J150 -> 64.792 | E27: =-'Monster Consolidated Statements'!K150 -> 995.137 | F27: =-'Monster Consolidated Statements'!L150 -> 131.146 | G27: =-'Monster Consolidated Statements'!M150 -> 821.347 | H27: =-'Monster Consolidated Statements'!N150 -> 2155 | I27: =-'Monster Consolidated Statements'!O150 -> 2920 | ... AA27: =-'Monster Consolidated Statements'!AG150 -> 25254
A28: Free Cash Flow | B28: =B25-B26-B27 -> -8805.096 | C28: =C25-C26-C27 -> 4554.15 | D28: =D25-D26-D27 -> 2245.004 | E28: =E25-E26-E27 -> 2861.787 | F28: =F25-F26-F27 -> 18659.303 | G28: =G25-G26-G27 -> 52308.329 | H28: =H25-H26-H27 -> 71513 | I28: =I25-I26-I27 -> 128423 | ... AA28: =AA25-AA26-AA27 -> 1940648
A29: Acquisition Spend | B29: =-SUM('Monster Consolidated Statements'!H142,'Monster Consolidated Statements'!H147,'Monster Consolidated Statements'!H148) -> 0 | C29: =-SUM('Monster Consolidated Statements'!I142,'Monster Consolidated Statements'!I147,'Monster Consolidated Statements'!I148) -> 0 | D29: =-SUM('Monster Consolidated Statements'!J142,'Monster Consolidated Statements'!J147,'Monster Consolidated Statements'!J148) -> 0 | E29: =-SUM('Monster Consolidated Statements'!K142,'Monster Consolidated Statements'!K147,'Monster Consolidated Statements'!K148) -> 0 | F29: =-SUM('Monster Consolidated Statements'!L142,'Monster Consolidated Statements'!L147,'Monster Consolidated Statements'!L148) -> 0 | G29: =-SUM('Monster Consolidated Statements'!M142,'Monster Consolidated Statements'!M147,'Monster Consolidated Statements'!M148) -> 0 | H29: =-SUM('Monster Consolidated Statements'!N142,'Monster Consolidated Statements'!N147,'Monster Consolidated Statements'!N148) -> 0 | I29: =-SUM('Monster Consolidated Statements'!O142,'Monster Consolidated Statements'!O147,'Monster Consolidated Statements'!O148) -> 0 | ... AA29: =-SUM('Monster Consolidated Statements'!AG142,'Monster Consolidated Statements'!AG147,'Monster Consolidated Statements'!AG148) -> 0
A30: Share Repurchases | B30: =-'Monster Consolidated Statements'!H163 -> 814.545 | C30: =-'Monster Consolidated Statements'!I163 -> 0 | D30: =-'Monster Consolidated Statements'!J163 -> 0 | E30: =-'Monster Consolidated Statements'!K163 -> -748.43 | F30: =-'Monster Consolidated Statements'!L163 -> -1719.928 | G30: =-'Monster Consolidated Statements'!M163 -> -1167.76 | H30: =-'Monster Consolidated Statements'!N163 -> 27699 | I30: =-'Monster Consolidated Statements'!O163 -> 148 | ... AA30: =-'Monster Consolidated Statements'!AG163 -> 103646
A31: Buybacks / FCF | B31: =IFERROR(B30/B28,0) -> -0.092508361 | C31: =IFERROR(C30/C28,0) -> 0 | D31: =IFERROR(D30/D28,0) -> 0 | E31: =IFERROR(E30/E28,0) -> -0.2615254 | F31: =IFERROR(F30/F28,0) -> -0.092175362 | G31: =IFERROR(G30/G28,0) -> -0.022324552 | H31: =IFERROR(H30/H28,0) -> 0.38732818 | I31: =IFERROR(I30/I28,0) -> 0.0011524415 | ... AA31: =IFERROR(AA30/AA28,0) -> 0.053407934
A32: Debt Issuance | B32: ='Monster Consolidated Statements'!H157 -> 9204.471 | C32: ='Monster Consolidated Statements'!I157 -> 0 | D32: ='Monster Consolidated Statements'!J157 -> 0 | E32: ='Monster Consolidated Statements'!K157 -> 0 | F32: ='Monster Consolidated Statements'!L157 -> 0 | G32: ='Monster Consolidated Statements'!M157 -> 0 | H32: ='Monster Consolidated Statements'!N157 -> 0 | I32: ='Monster Consolidated Statements'!O157 -> 0 | ... AA32: ='Monster Consolidated Statements'!AG157 -> 0
A33: Debt Repayments | B33: =-SUM('Monster Consolidated Statements'!H158,'Monster Consolidated Statements'!H159) -> 1551.049 | C33: =-SUM('Monster Consolidated Statements'!I158,'Monster Consolidated Statements'!I159) -> 4432.101 | D33: =-SUM('Monster Consolidated Statements'!J158,'Monster Consolidated Statements'!J159) -> 2352.197 | E33: =-SUM('Monster Consolidated Statements'!K158,'Monster Consolidated Statements'!K159) -> 3234.445 | F33: =-SUM('Monster Consolidated Statements'!L158,'Monster Consolidated Statements'!L159) -> 422.385 | G33: =-SUM('Monster Consolidated Statements'!M158,'Monster Consolidated Statements'!M159) -> 1054.961 | H33: =-SUM('Monster Consolidated Statements'!N158,'Monster Consolidated Statements'!N159) -> 1176 | I33: =-SUM('Monster Consolidated Statements'!O158,'Monster Consolidated Statements'!O159) -> 910 | ... AA33: =-SUM('Monster Consolidated Statements'!AG158,'Monster Consolidated Statements'!AG159) -> 375000
A34: Diluted Weighted Average Shares | B34: ='Monster Consolidated Statements'!H42 -> 10405.703 | C34: ='Monster Consolidated Statements'!I42 -> 10314.904 | D34: ='Monster Consolidated Statements'!J42 -> 10339.604 | E34: ='Monster Consolidated Statements'!K42 -> 10762.157 | F34: ='Monster Consolidated Statements'!L42 -> 92667.291 | G34: ='Monster Consolidated Statements'!M42 -> 96578.425 | H34: ='Monster Consolidated Statements'!N42 -> 98586 | I34: ='Monster Consolidated Statements'!O42 -> 98874 | ... AA34: ='Monster Consolidated Statements'!AG42 -> 984451
A35: YoY Diluted Share Count Change | B35: =IFERROR(B34/'Monster Consolidated Statements'!G42-1,0) -> -0.0099804921 | C35: =IFERROR(C34/'Monster Consolidated Statements'!H42-1,0) -> -0.0087258881 | D35: =IFERROR(D34/'Monster Consolidated Statements'!I42-1,0) -> 0.0023945933 | E35: =IFERROR(E34/'Monster Consolidated Statements'!J42-1,0) -> 0.040867426 | F35: =IFERROR(F34/'Monster Consolidated Statements'!K42-1,0) -> 7.6104757 | G35: =IFERROR(G34/'Monster Consolidated Statements'!L42-1,0) -> 0.042206195 | H35: =IFERROR(H34/'Monster Consolidated Statements'!M42-1,0) -> 0.020786997 | I35: =IFERROR(I34/'Monster Consolidated Statements'!N42-1,0) -> 0.0029213073 | ... AA35: =IFERROR(AA34/'Monster Consolidated Statements'!AF42-1,0) -> -0.028285265
A36: Net Change in Cash | B36: ='Monster Consolidated Statements'!H167 -> -1878.49 | C36: ='Monster Consolidated Statements'!I167 -> 116.992 | D36: ='Monster Consolidated Statements'!J167 -> 290.263 | E36: ='Monster Consolidated Statements'!K167 -> 560.865 | F36: ='Monster Consolidated Statements'!L167 -> 2577.334 | G36: ='Monster Consolidated Statements'!M167 -> 57978.165 | H36: ='Monster Consolidated Statements'!N167 -> -26525 | I36: ='Monster Consolidated Statements'!O167 -> -22689 | ... AA36: ='Monster Consolidated Statements'!AG167 -> 554830
A37: FCF / Diluted Share | B37: =IFERROR(B28/B34,0) -> -0.84617983 | C37: =IFERROR(C28/C34,0) -> 0.44151162 | D37: =IFERROR(D28/D34,0) -> 0.21712669 | E37: =IFERROR(E28/E34,0) -> 0.26591203 | F37: =IFERROR(F28/F34,0) -> 0.20135803 | G37: =IFERROR(G28/G34,0) -> 0.54161506 | H37: =IFERROR(H28/H34,0) -> 0.72538697 | I37: =IFERROR(I28/I34,0) -> 1.2988551 | ... AA37: =IFERROR(AA28/AA34,0) -> 1.9712997
A39: Volume vs Price/Mix Revenue Bridge
A40: Revenue | B40: ='Monster Consolidated Statements'!H6 -> 79732.709 | C40: ='Monster Consolidated Statements'!I6 -> 92279.711 | D40: ='Monster Consolidated Statements'!J6 -> 92046.362 | E40: ='Monster Consolidated Statements'!K6 -> 110352.2 | F40: ='Monster Consolidated Statements'!L6 -> 180341.14 | G40: ='Monster Consolidated Statements'!M6 -> 348886.37 | H40: ='Monster Consolidated Statements'!N6 -> 605774 | I40: ='Monster Consolidated Statements'!O6 -> 904465 | ... AA40: ='Monster Consolidated Statements'!AG6 -> 8294343
A41: Revenue Growth | B41: =IFERROR(B40/'Monster Consolidated Statements'!G6-1,0) -> 0.10275513 | C41: =IFERROR(C40/'Monster Consolidated Statements'!H6-1,0) -> 0.1573633 | D41: =IFERROR(D40/'Monster Consolidated Statements'!I6-1,0) -> -0.002528714 | E41: =IFERROR(E40/'Monster Consolidated Statements'!J6-1,0) -> 0.19887624 | F41: =IFERROR(F40/'Monster Consolidated Statements'!K6-1,0) -> 0.63423241 | G41: =IFERROR(G40/'Monster Consolidated Statements'!L6-1,0) -> 0.93459116 | H41: =IFERROR(H40/'Monster Consolidated Statements'!M6-1,0) -> 0.73630746 | I41: =IFERROR(I40/'Monster Consolidated Statements'!N6-1,0) -> 0.49307332 | ... AA41: =IFERROR(AA40/'Monster Consolidated Statements'!AF6-1,0) -> 0.10698854
A42: Volume Growth | L42: 0.17272727 | M42: 0.27644186 | N42: 0.23233795 | O42: 0.090824865 | P42: 0.076494931 | Q42: 0.15251385 | R42: 0.16873801 | S42: 0.12150112 | T42: 0.14148634 | U42: 0.092200756 | V42: 0.12489917 | W42: 0.21516538 | X42: 0.14383779 | Y42: 0.096289318 | Z42: 0.10064726 | AA42: 0.13262892
A43: Price / Mix Contribution | L43: -0.027884615 | M43: 0.022749753 | N43: -0.017408124 | O43: -0.00098425197 | P43: 0.018719212 | Q43: -0.041586074 | R43: -0.04641776 | S43: -0.015873016 | T43: -0.0096774194 | U43: 0.010857763 | V43: -0.026852846 | W43: -0.0077262693 | X43: -0.0189099 | Y43: 0.02154195 | Z43: -0.043285239 | AA43: -0.016241299
A44: Data Availability | L44: =(1+L42)*(1+L43)-1 -> 0.14002622 | M44: =(1+M42)*(1+M43)-1 -> 0.3054806 | N44: =(1+N42)*(1+N43)-1 -> 0.21088526 | O44: =(1+O42)*(1+O43)-1 -> 0.089751219 | P44: =(1+P42)*(1+P43)-1 -> 0.096646068 | Q44: =(1+Q42)*(1+Q43)-1 -> 0.10458532 | R44: =(1+R42)*(1+R43)-1 -> 0.11448781 | S44: =(1+S42)*(1+S43)-1 -> 0.10369952 | ... AA44: =(1+AA42)*(1+AA43)-1 -> 0.11423356
A46: Gross → EBITDA → EBIT Margin Bridge
A47: Gross Profit | B47: ='Monster Consolidated Statements'!H10 -> 37086.032 | C47: ='Monster Consolidated Statements'!I10 -> 40824.504 | D47: ='Monster Consolidated Statements'!J10 -> 33243.693 | E47: ='Monster Consolidated Statements'!K10 -> 43775.028 | F47: ='Monster Consolidated Statements'!L10 -> 83466.385 | G47: ='Monster Consolidated Statements'!M10 -> 182543.25 | H47: ='Monster Consolidated Statements'!N10 -> 316594 | I47: ='Monster Consolidated Statements'!O10 -> 468013 | ... AA47: ='Monster Consolidated Statements'!AG10 -> 4632195
A48: Gross Margin | B48: =IFERROR(B47/'Monster Consolidated Statements'!H6,0) -> 0.46512946 | C48: =IFERROR(C47/'Monster Consolidated Statements'!I6,0) -> 0.44239956 | D48: =IFERROR(D47/'Monster Consolidated Statements'!J6,0) -> 0.36116249 | E48: =IFERROR(E47/'Monster Consolidated Statements'!K6,0) -> 0.3966847 | F48: =IFERROR(F47/'Monster Consolidated Statements'!L6,0) -> 0.462825 | G48: =IFERROR(G47/'Monster Consolidated Statements'!M6,0) -> 0.52321691 | H48: =IFERROR(H47/'Monster Consolidated Statements'!N6,0) -> 0.52262725 | I48: =IFERROR(I47/'Monster Consolidated Statements'!O6,0) -> 0.51744733 | ... AA48: =IFERROR(AA47/'Monster Consolidated Statements'!AG6,0) -> 0.55847642
A49: Depreciation & Amortization | B49: =SUM('Monster Consolidated Statements'!H106,'Monster Consolidated Statements'!H107) -> 685.735 | C49: =SUM('Monster Consolidated Statements'!I106,'Monster Consolidated Statements'!I107) -> 943.947 | D49: =SUM('Monster Consolidated Statements'!J106,'Monster Consolidated Statements'!J107) -> 548.452 | E49: =SUM('Monster Consolidated Statements'!K106,'Monster Consolidated Statements'!K107) -> 646.085 | F49: =SUM('Monster Consolidated Statements'!L106,'Monster Consolidated Statements'!L107) -> 843.459 | G49: =SUM('Monster Consolidated Statements'!M106,'Monster Consolidated Statements'!M107) -> 1078.731 | H49: =SUM('Monster Consolidated Statements'!N106,'Monster Consolidated Statements'!N107) -> 1594 | I49: =SUM('Monster Consolidated Statements'!O106,'Monster Consolidated Statements'!O107) -> 2184 | ... AA49: =SUM('Monster Consolidated Statements'!AG106,'Monster Consolidated Statements'!AG107) -> 114441
A50: EBITDA | B50: ='Monster Consolidated Statements'!H23+B49 -> 7586.067 | C50: ='Monster Consolidated Statements'!I23+C49 -> 6494.851 | D50: ='Monster Consolidated Statements'!J23+D49 -> 5841.345 | E50: ='Monster Consolidated Statements'!K23+E49 -> 10472.213 | F50: ='Monster Consolidated Statements'!L23+F49 -> 34729.644 | G50: ='Monster Consolidated Statements'!M23+G49 -> 104522.08 | H50: ='Monster Consolidated Statements'!N23+H49 -> 160173 | I50: ='Monster Consolidated Statements'!O23+I49 -> 233170 | ... AA50: ='Monster Consolidated Statements'!AG23+AA49 -> 2533795
A51: EBITDA Margin | B51: =IFERROR(B50/'Monster Consolidated Statements'!H6,0) -> 0.095143726 | C51: =IFERROR(C50/'Monster Consolidated Statements'!I6,0) -> 0.070382221 | D51: =IFERROR(D50/'Monster Consolidated Statements'!J6,0) -> 0.0634609 | E51: =IFERROR(E50/'Monster Consolidated Statements'!K6,0) -> 0.094898093 | F51: =IFERROR(F50/'Monster Consolidated Statements'!L6,0) -> 0.19257749 | G51: =IFERROR(G50/'Monster Consolidated Statements'!M6,0) -> 0.29958774 | H51: =IFERROR(H50/'Monster Consolidated Statements'!N6,0) -> 0.26441049 | I51: =IFERROR(I50/'Monster Consolidated Statements'!O6,0) -> 0.25779881 | ... AA51: =IFERROR(AA50/'Monster Consolidated Statements'!AG6,0) -> 0.30548471
A52: Operating Income (EBIT) | B52: ='Monster Consolidated Statements'!H23 -> 6900.332 | C52: ='Monster Consolidated Statements'!I23 -> 5550.904 | D52: ='Monster Consolidated Statements'!J23 -> 5292.893 | E52: ='Monster Consolidated Statements'!K23 -> 9826.128 | F52: ='Monster Consolidated Statements'!L23 -> 33886.185 | G52: ='Monster Consolidated Statements'!M23 -> 103443.35 | H52: ='Monster Consolidated Statements'!N23 -> 158579 | I52: ='Monster Consolidated Statements'!O23 -> 230986 | ... AA52: ='Monster Consolidated Statements'!AG23 -> 2419354
A53: EBIT Margin | B53: =IFERROR(B52/'Monster Consolidated Statements'!H6,0) -> 0.086543303 | C53: =IFERROR(C52/'Monster Consolidated Statements'!I6,0) -> 0.060153028 | D53: =IFERROR(D52/'Monster Consolidated Statements'!J6,0) -> 0.057502468 | E53: =IFERROR(E52/'Monster Consolidated Statements'!K6,0) -> 0.089043339 | F53: =IFERROR(F52/'Monster Consolidated Statements'!L6,0) -> 0.18790048 | G53: =IFERROR(G52/'Monster Consolidated Statements'!M6,0) -> 0.29649582 | H53: =IFERROR(H52/'Monster Consolidated Statements'!N6,0) -> 0.26177915 | I53: =IFERROR(I52/'Monster Consolidated Statements'!O6,0) -> 0.25538412 | ... AA53: =IFERROR(AA52/'Monster Consolidated Statements'!AG6,0) -> 0.29168724
A54: Freight-Out Costs / Revenue | B54: =IFERROR('Monster Consolidated Statements'!H15/'Monster Consolidated Statements'!H6,0) -> 0 | C54: =IFERROR('Monster Consolidated Statements'!I15/'Monster Consolidated Statements'!I6,0) -> 0 | D54: =IFERROR('Monster Consolidated Statements'!J15/'Monster Consolidated Statements'!J6,0) -> 0 | E54: =IFERROR('Monster Consolidated Statements'!K15/'Monster Consolidated Statements'!K6,0) -> 0 | F54: =IFERROR('Monster Consolidated Statements'!L15/'Monster Consolidated Statements'!L6,0) -> 0 | G54: =IFERROR('Monster Consolidated Statements'!M15/'Monster Consolidated Statements'!M6,0) -> 0 | H54: =IFERROR('Monster Consolidated Statements'!N15/'Monster Consolidated Statements'!N6,0) -> 0.05975826 | I54: =IFERROR('Monster Consolidated Statements'!O15/'Monster Consolidated Statements'!O6,0) -> 0.04510954 | ... AA54: =IFERROR('Monster Consolidated Statements'!AG15/'Monster Consolidated Statements'!AG6,0) -> 0.028573692
A55: Advertising & Promotional / Revenue | B55: =IFERROR('Monster Consolidated Statements'!H17/'Monster Consolidated Statements'!H6,0) -> 0 | C55: =IFERROR('Monster Consolidated Statements'!I17/'Monster Consolidated Statements'!I6,0) -> 0 | D55: =IFERROR('Monster Consolidated Statements'!J17/'Monster Consolidated Statements'!J6,0) -> 0 | E55: =IFERROR('Monster Consolidated Statements'!K17/'Monster Consolidated Statements'!K6,0) -> 0 | F55: =IFERROR('Monster Consolidated Statements'!L17/'Monster Consolidated Statements'!L6,0) -> 0 | G55: =IFERROR('Monster Consolidated Statements'!M17/'Monster Consolidated Statements'!M6,0) -> 0 | H55: =IFERROR('Monster Consolidated Statements'!N17/'Monster Consolidated Statements'!N6,0) -> 0.058932869 | I55: =IFERROR('Monster Consolidated Statements'!O17/'Monster Consolidated Statements'!O6,0) -> 0.07363469 | ... AA55: =IFERROR('Monster Consolidated Statements'!AG17/'Monster Consolidated Statements'!AG6,0) -> 0.072326404
A56: Other Expenses / Revenue | B56: =IFERROR('Monster Consolidated Statements'!H19/'Monster Consolidated Statements'!H6,0) -> 0.0046541878 | C56: =IFERROR('Monster Consolidated Statements'!I19/'Monster Consolidated Statements'!I6,0) -> 0.0054989444 | D56: =IFERROR('Monster Consolidated Statements'!J19/'Monster Consolidated Statements'!J6,0) -> 0.00059315761 | E56: =IFERROR('Monster Consolidated Statements'!K19/'Monster Consolidated Statements'!K6,0) -> 0.00056052351 | F56: =IFERROR('Monster Consolidated Statements'!L19/'Monster Consolidated Statements'!L6,0) -> 0.00040513774 | G56: =IFERROR('Monster Consolidated Statements'!M19/'Monster Consolidated Statements'!M6,0) -> 0.00020081897 | H56: =IFERROR('Monster Consolidated Statements'!N19/'Monster Consolidated Statements'!N6,0) -> 0.14215698 | I56: =IFERROR('Monster Consolidated Statements'!O19/'Monster Consolidated Statements'!O6,0) -> 0.14331898 | ... AA56: =IFERROR('Monster Consolidated Statements'!AG19/'Monster Consolidated Statements'!AG6,0) -> 0.16588909
A57: Total Operating Expenses / Revenue | B57: =IFERROR('Monster Consolidated Statements'!H21/'Monster Consolidated Statements'!H6,0) -> 0.37858616 | C57: =IFERROR('Monster Consolidated Statements'!I21/'Monster Consolidated Statements'!I6,0) -> 0.38224654 | D57: =IFERROR('Monster Consolidated Statements'!J21/'Monster Consolidated Statements'!J6,0) -> 0.30366002 | E57: =IFERROR('Monster Consolidated Statements'!K21/'Monster Consolidated Statements'!K6,0) -> 0.30764136 | F57: =IFERROR('Monster Consolidated Statements'!L21/'Monster Consolidated Statements'!L6,0) -> 0.27492452 | G57: =IFERROR('Monster Consolidated Statements'!M21/'Monster Consolidated Statements'!M6,0) -> 0.2267211 | H57: =IFERROR('Monster Consolidated Statements'!N21/'Monster Consolidated Statements'!N6,0) -> 0.26084811 | I57: =IFERROR('Monster Consolidated Statements'!O21/'Monster Consolidated Statements'!O6,0) -> 0.26206321 | ... AA57: =IFERROR('Monster Consolidated Statements'!AG21/'Monster Consolidated Statements'!AG6,0) -> 0.26678918
A59: Cash Conversion Cycle + NWC Efficiency
A60: Accounts Receivable | B60: ='Monster Consolidated Statements'!H51 -> 6584.486 | C60: ='Monster Consolidated Statements'!I51 -> 4412.422 | D60: ='Monster Consolidated Statements'!J51 -> 5949.402 | E60: ='Monster Consolidated Statements'!K51 -> 5372.983 | F60: ='Monster Consolidated Statements'!L51 -> 12650.055 | G60: ='Monster Consolidated Statements'!M51 -> 28751.588 | H60: ='Monster Consolidated Statements'!N51 -> 54624 | I60: ='Monster Consolidated Statements'!O51 -> 81497 | ... AA60: ='Monster Consolidated Statements'!AG51 -> 1618072
A61: Inventory | B61: ='Monster Consolidated Statements'!H53 -> 10907.895 | C61: ='Monster Consolidated Statements'!I53 -> 11956.68 | D61: ='Monster Consolidated Statements'!J53 -> 11643.734 | E61: ='Monster Consolidated Statements'!K53 -> 17643.786 | F61: ='Monster Consolidated Statements'!L53 -> 22406.054 | G61: ='Monster Consolidated Statements'!M53 -> 31399.628 | H61: ='Monster Consolidated Statements'!N53 -> 77013 | I61: ='Monster Consolidated Statements'!O53 -> 98140 | ... AA61: ='Monster Consolidated Statements'!AG53 -> 799623
A62: Accounts Payable | B62: ='Monster Consolidated Statements'!H75 -> 3681.956 | C62: ='Monster Consolidated Statements'!I75 -> 3919.741 | D62: ='Monster Consolidated Statements'!J75 -> 4732.261 | E62: ='Monster Consolidated Statements'!K75 -> 6521.402 | F62: ='Monster Consolidated Statements'!L75 -> 14542.753 | G62: ='Monster Consolidated Statements'!M75 -> 26613.663 | H62: ='Monster Consolidated Statements'!N75 -> 34362 | I62: ='Monster Consolidated Statements'!O75 -> 56766 | ... AA62: ='Monster Consolidated Statements'!AG75 -> 565974
A63: Days Sales Outstanding (DSO) | B63: =IFERROR(AVERAGE('Monster Consolidated Statements'!G51,'Monster Consolidated Statements'!H51)/'Monster Consolidated Statements'!H6*365,0) -> 23.657459 | C63: =IFERROR(AVERAGE('Monster Consolidated Statements'!H51,'Monster Consolidated Statements'!I51)/'Monster Consolidated Statements'!I6*365,0) -> 21.748396 | D63: =IFERROR(AVERAGE('Monster Consolidated Statements'!I51,'Monster Consolidated Statements'!J51)/'Monster Consolidated Statements'!J6*365,0) -> 20.544352 | E63: =IFERROR(AVERAGE('Monster Consolidated Statements'!J51,'Monster Consolidated Statements'!K51)/'Monster Consolidated Statements'!K6*365,0) -> 18.724913 | F63: =IFERROR(AVERAGE('Monster Consolidated Statements'!K51,'Monster Consolidated Statements'!L51)/'Monster Consolidated Statements'!L6*365,0) -> 18.238792 | G63: =IFERROR(AVERAGE('Monster Consolidated Statements'!L51,'Monster Consolidated Statements'!M51)/'Monster Consolidated Statements'!M6*365,0) -> 21.656908 | H63: =IFERROR(AVERAGE('Monster Consolidated Statements'!M51,'Monster Consolidated Statements'!N51)/'Monster Consolidated Statements'!N6*365,0) -> 25.118352 | I63: =IFERROR(AVERAGE('Monster Consolidated Statements'!N51,'Monster Consolidated Statements'!O51)/'Monster Consolidated Statements'!O6*365,0) -> 27.466052 | ... AA63: =IFERROR(AVERAGE('Monster Consolidated Statements'!AF51,'Monster Consolidated Statements'!AG51)/'Monster Consolidated Statements'!AG6*365,0) -> 62.482168
A64: Days Inventory Outstanding (DIO) | B64: =IFERROR(AVERAGE('Monster Consolidated Statements'!G53,'Monster Consolidated Statements'!H53)/'Monster Consolidated Statements'!H8*365,0) -> 89.020333 | C64: =IFERROR(AVERAGE('Monster Consolidated Statements'!H53,'Monster Consolidated Statements'!I53)/'Monster Consolidated Statements'!I8*365,0) -> 81.095484 | D64: =IFERROR(AVERAGE('Monster Consolidated Statements'!I53,'Monster Consolidated Statements'!J53)/'Monster Consolidated Statements'!J8*365,0) -> 73.24626 | E64: =IFERROR(AVERAGE('Monster Consolidated Statements'!J53,'Monster Consolidated Statements'!K53)/'Monster Consolidated Statements'!K8*365,0) -> 80.282363 | F64: =IFERROR(AVERAGE('Monster Consolidated Statements'!K53,'Monster Consolidated Statements'!L53)/'Monster Consolidated Statements'!L8*365,0) -> 75.448926 | G64: =IFERROR(AVERAGE('Monster Consolidated Statements'!L53,'Monster Consolidated Statements'!M53)/'Monster Consolidated Statements'!M8*365,0) -> 59.03182 | H64: =IFERROR(AVERAGE('Monster Consolidated Statements'!M53,'Monster Consolidated Statements'!N53)/'Monster Consolidated Statements'!N8*365,0) -> 68.418648 | I64: =IFERROR(AVERAGE('Monster Consolidated Statements'!N53,'Monster Consolidated Statements'!O53)/'Monster Consolidated Statements'!O8*365,0) -> 73.239262 | ... AA64: =IFERROR(AVERAGE('Monster Consolidated Statements'!AF53,'Monster Consolidated Statements'!AG53)/'Monster Consolidated Statements'!AG8*365,0) -> 76.58162
A65: Days Payables Outstanding (DPO) | B65: =IFERROR(AVERAGE('Monster Consolidated Statements'!G75,'Monster Consolidated Statements'!H75)/'Monster Consolidated Statements'!H8*365,0) -> 41.162323 | C65: =IFERROR(AVERAGE('Monster Consolidated Statements'!H75,'Monster Consolidated Statements'!I75)/'Monster Consolidated Statements'!I8*365,0) -> 26.961503 | D65: =IFERROR(AVERAGE('Monster Consolidated Statements'!I75,'Monster Consolidated Statements'!J75)/'Monster Consolidated Statements'!J8*365,0) -> 26.852359 | E65: =IFERROR(AVERAGE('Monster Consolidated Statements'!J75,'Monster Consolidated Statements'!K75)/'Monster Consolidated Statements'!K8*365,0) -> 30.848316 | F65: =IFERROR(AVERAGE('Monster Consolidated Statements'!K75,'Monster Consolidated Statements'!L75)/'Monster Consolidated Statements'!L8*365,0) -> 39.682252 | G65: =IFERROR(AVERAGE('Monster Consolidated Statements'!L75,'Monster Consolidated Statements'!M75)/'Monster Consolidated Statements'!M8*365,0) -> 45.153932 | H65: =IFERROR(AVERAGE('Monster Consolidated Statements'!M75,'Monster Consolidated Statements'!N75)/'Monster Consolidated Statements'!N8*365,0) -> 38.481425 | I65: =IFERROR(AVERAGE('Monster Consolidated Statements'!N75,'Monster Consolidated Statements'!O75)/'Monster Consolidated Statements'!O8*365,0) -> 38.104671 | ... AA65: =IFERROR(AVERAGE('Monster Consolidated Statements'!AF75,'Monster Consolidated Statements'!AG75)/'Monster Consolidated Statements'!AG8*365,0) -> 51.466159
A66: Cash Conversion Cycle | B66: =B63+B64-B65 -> 71.515469 | C66: =C63+C64-C65 -> 75.882378 | D66: =D63+D64-D65 -> 66.938253 | E66: =E63+E64-E65 -> 68.158961 | F66: =F63+F64-F65 -> 54.005465 | G66: =G63+G64-G65 -> 35.534795 | H66: =H63+H64-H65 -> 55.055575 | I66: =I63+I64-I65 -> 62.600643 | ... AA66: =AA63+AA64-AA65 -> 87.597629
A67: Operating NWC | B67: ='Monster Consolidated Statements'!H51+'Monster Consolidated Statements'!H53+'Monster Consolidated Statements'!H54-'Monster Consolidated Statements'!H75-'Monster Consolidated Statements'!H76 -> 14026.369 | C67: ='Monster Consolidated Statements'!I51+'Monster Consolidated Statements'!I53+'Monster Consolidated Statements'!I54-'Monster Consolidated Statements'!I75-'Monster Consolidated Statements'!I76 -> 12551.675 | D67: ='Monster Consolidated Statements'!J51+'Monster Consolidated Statements'!J53+'Monster Consolidated Statements'!J54-'Monster Consolidated Statements'!J75-'Monster Consolidated Statements'!J76 -> 13807.601 | E67: ='Monster Consolidated Statements'!K51+'Monster Consolidated Statements'!K53+'Monster Consolidated Statements'!K54-'Monster Consolidated Statements'!K75-'Monster Consolidated Statements'!K76 -> 15791.802 | F67: ='Monster Consolidated Statements'!L51+'Monster Consolidated Statements'!L53+'Monster Consolidated Statements'!L54-'Monster Consolidated Statements'!L75-'Monster Consolidated Statements'!L76 -> 19569.355 | G67: ='Monster Consolidated Statements'!M51+'Monster Consolidated Statements'!M53+'Monster Consolidated Statements'!M54-'Monster Consolidated Statements'!M75-'Monster Consolidated Statements'!M76 -> 31533.087 | H67: ='Monster Consolidated Statements'!N51+'Monster Consolidated Statements'!N53+'Monster Consolidated Statements'!N54-'Monster Consolidated Statements'!N75-'Monster Consolidated Statements'!N76 -> 81557 | I67: ='Monster Consolidated Statements'!O51+'Monster Consolidated Statements'!O53+'Monster Consolidated Statements'!O54-'Monster Consolidated Statements'!O75-'Monster Consolidated Statements'!O76 -> 117607 | ... AA67: ='Monster Consolidated Statements'!AG51+'Monster Consolidated Statements'!AG53+'Monster Consolidated Statements'!AG54-'Monster Consolidated Statements'!AG75-'Monster Consolidated Statements'!AG76 -> 1649187
A68: Operating NWC / Revenue | B68: =IFERROR(B67/'Monster Consolidated Statements'!H6,0) -> 0.17591738 | C68: =IFERROR(C67/'Monster Consolidated Statements'!I6,0) -> 0.13601771 | D68: =IFERROR(D67/'Monster Consolidated Statements'!J6,0) -> 0.15000703 | E68: =IFERROR(E67/'Monster Consolidated Statements'!K6,0) -> 0.14310365 | F68: =IFERROR(F67/'Monster Consolidated Statements'!L6,0) -> 0.10851299 | G68: =IFERROR(G67/'Monster Consolidated Statements'!M6,0) -> 0.090382113 | H68: =IFERROR(H67/'Monster Consolidated Statements'!N6,0) -> 0.13463272 | I68: =IFERROR(I67/'Monster Consolidated Statements'!O6,0) -> 0.13002935 | ... AA68: =IFERROR(AA67/'Monster Consolidated Statements'!AG6,0) -> 0.19883275
A69: Δ Operating NWC / Δ Revenue | B69: =IFERROR((B67-('Monster Consolidated Statements'!G51+'Monster Consolidated Statements'!G53+'Monster Consolidated Statements'!G54-'Monster Consolidated Statements'!G75-'Monster Consolidated Statements'!G76))/('Monster Consolidated Statements'!H6-'Monster Consolidated Statements'!G6),0) -> 0.82235091 | C69: =IFERROR((C67-('Monster Consolidated Statements'!H51+'Monster Consolidated Statements'!H53+'Monster Consolidated Statements'!H54-'Monster Consolidated Statements'!H75-'Monster Consolidated Statements'!H76))/('Monster Consolidated Statements'!I6-'Monster Consolidated Statements'!H6),0) -> -0.11753357 | D69: =IFERROR((D67-('Monster Consolidated Statements'!I51+'Monster Consolidated Statements'!I53+'Monster Consolidated Statements'!I54-'Monster Consolidated Statements'!I75-'Monster Consolidated Statements'!I76))/('Monster Consolidated Statements'!J6-'Monster Consolidated Statements'!I6),0) -> -5.3821786 | E69: =IFERROR((E67-('Monster Consolidated Statements'!J51+'Monster Consolidated Statements'!J53+'Monster Consolidated Statements'!J54-'Monster Consolidated Statements'!J75-'Monster Consolidated Statements'!J76))/('Monster Consolidated Statements'!K6-'Monster Consolidated Statements'!J6),0) -> 0.10839173 | F69: =IFERROR((F67-('Monster Consolidated Statements'!K51+'Monster Consolidated Statements'!K53+'Monster Consolidated Statements'!K54-'Monster Consolidated Statements'!K75-'Monster Consolidated Statements'!K76))/('Monster Consolidated Statements'!L6-'Monster Consolidated Statements'!K6),0) -> 0.053973571 | G69: =IFERROR((G67-('Monster Consolidated Statements'!L51+'Monster Consolidated Statements'!L53+'Monster Consolidated Statements'!L54-'Monster Consolidated Statements'!L75-'Monster Consolidated Statements'!L76))/('Monster Consolidated Statements'!M6-'Monster Consolidated Statements'!L6),0) -> 0.070982323 | H69: =IFERROR((H67-('Monster Consolidated Statements'!M51+'Monster Consolidated Statements'!M53+'Monster Consolidated Statements'!M54-'Monster Consolidated Statements'!M75-'Monster Consolidated Statements'!M76))/('Monster Consolidated Statements'!N6-'Monster Consolidated Statements'!M6),0) -> 0.19473072 | I69: =IFERROR((I67-('Monster Consolidated Statements'!N51+'Monster Consolidated Statements'!N53+'Monster Consolidated Statements'!N54-'Monster Consolidated Statements'!N75-'Monster Consolidated Statements'!N76))/('Monster Consolidated Statements'!O6-'Monster Consolidated Statements'!N6),0) -> 0.12069329 | ... AA69: =IFERROR((AA67-('Monster Consolidated Statements'!AF51+'Monster Consolidated Statements'!AF53+'Monster Consolidated Statements'!AF54-'Monster Consolidated Statements'!AF75-'Monster Consolidated Statements'!AF76))/('Monster Consolidated Statements'!AG6-'Monster Consolidated Statements'!AF6),0) -> 0.337699
A71: CFO/NI and FCF/NI Earnings-Quality Analysis
A72: Cash Flow from Operations | B72: ='Monster Consolidated Statements'!H135 -> -1122.84 | C72: ='Monster Consolidated Statements'!I135 -> 5202.706 | D72: ='Monster Consolidated Statements'!J135 -> 2726.669 | E72: ='Monster Consolidated Statements'!K135 -> 5484.414 | F72: ='Monster Consolidated Statements'!L135 -> 20050.517 | G72: ='Monster Consolidated Statements'!M135 -> 54649.436 | H72: ='Monster Consolidated Statements'!N135 -> 76414 | I72: ='Monster Consolidated Statements'!O135 -> 135451 | ... AA72: ='Monster Consolidated Statements'!AG135 -> 2098177
A73: Net Income | B73: ='Monster Consolidated Statements'!H33 -> 3889.28 | C73: ='Monster Consolidated Statements'!I33 -> 3001.416 | D73: ='Monster Consolidated Statements'!J33 -> 3023.207 | E73: ='Monster Consolidated Statements'!K33 -> 5930.437 | F73: ='Monster Consolidated Statements'!L33 -> 20386.787 | G73: ='Monster Consolidated Statements'!M33 -> 65631.621 | H73: ='Monster Consolidated Statements'!N33 -> 97949 | I73: ='Monster Consolidated Statements'!O33 -> 149406 | ... AA73: ='Monster Consolidated Statements'!AG33 -> 1779082
A74: CFO / Net Income | B74: =IFERROR(B72/B73,0) -> -0.28870125 | C74: =IFERROR(C72/C73,0) -> 1.7334172 | D74: =IFERROR(D72/D73,0) -> 0.90191277 | E74: =IFERROR(E72/E73,0) -> 0.92479087 | F74: =IFERROR(F72/F73,0) -> 0.98350549 | G74: =IFERROR(G72/G73,0) -> 0.8326693 | H74: =IFERROR(H72/H73,0) -> 0.78014069 | I74: =IFERROR(I72/I73,0) -> 0.90659679 | ... AA74: =IFERROR(AA72/AA73,0) -> 1.1793594
A75: Free Cash Flow | B75: ='Monster Consolidated Statements'!H135+'Monster Consolidated Statements'!H149+'Monster Consolidated Statements'!H150 -> -8805.096 | C75: ='Monster Consolidated Statements'!I135+'Monster Consolidated Statements'!I149+'Monster Consolidated Statements'!I150 -> 4554.15 | D75: ='Monster Consolidated Statements'!J135+'Monster Consolidated Statements'!J149+'Monster Consolidated Statements'!J150 -> 2245.004 | E75: ='Monster Consolidated Statements'!K135+'Monster Consolidated Statements'!K149+'Monster Consolidated Statements'!K150 -> 2861.787 | F75: ='Monster Consolidated Statements'!L135+'Monster Consolidated Statements'!L149+'Monster Consolidated Statements'!L150 -> 18659.303 | G75: ='Monster Consolidated Statements'!M135+'Monster Consolidated Statements'!M149+'Monster Consolidated Statements'!M150 -> 52308.329 | H75: ='Monster Consolidated Statements'!N135+'Monster Consolidated Statements'!N149+'Monster Consolidated Statements'!N150 -> 71513 | I75: ='Monster Consolidated Statements'!O135+'Monster Consolidated Statements'!O149+'Monster Consolidated Statements'!O150 -> 128423 | ... AA75: ='Monster Consolidated Statements'!AG135+'Monster Consolidated Statements'!AG149+'Monster Consolidated Statements'!AG150 -> 1940648
A76: FCF / Net Income | B76: =IFERROR(B75/B73,0) -> -2.2639399 | C76: =IFERROR(C75/C73,0) -> 1.5173338 | D76: =IFERROR(D75/D73,0) -> 0.74259024 | E76: =IFERROR(E75/E73,0) -> 0.48255921 | F76: =IFERROR(F75/F73,0) -> 0.91526453 | G76: =IFERROR(G75/G73,0) -> 0.79699889 | H76: =IFERROR(H75/H73,0) -> 0.73010444 | I76: =IFERROR(I75/I73,0) -> 0.85955718 | ... AA76: =IFERROR(AA75/AA73,0) -> 1.0908143
